Workbook

Sheet Dashboard
A1: Vendor Master & AP Data Governance - Dashboard
A2: Finance Operations | Synthetic data | All KPIs are live formulas
A3: Vendor master KPI | B3: Value
A4: Raw vendor records | B4: =COUNTA(Vendor_Master_Raw!A2:A229) -> 228
A5: Golden (unique) vendors | B5: =COUNTA(Vendor_Master_Golden!A2:A208) -> 207
A6: Duplicate records merged | B6: =B4-B5 -> 21
A7: Avg DQ pass % (before) | B7: =DQ_Scorecard!E13 -> 0.77741228
A8: Avg DQ pass % (after) | B8: =DQ_Scorecard!H13 -> 0.91727053
A9: Vendors needing steward action | B9: =COUNTA(Steward_Queue!A2:A86) -> 85
A10: High-priority steward cases | B10: =COUNTIF(Steward_Queue!F2:F86,"High") -> 71
A11: Near-duplicate pairs to review | B11: =COUNTA(Duplicate_Review!A2:A10) -> 9
A13: AP invoice KPI | B13: Count | C13: Amount (INR)
A14: Total invoices | B14: =COUNTA(AP_Invoices_Recon!A2:A511) -> 510 | C14: =SUM(AP_Invoices_Recon!D2:D511) -> 47492000
A15: Orphan vendor ID (not in master) | B15: =COUNTIF(AP_Invoices_Recon!I2:I511,"Orphan Vendor ID") -> 10 | C15: =SUMIFS(AP_Invoices_Recon!D2:D511,AP_Invoices_Recon!I2:I511,"Orphan Vendor ID") -> 803600
A16: Invoices on inactive vendors | B16: =COUNTIF(AP_Invoices_Recon!I2:I511,"Inactive Vendor") -> 65 | C16: =SUMIFS(AP_Invoices_Recon!D2:D511,AP_Invoices_Recon!I2:I511,"Inactive Vendor") -> 6245900
A17: Duplicate invoices (after MDM) | B17: =COUNTIF(AP_Invoices_Recon!L2:L511,"Duplicate") -> 12 | C17: =SUMIFS(AP_Invoices_Recon!D2:D511,AP_Invoices_Recon!L2:L511,"Duplicate") -> 997600
A18: of which duplicate already Paid | B18: =COUNTIFS(AP_Invoices_Recon!L2:L511,"Duplicate",AP_Invoices_Recon!E2:E511,"Paid") -> 6 | C18: =SUMIFS(AP_Invoices_Recon!D2:D511,AP_Invoices_Recon!L2:L511,"Duplicate",AP_Invoices_Recon!E2:E511,"Paid") -> 599500
A19: of which still Pending (stoppable) | B19: =COUNTIFS(AP_Invoices_Recon!L2:L511,"Duplicate",AP_Invoices_Recon!E2:E511,"Pending") -> 6 | C19: =SUMIFS(AP_Invoices_Recon!D2:D511,AP_Invoices_Recon!L2:L511,"Duplicate",AP_Invoices_Recon!E2:E511,"Pending") -> 398100
A20: Duplicates found ONLY after vendor merge | B20: =COUNTIF(AP_Invoices_Recon!M2:M511,"Yes") -> 6 | C20: =SUMIFS(AP_Invoices_Recon!D2:D511,AP_Invoices_Recon!M2:M511,"Yes") -> 555400

Sheet DQ_Scorecard
A1: Vendor Master Data Quality Scorecard - Before vs After
A2: All figures are live formulas over Vendor_Master_Raw (before) and Vendor_Master_Golden (after).
A4: Rule | B4: Check column | C4: Records (Before) | D4: Valid (Before) | E4: Pass % (Before) | F4: Records (After) | G4: Valid (After) | H4: Pass % (After) | I4: Improvement (pts) | J4: Open issues (After)
A5: PAN | B5: PAN_Check | C5: =COUNTA(Vendor_Master_Raw!$A$2:$A$229) -> 228 | D5: =COUNTIF(Vendor_Master_Raw!$M$2:$M$229,"Valid") -> 190 | E5: =IF(C5=0,0,D5/C5) -> 0.83333333 | F5: =COUNTA(Vendor_Master_Golden!$A$2:$A$208) -> 207 | G5: =COUNTIF(Vendor_Master_Golden!$M$2:$M$208,"Valid") -> 183 | H5: =IF(F5=0,0,G5/F5) -> 0.88405797 | I5: =(H5-E5)*100 -> 5.0724638 | J5: =F5-G5 -> 24
A6: GSTIN | B6: GSTIN_Check | C6: =COUNTA(Vendor_Master_Raw!$A$2:$A$229) -> 228 | D6: =COUNTIF(Vendor_Master_Raw!$N$2:$N$229,"Valid") -> 166 | E6: =IF(C6=0,0,D6/C6) -> 0.72807018 | F6: =COUNTA(Vendor_Master_Golden!$A$2:$A$208) -> 207 | G6: =COUNTIF(Vendor_Master_Golden!$N$2:$N$208,"Valid") -> 155 | H6: =IF(F6=0,0,G6/F6) -> 0.74879227 | I6: =(H6-E6)*100 -> 2.0722095 | J6: =F6-G6 -> 52
A7: Email | B7: Email_Check | C7: =COUNTA(Vendor_Master_Raw!$A$2:$A$229) -> 228 | D7: =COUNTIF(Vendor_Master_Raw!$O$2:$O$229,"Valid") -> 209 | E7: =IF(C7=0,0,D7/C7) -> 0.91666667 | F7: =COUNTA(Vendor_Master_Golden!$A$2:$A$208) -> 207 | G7: =COUNTIF(Vendor_Master_Golden!$O$2:$O$208,"Valid") -> 190 | H7: =IF(F7=0,0,G7/F7) -> 0.9178744 | I7: =(H7-E7)*100 -> 0.12077295 | J7: =F7-G7 -> 17
A8: Phone | B8: Phone_Check | C8: =COUNTA(Vendor_Master_Raw!$A$2:$A$229) -> 228 | D8: =COUNTIF(Vendor_Master_Raw!$P$2:$P$229,"Valid") -> 211 | E8: =IF(C8=0,0,D8/C8) -> 0.9254386 | F8: =COUNTA(Vendor_Master_Golden!$A$2:$A$208) -> 207 | G8: =COUNTIF(Vendor_Master_Golden!$P$2:$P$208,"Valid") -> 196 | H8: =IF(F8=0,0,G8/F8) -> 0.9468599 | I8: =(H8-E8)*100 -> 2.1421307 | J8: =F8-G8 -> 11
A9: Bank Account | B9: Bank_Check | C9: =COUNTA(Vendor_Master_Raw!$A$2:$A$229) -> 228 | D9: =COUNTIF(Vendor_Master_Raw!$Q$2:$Q$229,"Valid") -> 216 | E9: =IF(C9=0,0,D9/C9) -> 0.94736842 | F9: =COUNTA(Vendor_Master_Golden!$A$2:$A$208) -> 207 | G9: =COUNTIF(Vendor_Master_Golden!$Q$2:$Q$208,"Valid") -> 197 | H9: =IF(F9=0,0,G9/F9) -> 0.95169082 | I9: =(H9-E9)*100 -> 0.43224002 | J9: =F9-G9 -> 10
A10: IFSC | B10: IFSC_Check | C10: =COUNTA(Vendor_Master_Raw!$A$2:$A$229) -> 228 | D10: =COUNTIF(Vendor_Master_Raw!$R$2:$R$229,"Valid") -> 191 | E10: =IF(C10=0,0,D10/C10) -> 0.8377193 | F10: =COUNTA(Vendor_Master_Golden!$A$2:$A$208) -> 207 | G10: =COUNTIF(Vendor_Master_Golden!$R$2:$R$208,"Valid") -> 184 | H10: =IF(F10=0,0,G10/F10) -> 0.88888889 | I10: =(H10-E10)*100 -> 5.1169591 | J10: =F10-G10 -> 23
A11: Country | B11: Country_Check | C11: =COUNTA(Vendor_Master_Raw!$A$2:$A$229) -> 228 | D11: =COUNTIF(Vendor_Master_Raw!$S$2:$S$229,"Valid") -> 163 | E11: =IF(C11=0,0,D11/C11) -> 0.71491228 | F11: =COUNTA(Vendor_Master_Golden!$A$2:$A$208) -> 207 | G11: =COUNTIF(Vendor_Master_Golden!$S$2:$S$208,"Valid") -> 207 | H11: =IF(F11=0,0,G11/F11) -> 1 | I11: =(H11-E11)*100 -> 28.508772 | J11: =F11-G11 -> 0
A12: Payment Terms | B12: Terms_Check | C12: =COUNTA(Vendor_Master_Raw!$A$2:$A$229) -> 228 | D12: =COUNTIF(Vendor_Master_Raw!$T$2:$T$229,"Valid") -> 72 | E12: =IF(C12=0,0,D12/C12) -> 0.31578947 | F12: =COUNTA(Vendor_Master_Golden!$A$2:$A$208) -> 207 | G12: =COUNTIF(Vendor_Master_Golden!$T$2:$T$208,"Valid") -> 207 | H12: =IF(F12=0,0,G12/F12) -> 1 | I12: =(H12-E12)*100 -> 68.421053 | J12: =F12-G12 -> 0
A13: Average pass % | E13: =AVERAGE(E5:E12) -> 0.77741228 | H13: =AVERAGE(H5:H12) -> 0.91727053 | I13: =(H13-E13)*100 -> 13.985825 | J13: =SUM(J5:J12) -> 137
A14: Records with zero issues | D14: =COUNTIF(Vendor_Master_Raw!$U$2:$U$229,0) -> 27 | E14: =D14/C5 -> 0.11842105 | G14: =COUNTIF(Vendor_Master_Golden!$U$2:$U$208,0) -> 122 | H14: =G14/F5 -> 0.58937198 | I14: =(H14-E14)*100 -> 47.095093
A16: Note: 'After' improves on format/standardisation and duplicates. Missing or unverifiable PAN, GSTIN, bank and IFSC values are NOT invented - they go to Steward_Queue.

Sheet DQ_Rules
A1: Rule_ID | B1: Field / Area | C1: Validation Rule | D1: Severity | E1: Treatment
A2: R01 | B2: PAN | C2: Not blank; 10 chars: 5 capital letters + 4 digits + 1 capital letter | D2: High | E2: Uppercase automatically; blanks need vendor document
A3: R02 | B3: GSTIN | C3: 15 chars, 14th char = Z, characters 3-12 must equal the vendor's PAN. Fails as 'PAN Mismatch' if PAN is missing or different | D3: High | E3: Cannot be auto-fixed - confirm with vendor / GST portal
A4: R03 | B4: Email | C4: Not blank; contains @; a dot after the @; no spaces | D4: Medium | E4: Lowercase automatically; invalid needs vendor confirmation
A5: R04 | B5: Phone | C5: Digits only after removing space, hyphen, +; 10 digits (or 12 starting 91); first digit 6-9 | D5: Medium | E5: Re-formatted to +91 XXXXXXXXXX when valid
A6: R05 | B6: Bank_Account | C6: Not blank; digits only; 9-18 digits | D6: High | E6: Cannot be auto-fixed - needs bank proof
A7: R06 | B7: IFSC | C7: 11 chars: 4 capital letters + '0' + 6 characters | D7: High | E7: Uppercase automatically; invalid needs bank proof
A8: R07 | B8: Country | C8: Must equal 'India' (standard value) | D8: Low | E8: IN / INDIA / india mapped to India
A9: R08 | B9: Payment_Terms | C9: Standard values only: Net 15 / Net 30 / Net 45 / Net 60 | D9: Low | E9: 30D, NET30, 30 Days mapped to Net 30
A10: R09 | B10: Duplicate vendor | C10: Same normalised name (case, punctuation, Pvt/Private/Ltd/Limited/LLP ignored) OR same valid PAN | D10: High | E10: Auto-merged to one golden record; most complete record survives
A11: R10 | B11: Near-duplicate | C11: Name similarity >= 0.90 but no exact name/PAN match | D11: Medium | E11: Listed in Duplicate_Review - NOT auto-merged
A12: R11 | B12: Invoice vendor | C12: Invoice Vendor_ID must exist in vendor master | D12: High | E12: Orphan IDs routed to vendor onboarding
A13: R12 | B13: Duplicate invoice | C13: Same golden vendor + Invoice_No + amount appears more than once | D13: High | E13: Hold duplicate before payment run

Sheet Vendor_Master_Raw
A1: Vendor_ID | B1: Vendor_Name | C1: PAN | D1: GSTIN | E1: Email | F1: Phone | G1: Bank_Account | H1: IFSC | I1: Country | J1: Payment_Terms | K1: Status | L1: Created_Date | M1: PAN_Check | N1: GSTIN_Check | O1: Email_Check | P1: Phone_Check | Q1: Bank_Check | R1: IFSC_Check | S1: Country_Check | T1: Terms_Check | U1: Issue_Count | V1: Phone_Digits_(helper) | W1: Golden_Vendor_ID (from Python de-dup) | X1: Dup_Flag
A2: V1079 | B2: Falcon Landscaping Pvt Ltd | C2: NPMCL8617Z | D2: 19NPMCL8617Z1ZO | E2: accounts@falconlandscaping.in | F2: +91 91040 54115 | G2: 621815997062 | H2: KKBK0620153 | I2: IN | J2: net 30 | K2: Active | L2: 2025-03-19 | M2: =IF(TRIM(C2)="","Missing",IF(AND(LEN(TRIM(C2))=10,SUMPRODUCT(--(CODE(MID(TRIM(C2),{1,2,3,4,5,10},1))>=65),--(CODE(MID(TRIM(C2),{1,2,3,4,5,10},1))<=90))=6,ISNUMBER(--MID(TRIM(C2),6,4))),"Valid","Invalid")) -> Valid | N2: =IF(TRIM(D2)="","Missing",IF(AND(LEN(TRIM(D2))=15,MID(TRIM(D2),14,1)="Z"),IF(AND(TRIM(C2)<>"",MID(TRIM(D2),3,10)=TRIM(C2)),"Valid","PAN Mismatch"),"Invalid")) -> Valid | O2: =IF(TRIM(E2)="","Missing",IF(AND(ISNUMBER(FIND("@",E2)),ISERROR(FIND(" ",TRIM(E2))),IFERROR(FIND(".",E2,FIND("@",E2)),0)>0),"Valid","Invalid")) -> Valid | P2: =IF(TRIM(F2)="","Missing",IFERROR(IF(AND(ISNUMBER(--V2),OR(LEN(V2)=10,AND(LEN(V2)=12,LEFT(V2,2)="91")),VALUE(LEFT(RIGHT(V2,10),1))>=6),"Valid","Invalid"),"Invalid")) -> Valid | Q2: =IF(TRIM(G2)="","Missing",IFERROR(IF(AND(ISNUMBER(--TRIM(G2)),LEN(TRIM(G2))>=9,LEN(TRIM(G2))<=18,ISERROR(FIND(".",G2))),"Valid","Invalid"),"Invalid")) -> Valid | R2: =IF(TRIM(H2)="","Missing",IF(AND(LEN(TRIM(H2))=11,SUMPRODUCT(--(CODE(MID(TRIM(H2),{1,2,3,4},1))>=65),--(CODE(MID(TRIM(H2),{1,2,3,4},1))<=90))=4,MID(TRIM(H2),5,1)="0"),"Valid","Invalid")) -> Valid | S2: =IF(TRIM(I2)="","Missing",IF(EXACT(TRIM(I2),"India"),"Valid","Invalid")) -> Invalid | T2: =IF(TRIM(J2)="","Missing",IF(OR(EXACT(TRIM(J2),"Net 15"),EXACT(TRIM(J2),"Net 30"),EXACT(TRIM(J2),"Net 45"),EXACT(TRIM(J2),"Net 60")),"Valid","Invalid")) -> Invalid | U2: =COUNTIF(M2:T2,"<>Valid") -> 2 | V2: =SUBSTITUTE(SUBSTITUTE(SUBSTITUTE(F2," ",""),"-",""),"+","") -> 919104054115 | W2: V1079 | X2: =IF(COUNTIF($W$2:$W$229,W2)>1,"Duplicate","Unique") -> Duplicate
A3: V1109 | B3: Sunrise Housekeeping LLP | C3: QAXCW1184X | D3: 19QAXCW1184X1Z9 | E3: ACCOUNTS@SUNRISEHOUSEKEEPING.IN | F3: +91 84393 76904 | H3: KKBK0476973 | I3: India | J3: NET45 | K3: Active | L3: 2024-02-23 | M3: =IF(TRIM(C3)="","Missing",IF(AND(LEN(TRIM(C3))=10,SUMPRODUCT(--(CODE(MID(TRIM(C3),{1,2,3,4,5,10},1))>=65),--(CODE(MID(TRIM(C3),{1,2,3,4,5,10},1))<=90))=6,ISNUMBER(--MID(TRIM(C3),6,4))),"Valid","Invalid")) -> Valid | N3: =IF(TRIM(D3)="","Missing",IF(AND(LEN(TRIM(D3))=15,MID(TRIM(D3),14,1)="Z"),IF(AND(TRIM(C3)<>"",MID(TRIM(D3),3,10)=TRIM(C3)),"Valid","PAN Mismatch"),"Invalid")) -> Valid | O3: =IF(TRIM(E3)="","Missing",IF(AND(ISNUMBER(FIND("@",E3)),ISERROR(FIND(" ",TRIM(E3))),IFERROR(FIND(".",E3,FIND("@",E3)),0)>0),"Valid","Invalid")) -> Valid | P3: =IF(TRIM(F3)="","Missing",IFERROR(IF(AND(ISNUMBER(--V3),OR(LEN(V3)=10,AND(LEN(V3)=12,LEFT(V3,2)="91")),VALUE(LEFT(RIGHT(V3,10),1))>=6),"Valid","Invalid"),"Invalid")) -> Valid | Q3: =IF(TRIM(G3)="","Missing",IFERROR(IF(AND(ISNUMBER(--TRIM(G3)),LEN(TRIM(G3))>=9,LEN(TRIM(G3))<=18,ISERROR(FIND(".",G3))),"Valid","Invalid"),"Invalid")) -> Missing | R3: =IF(TRIM(H3)="","Missing",IF(AND(LEN(TRIM(H3))=11,SUMPRODUCT(--(CODE(MID(TRIM(H3),{1,2,3,4},1))>=65),--(CODE(MID(TRIM(H3),{1,2,3,4},1))<=90))=4,MID(TRIM(H3),5,1)="0"),"Valid","Invalid")) -> Valid | S3: =IF(TRIM(I3)="","Missing",IF(EXACT(TRIM(I3),"India"),"Valid","Invalid")) -> Valid | T3: =IF(TRIM(J3)="","Missing",IF(OR(EXACT(TRIM(J3),"Net 15"),EXACT(TRIM(J3),"Net 30"),EXACT(TRIM(J3),"Net 45"),EXACT(TRIM(J3),"Net 60")),"Valid","Invalid")) -> Invalid | U3: =COUNTIF(M3:T3,"<>Valid") -> 2 | V3: =SUBSTITUTE(SUBSTITUTE(SUBSTITUTE(F3," ",""),"-",""),"+","") -> 918439376904 | W3: V1109 | X3: =IF(COUNTIF($W$2:$W$229,W3)>1,"Duplicate","Unique") -> Unique
A4: V1054 | B4: Quantum Stationers Pvt Ltd | C4: IRSCS6423K | D4: 29IRSCS6423K1ZY | E4: accounts@quantumstationers.in | F4: 98547-77252 | G4: 872808010062 | H4: ICIC0120387 | I4: IN | J4: Net 45 | K4: Inactive | L4: 2024-06-02 | M4: =IF(TRIM(C4)="","Missing",IF(AND(LEN(TRIM(C4))=10,SUMPRODUCT(--(CODE(MID(TRIM(C4),{1,2,3,4,5,10},1))>=65),--(CODE(MID(TRIM(C4),{1,2,3,4,5,10},1))<=90))=6,ISNUMBER(--MID(TRIM(C4),6,4))),"Valid","Invalid")) -> Valid | N4: =IF(TRIM(D4)="","Missing",IF(AND(LEN(TRIM(D4))=15,MID(TRIM(D4),14,1)="Z"),IF(AND(TRIM(C4)<>"",MID(TRIM(D4),3,10)=TRIM(C4)),"Valid","PAN Mismatch"),"Invalid")) -> Valid | O4: =IF(TRIM(E4)="","Missing",IF(AND(ISNUMBER(FIND("@",E4)),ISERROR(FIND(" ",TRIM(E4))),IFERROR(FIND(".",E4,FIND("@",E4)),0)>0),"Valid","Invalid")) -> Valid | P4: =IF(TRIM(F4)="","Missing",IFERROR(IF(AND(ISNUMBER(--V4),OR(LEN(V4)=10,AND(LEN(V4)=12,LEFT(V4,2)="91")),VALUE(LEFT(RIGHT(V4,10),1))>=6),"Valid","Invalid"),"Invalid")) -> Valid | Q4: =IF(TRIM(G4)="","Missing",IFERROR(IF(AND(ISNUMBER(--TRIM(G4)),LEN(TRIM(G4))>=9,LEN(TRIM(G4))<=18,ISERROR(FIND(".",G4))),"Valid","Invalid"),"Invalid")) -> Valid | R4: =IF(TRIM(H4)="","Missing",IF(AND(LEN(TRIM(H4))=11,SUMPRODUCT(--(CODE(MID(TRIM(H4),{1,2,3,4},1))>=65),--(CODE(MID(TRIM(H4),{1,2,3,4},1))<=90))=4,MID(TRIM(H4),5,1)="0"),"Valid","Invalid")) -> Valid | S4: =IF(TRIM(I4)="","Missing",IF(EXACT(TRIM(I4),"India"),"Valid","Invalid")) -> Invalid | T4: =IF(TRIM(J4)="","Missing",IF(OR(EXACT(TRIM(J4),"Net 15"),EXACT(TRIM(J4),"Net 30"),EXACT(TRIM(J4),"Net 45"),EXACT(TRIM(J4),"Net 60")),"Valid","Invalid")) -> Valid | U4: =COUNTIF(M4:T4,"<>Valid") -> 1 | V4: =SUBSTITUTE(SUBSTITUTE(SUBSTITUTE(F4," ",""),"-",""),"+","") -> 9854777252 | W4: V1054 | X4: =IF(COUNTIF($W$2:$W$229,W4)>1,"Duplicate","Unique") -> Duplicate
A5: V1209 | B5: BLUEWAVE FACILITY SERVICES L.L.P. | C5: WYUCY2965O | D5: 07WYUCY2965O1ZI | E5: accounts@bluewavefacilityservices.in | F5: 79543-16526 | G5: 93008931734206 | H5: KKBK0694215 | I5: INDIA | J5: NET30 | K5: Active | L5: 2021-04-22 | M5: =IF(TRIM(C5)="","Missing",IF(AND(LEN(TRIM(C5))=10,SUMPRODUCT(--(CODE(MID(TRIM(C5),{1,2,3,4,5,10},1))>=65),--(CODE(MID(TRIM(C5),{1,2,3,4,5,10},1))<=90))=6,ISNUMBER(--MID(TRIM(C5),6,4))),"Valid","Invalid")) -> Valid | N5: =IF(TRIM(D5)="","Missing",IF(AND(LEN(TRIM(D5))=15,MID(TRIM(D5),14,1)="Z"),IF(AND(TRIM(C5)<>"",MID(TRIM(D5),3,10)=TRIM(C5)),"Valid","PAN Mismatch"),"Invalid")) -> Valid | O5: =IF(TRIM(E5)="","Missing",IF(AND(ISNUMBER(FIND("@",E5)),ISERROR(FIND(" ",TRIM(E5))),IFERROR(FIND(".",E5,FIND("@",E5)),0)>0),"Valid","Invalid")) -> Valid | P5: =IF(TRIM(F5)="","Missing",IFERROR(IF(AND(ISNUMBER(--V5),OR(LEN(V5)=10,AND(LEN(V5)=12,LEFT(V5,2)="91")),VALUE(LEFT(RIGHT(V5,10),1))>=6),"Valid","Invalid"),"Invalid")) -> Valid | Q5: =IF(TRIM(G5)="","Missing",IFERROR(IF(AND(ISNUMBER(--TRIM(G5)),LEN(TRIM(G5))>=9,LEN(TRIM(G5))<=18,ISERROR(FIND(".",G5))),"Valid","Invalid"),"Invalid")) -> Valid | R5: =IF(TRIM(H5)="","Missing",IF(AND(LEN(TRIM(H5))=11,SUMPRODUCT(--(CODE(MID(TRIM(H5),{1,2,3,4},1))>=65),--(CODE(MID(TRIM(H5),{1,2,3,4},1))<=90))=4,MID(TRIM(H5),5,1)="0"),"Valid","Invalid")) -> Valid | S5: =IF(TRIM(I5)="","Missing",IF(EXACT(TRIM(I5),"India"),"Valid","Invalid")) -> Invalid | T5: =IF(TRIM(J5)="","Missing",IF(OR(EXACT(TRIM(J5),"Net 15"),EXACT(TRIM(J5),"Net 30"),EXACT(TRIM(J5),"Net 45"),EXACT(TRIM(J5),"Net 60")),"Valid","Invalid")) -> Invalid | U5: =COUNTIF(M5:T5,"<>Valid") -> 2 | V5: =SUBSTITUTE(SUBSTITUTE(SUBSTITUTE(F5," ",""),"-",""),"+","") -> 7954316526 | W5: V1174 | X5: =IF(COUNTIF($W$2:$W$229,W5)>1,"Duplicate","Unique") -> Duplicate
A6: V1137 | B6: Redwood Electricals Private Limited | C6: UGKCG3448K | D6: 19UGKCG3448K | E6: accounts@redwoodelectricals.in | F6: +91 82241 09881 | G6: 858542493214 | H6: KKBK0587020 | I6: IN | J6: Net 60 | K6: Active | L6: 2019-07-26 | M6: =IF(TRIM(C6)="","Missing",IF(AND(LEN(TRIM(C6))=10,SUMPRODUCT(--(CODE(MID(TRIM(C6),{1,2,3,4,5,10},1))>=65),--(CODE(MID(TRIM(C6),{1,2,3,4,5,10},1))<=90))=6,ISNUMBER(--MID(TRIM(C6),6,4))),"Valid","Invalid")) -> Valid | N6: =IF(TRIM(D6)="","Missing",IF(AND(LEN(TRIM(D6))=15,MID(TRIM(D6),14,1)="Z"),IF(AND(TRIM(C6)<>"",MID(TRIM(D6),3,10)=TRIM(C6)),"Valid","PAN Mismatch"),"Invalid")) -> Invalid | O6: =IF(TRIM(E6)="","Missing",IF(AND(ISNUMBER(FIND("@",E6)),ISERROR(FIND(" ",TRIM(E6))),IFERROR(FIND(".",E6,FIND("@",E6)),0)>0),"Valid","Invalid")) -> Valid | P6: =IF(TRIM(F6)="","Missing",IFERROR(IF(AND(ISNUMBER(--V6),OR(LEN(V6)=10,AND(LEN(V6)=12,LEFT(V6,2)="91")),VALUE(LEFT(RIGHT(V6,10),1))>=6),"Valid","Invalid"),"Invalid")) -> Valid | Q6: =IF(TRIM(G6)="","Missing",IFERROR(IF(AND(ISNUMBER(--TRIM(G6)),LEN(TRIM(G6))>=9,LEN(TRIM(G6))<=18,ISERROR(FIND(".",G6))),"Valid","Invalid"),"Invalid")) -> Valid | R6: =IF(TRIM(H6)="","Missing",IF(AND(LEN(TRIM(H6))=11,SUMPRODUCT(--(CODE(MID(TRIM(H6),{1,2,3,4},1))>=65),--(CODE(MID(TRIM(H6),{1,2,3,4},1))<=90))=4,MID(TRIM(H6),5,1)="0"),"Valid","Invalid")) -> Valid | S6: =IF(TRIM(I6)="","Missing",IF(EXACT(TRIM(I6),"India"),"Valid","Invalid")) -> Invalid | T6: =IF(TRIM(J6)="","Missing",IF(OR(EXACT(TRIM(J6),"Net 15"),EXACT(TRIM(J6),"Net 30"),EXACT(TRIM(J6),"Net 45"),EXACT(TRIM(J6),"Net 60")),"Valid","Invalid")) -> Valid | U6: =COUNTIF(M6:T6,"<>Valid") -> 2 | V6: =SUBSTITUTE(SUBSTITUTE(SUBSTITUTE(F6," ",""),"-",""),"+","") -> 918224109881 | W6: V1137 | X6: =IF(COUNTIF($W$2:$W$229,W6)>1,"Duplicate","Unique") -> Unique
A7: V1047 | B7: Nova Pest Control Private Limited | C7: YCUCS3802N | D7: 19YCUCS3802N1ZL | E7: accounts@novapestcontrol.in | F7: +91 97240 04991 | G7: 4788728743152 | H7: UTIB0420549 | I7: INDIA | J7: Net 30 | K7: Active | L7: 2023-07-19 | M7: =IF(TRIM(C7)="","Missing",IF(AND(LEN(TRIM(C7))=10,SUMPRODUCT(--(CODE(MID(TRIM(C7),{1,2,3,4,5,10},1))>=65),--(CODE(MID(TRIM(C7),{1,2,3,4,5,10},1))<=90))=6,ISNUMBER(--MID(TRIM(C7),6,4))),"Valid","Invalid")) -> Valid | N7: =IF(TRIM(D7)="","Missing",IF(AND(LEN(TRIM(D7))=15,MID(TRIM(D7),14,1)="Z"),IF(AND(TRIM(C7)<>"",MID(TRIM(D7),3,10)=TRIM(C7)),"Valid","PAN Mismatch"),"Invalid")) -> Valid | O7: =IF(TRIM(E7)="","Missing",IF(AND(ISNUMBER(FIND("@",E7)),ISERROR(FIND(" ",TRIM(E7))),IFERROR(FIND(".",E7,FIND("@",E7)),0)>0),"Valid","Invalid")) -> Valid | P7: =IF(TRIM(F7)="","Missing",IFERROR(IF(AND(ISNUMBER(--V7),OR(LEN(V7)=10,AND(LEN(V7)=12,LEFT(V7,2)="91")),VALUE(LEFT(RIGHT(V7,10),1))>=6),"Valid","Invalid"),"Invalid")) -> Valid | Q7: =IF(TRIM(G7)="","Missing",IFERROR(IF(AND(ISNUMBER(--TRIM(G7)),LEN(TRIM(G7))>=9,LEN(TRIM(G7))<=18,ISERROR(FIND(".",G7))),"Valid","Invalid"),"Invalid")) -> Valid | R7: =IF(TRIM(H7)="","Missing",IF(AND(LEN(TRIM(H7))=11,SUMPRODUCT(--(CODE(MID(TRIM(H7),{1,2,3,4},1))>=65),--(CODE(MID(TRIM(H7),{1,2,3,4},1))<=90))=4,MID(TRIM(H7),5,1)="0"),"Valid","Invalid")) -> Valid | S7: =IF(TRIM(I7)="","Missing",IF(EXACT(TRIM(I7),"India"),"Valid","Invalid")) -> Invalid | T7: =IF(TRIM(J7)="","Missing",IF(OR(EXACT(TRIM(J7),"Net 15"),EXACT(TRIM(J7),"Net 30"),EXACT(TRIM(J7),"Net 45"),EXACT(TRIM(J7),"Net 60")),"Valid","Invalid")) -> Valid | U7: =COUNTIF(M7:T7,"<>Valid") -> 1 | V7: =SUBSTITUTE(SUBSTITUTE(SUBSTITUTE(F7," ",""),"-",""),"+","") -> 919724004991 | W7: V1047 | X7: =IF(COUNTIF($W$2:$W$229,W7)>1,"Duplicate","Unique") -> Unique
A8: V1180 | B8: Bluewave Water Solutions Limited | C8: KOVCH2788C | D8: 33KOVCH2788C1Z3 | E8: accounts@bluewavewatersolutions.in | F8: +91 67422 43864 | G8: 81081866179 | H8: SBIN0549180 | I8: India | J8: 15 Days | K8: Active | L8: 2024-03-10 | M8: =IF(TRIM(C8)="","Missing",IF(AND(LEN(TRIM(C8))=10,SUMPRODUCT(--(CODE(MID(TRIM(C8),{1,2,3,4,5,10},1))>=65),--(CODE(MID(TRIM(C8),{1,2,3,4,5,10},1))<=90))=6,ISNUMBER(--MID(TRIM(C8),6,4))),"Valid","Invalid")) -> Valid | N8: =IF(TRIM(D8)="","Missing",IF(AND(LEN(TRIM(D8))=15,MID(TRIM(D8),14,1)="Z"),IF(AND(TRIM(C8)<>"",MID(TRIM(D8),3,10)=TRIM(C8)),"Valid","PAN Mismatch"),"Invalid")) -> Valid | O8: =IF(TRIM(E8)="","Missing",IF(AND(ISNUMBER(FIND("@",E8)),ISERROR(FIND(" ",TRIM(E8))),IFERROR(FIND(".",E8,FIND("@",E8)),0)>0),"Valid","Invalid")) -> Valid | P8: =IF(TRIM(F8)="","Missing",IFERROR(IF(AND(ISNUMBER(--V8),OR(LEN(V8)=10,AND(LEN(V8)=12,LEFT(V8,2)="91")),VALUE(LEFT(RIGHT(V8,10),1))>=6),"Valid","Invalid"),"Invalid")) -> Valid | Q8: =IF(TRIM(G8)="","Missing",IFERROR(IF(AND(ISNUMBER(--TRIM(G8)),LEN(TRIM(G8))>=9,LEN(TRIM(G8))<=18,ISERROR(FIND(".",G8))),"Valid","Invalid"),"Invalid")) -> Valid | R8: =IF(TRIM(H8)="","Missing",IF(AND(LEN(TRIM(H8))=11,SUMPRODUCT(--(CODE(MID(TRIM(H8),{1,2,3,4},1))>=65),--(CODE(MID(TRIM(H8),{1,2,3,4},1))<=90))=4,MID(TRIM(H8),5,1)="0"),"Valid","Invalid")) -> Valid | S8: =IF(TRIM(I8)="","Missing",IF(EXACT(TRIM(I8),"India"),"Valid","Invalid")) -> Valid | T8: =IF(TRIM(J8)="","Missing",IF(OR(EXACT(TRIM(J8),"Net 15"),EXACT(TRIM(J8),"Net 30"),EXACT(TRIM(J8),"Net 45"),EXACT(TRIM(J8),"Net 60")),"Valid","Invalid")) -> Invalid | U8: =COUNTIF(M8:T8,"<>Valid") -> 1 | V8: =SUBSTITUTE(SUBSTITUTE(SUBSTITUTE(F8," ",""),"-",""),"+","") -> 916742243864 | W8: V1180 | X8: =IF(COUNTIF($W$2:$W$229,W8)>1,"Duplicate","Unique") -> Unique
A9: V1186 | B9: Titan Stationers Private Limited | C9: NZHCE6667Q | D9: 19NZHCE6667Q1ZX | E9: accounts@titanstationers.in | F9: +91 92081 15562 | G9: 06029084668455 | H9: HDFC0489267 | I9: INDIA | J9: 30 Days | K9: Active | L9: 2023-12-17 | M9: =IF(TRIM(C9)="","Missing",IF(AND(LEN(TRIM(C9))=10,SUMPRODUCT(--(CODE(MID(TRIM(C9),{1,2,3,4,5,10},1))>=65),--(CODE(MID(TRIM(C9),{1,2,3,4,5,10},1))<=90))=6,ISNUMBER(--MID(TRIM(C9),6,4))),"Valid","Invalid")) -> Valid | N9: =IF(TRIM(D9)="","Missing",IF(AND(LEN(TRIM(D9))=15,MID(TRIM(D9),14,1)="Z"),IF(AND(TRIM(C9)<>"",MID(TRIM(D9),3,10)=TRIM(C9)),"Valid","PAN Mismatch"),"Invalid")) -> Valid | O9: =IF(TRIM(E9)="","Missing",IF(AND(ISNUMBER(FIND("@",E9)),ISERROR(FIND(" ",TRIM(E9))),IFERROR(FIND(".",E9,FIND("@",E9)),0)>0),"Valid","Invalid")) -> Valid | P9: =IF(TRIM(F9)="","Missing",IFERROR(IF(AND(ISNUMBER(--V9),OR(LEN(V9)=10,AND(LEN(V9)=12,LEFT(V9,2)="91")),VALUE(LEFT(RIGHT(V9,10),1))>=6),"Valid","Invalid"),"Invalid")) -> Valid | Q9: =IF(TRIM(G9)="","Missing",IFERROR(IF(AND(ISNUMBER(--TRIM(G9)),LEN(TRIM(G9))>=9,LEN(TRIM(G9))<=18,ISERROR(FIND(".",G9))),"Valid","Invalid"),"Invalid")) -> Valid | R9: =IF(TRIM(H9)="","Missing",IF(AND(LEN(TRIM(H9))=11,SUMPRODUCT(--(CODE(MID(TRIM(H9),{1,2,3,4},1))>=65),--(CODE(MID(TRIM(H9),{1,2,3,4},1))<=90))=4,MID(TRIM(H9),5,1)="0"),"Valid","Invalid")) -> Valid | S9: =IF(TRIM(I9)="","Missing",IF(EXACT(TRIM(I9),"India"),"Valid","Invalid")) -> Invalid | T9: =IF(TRIM(J9)="","Missing",IF(OR(EXACT(TRIM(J9),"Net 15"),EXACT(TRIM(J9),"Net 30"),EXACT(TRIM(J9),"Net 45"),EXACT(TRIM(J9),"Net 60")),"Valid","Invalid")) -> Invalid | U9: =COUNTIF(M9:T9,"<>Valid") -> 2 | V9: =SUBSTITUTE(SUBSTITUTE(SUBSTITUTE(F9," ",""),"-",""),"+","") -> 919208115562 | W9: V1186 | X9: =IF(COUNTIF($W$2:$W$229,W9)>1,"Duplicate","Unique") -> Unique
A10: V1108 | B10: Western Water Solutions Private Limited | C10: ZCECP9611I | D10: 29ZCECP9611I1ZX | E10: accounts@westernwatersolutions.in | F10: 6669849027 | G10: 03843098839205 | H10: ICIC0021465 | I10: INDIA | J10: 60 Days | K10: Active | L10: 2021-03-31 | M10: =IF(TRIM(C10)="","Missing",IF(AND(LEN(TRIM(C10))=10,SUMPRODUCT(--(CODE(MID(TRIM(C10),{1,2,3,4,5,10},1))>=65),--(CODE(MID(TRIM(C10),{1,2,3,4,5,10},1))<=90))=6,ISNUMBER(--MID(TRIM(C10),6,4))),"Valid","Invalid")) -> Valid | N10: =IF(TRIM(D10)="","Missing",IF(AND(LEN(TRIM(D10))=15,MID(TRIM(D10),14,1)="Z"),IF(AND(TRIM(C10)<>"",MID(TRIM(D10),3,10)=TRIM(C10)),"Valid","PAN Mismatch"),"Invalid")) -> Valid | O10: =IF(TRIM(E10)="","Missing",IF(AND(ISNUMBER(FIND("@",E10)),ISERROR(FIND(" ",TRIM(E10))),IFERROR(FIND(".",E10,FIND("@",E10)),0)>0),"Valid","Invalid")) -> Valid | P10: =IF(TRIM(F10)="","Missing",IFERROR(IF(AND(ISNUMBER(--V10),OR(LEN(V10)=10,AND(LEN(V10)=12,LEFT(V10,2)="91")),VALUE(LEFT(RIGHT(V10,10),1))>=6),"Valid","Invalid"),"Invalid")) -> Valid | Q10: =IF(TRIM(G10)="","Missing",IFERROR(IF(AND(ISNUMBER(--TRIM(G10)),LEN(TRIM(G10))>=9,LEN(TRIM(G10))<=18,ISERROR(FIND(".",G10))),"Valid","Invalid"),"Invalid")) -> Valid | R10: =IF(TRIM(H10)="","Missing",IF(AND(LEN(TRIM(H10))=11,SUMPRODUCT(--(CODE(MID(TRIM(H10),{1,2,3,4},1))>=65),--(CODE(MID(TRIM(H10),{1,2,3,4},1))<=90))=4,MID(TRIM(H10),5,1)="0"),"Valid","Invalid")) -> Valid | S10: =IF(TRIM(I10)="","Missing",IF(EXACT(TRIM(I10),"India"),"Valid","Invalid")) -> Invalid | T10: =IF(TRIM(J10)="","Missing",IF(OR(EXACT(TRIM(J10),"Net 15"),EXACT(TRIM(J10),"Net 30"),EXACT(TRIM(J10),"Net 45"),EXACT(TRIM(J10),"Net 60")),"Valid","Invalid")) -> Invalid | U10: =COUNTIF(M10:T10,"<>Valid") -> 2 | V10: =SUBSTITUTE(SUBSTITUTE(SUBSTITUTE(F10," ",""),"-",""),"+","") -> 6669849027 | W10: V1108 | X10: =IF(COUNTIF($W$2:$W$229,W10)>1,"Duplicate","Unique") -> Unique
A11: V1022 | B11: Sunrise Printing Pvt Ltd | C11: AVMCI0909X | D11: 07AVMCI0909X1ZS | E11: accounts@sunriseprinting | F11: 83394-21047 | G11: 95214562328 | H11: sbin0884247 | I11: India | J11: NET45 | K11: Active | L11: 2022-10-19 | M11: =IF(TRIM(C11)="","Missing",IF(AND(LEN(TRIM(C11))=10,SUMPRODUCT(--(CODE(MID(TRIM(C11),{1,2,3,4,5,10},1))>=65),--(CODE(MID(TRIM(C11),{1,2,3,4,5,10},1))<=90))=6,ISNUMBER(--MID(TRIM(C11),6,4))),"Valid","Invalid")) -> Valid | N11: =IF(TRIM(D11)="","Missing",IF(AND(LEN(TRIM(D11))=15,MID(TRIM(D11),14,1)="Z"),IF(AND(TRIM(C11)<>"",MID(TRIM(D11),3,10)=TRIM(C11)),"Valid","PAN Mismatch"),"Invalid")) -> Valid | O11: =IF(TRIM(E11)="","Missing",IF(AND(ISNUMBER(FIND("@",E11)),ISERROR(FIND(" ",TRIM(E11))),IFERROR(FIND(".",E11,FIND("@",E11)),0)>0),"Valid","Invalid")) -> Invalid | P11: =IF(TRIM(F11)="","Missing",IFERROR(IF(AND(ISNUMBER(--V11),OR(LEN(V11)=10,AND(LEN(V11)=12,LEFT(V11,2)="91")),VALUE(LEFT(RIGHT(V11,10),1))>=6),"Valid","Invalid"),"Invalid")) -> Valid | Q11: =IF(TRIM(G11)="","Missing",IFERROR(IF(AND(ISNUMBER(--TRIM(G11)),LEN(TRIM(G11))>=9,LEN(TRIM(G11))<=18,ISERROR(FIND(".",G11))),"Valid","Invalid"),"Invalid")) -> Valid | R11: =IF(TRIM(H11)="","Missing",IF(AND(LEN(TRIM(H11))=11,SUMPRODUCT(--(CODE(MID(TRIM(H11),{1,2,3,4},1))>=65),--(CODE(MID(TRIM(H11),{1,2,3,4},1))<=90))=4,MID(TRIM(H11),5,1)="0"),"Valid","Invalid")) -> Invalid | S11: =IF(TRIM(I11)="","Missing",IF(EXACT(TRIM(I11),"India"),"Valid","Invalid")) -> Valid | T11: =IF(TRIM(J11)="","Missing",IF(OR(EXACT(TRIM(J11),"Net 15"),EXACT(TRIM(J11),"Net 30"),EXACT(TRIM(J11),"Net 45"),EXACT(TRIM(J11),"Net 60")),"Valid","Invalid")) -> Invalid | U11: =COUNTIF(M11:T11,"<>Valid") -> 3 | V11: =SUBSTITUTE(SUBSTITUTE(SUBSTITUTE(F11," ",""),"-",""),"+","") -> 8339421047 | W11: V1022 | X11: =IF(COUNTIF($W$2:$W$229,W11)>1,"Duplicate","Unique") -> Unique
A12: V1083 | B12: Jupiter Maintenance Limited | C12: TTVCW6065W | D12: 29TTVCW6065W1ZD | E12: accounts@jupitermaintenance.in | F12: 85054-44713 | G12: 475469137367 | H12: KKBK0508214 | I12: India | J12: Net 60 | K12: Active | L12: 2024-11-17 | M12: =IF(TRIM(C12)="","Missing",IF(AND(LEN(TRIM(C12))=10,SUMPRODUCT(--(CODE(MID(TRIM(C12),{1,2,3,4,5,10},1))>=65),--(CODE(MID(TRIM(C12),{1,2,3,4,5,10},1))<=90))=6,ISNUMBER(--MID(TRIM(C12),6,4))),"Valid","Invalid")) -> Valid | N12: =IF(TRIM(D12)="","Missing",IF(AND(LEN(TRIM(D12))=15,MID(TRIM(D12),14,1)="Z"),IF(AND(TRIM(C12)<>"",MID(TRIM(D12),3,10)=TRIM(C12)),"Valid","PAN Mismatch"),"Invalid")) -> Valid | O12: =IF(TRIM(E12)="","Missing",IF(AND(ISNUMBER(FIND("@",E12)),ISERROR(FIND(" ",TRIM(E12))),IFERROR(FIND(".",E12,FIND("@",E12)),0)>0),"Valid","Invalid")) -> Valid | P12: =IF(TRIM(F12)="","Missing",IFERROR(IF(AND(ISNUMBER(--V12),OR(LEN(V12)=10,AND(LEN(V12)=12,LEFT(V12,2)="91")),VALUE(LEFT(RIGHT(V12,10),1))>=6),"Valid","Invalid"),"Invalid")) -> Valid | Q12: =IF(TRIM(G12)="","Missing",IFERROR(IF(AND(ISNUMBER(--TRIM(G12)),LEN(TRIM(G12))>=9,LEN(TRIM(G12))<=18,ISERROR(FIND(".",G12))),"Valid","Invalid"),"Invalid")) -> Valid | R12: =IF(TRIM(H12)="","Missing",IF(AND(LEN(TRIM(H12))=11,SUMPRODUCT(--(CODE(MID(TRIM(H12),{1,2,3,4},1))>=65),--(CODE(MID(TRIM(H12),{1,2,3,4},1))<=90))=4,MID(TRIM(H12),5,1)="0"),"Valid","Invalid")) -> Valid | S12: =IF(TRIM(I12)="","Missing",IF(EXACT(TRIM(I12),"India"),"Valid","Invalid")) -> Valid | T12: =IF(TRIM(J12)="","Missing",IF(OR(EXACT(TRIM(J12),"Net 15"),EXACT(TRIM(J12),"Net 30"),EXACT(TRIM(J12),"Net 45"),EXACT(TRIM(J12),"Net 60")),"Valid","Invalid")) -> Valid | U12: =COUNTIF(M12:T12,"<>Valid") -> 0 | V12: =SUBSTITUTE(SUBSTITUTE(SUBSTITUTE(F12," ",""),"-",""),"+","") -> 8505444713 | W12: V1083 | X12: =IF(COUNTIF($W$2:$W$229,W12)>1,"Duplicate","Unique") -> Unique
A13: V1051 | B13: Western Electricals Pvt Ltd | C13: OLECI3106T | E13: accounts@westernelectricals.in | F13: +91 71190 79030 | G13: 73830284395995 | H13: ICIC0428364 | I13: India | J13: net 45 | K13: Inactive | L13: 2020-12-18 | M13: =IF(TRIM(C13)="","Missing",IF(AND(LEN(TRIM(C13))=10,SUMPRODUCT(--(CODE(MID(TRIM(C13),{1,2,3,4,5,10},1))>=65),--(CODE(MID(TRIM(C13),{1,2,3,4,5,10},1))<=90))=6,ISNUMBER(--MID(TRIM(C13),6,4))),"Valid","Invalid")) -> Valid | N13: =IF(TRIM(D13)="","Missing",IF(AND(LEN(TRIM(D13))=15,MID(TRIM(D13),14,1)="Z"),IF(AND(TRIM(C13)<>"",MID(TRIM(D13),3,10)=TRIM(C13)),"Valid","PAN Mismatch"),"Invalid")) -> Missing | O13: =IF(TRIM(E13)="","Missing",IF(AND(ISNUMBER(FIND("@",E13)),ISERROR(FIND(" ",TRIM(E13))),IFERROR(FIND(".",E13,FIND("@",E13)),0)>0),"Valid","Invalid")) -> Valid | P13: =IF(TRIM(F13)="","Missing",IFERROR(IF(AND(ISNUMBER(--V13),OR(LEN(V13)=10,AND(LEN(V13)=12,LEFT(V13,2)="91")),VALUE(LEFT(RIGHT(V13,10),1))>=6),"Valid","Invalid"),"Invalid")) -> Valid | Q13: =IF(TRIM(G13)="","Missing",IFERROR(IF(AND(ISNUMBER(--TRIM(G13)),LEN(TRIM(G13))>=9,LEN(TRIM(G13))<=18,ISERROR(FIND(".",G13))),"Valid","Invalid"),"Invalid")) -> Valid | R13: =IF(TRIM(H13)="","Missing",IF(AND(LEN(TRIM(H13))=11,SUMPRODUCT(--(CODE(MID(TRIM(H13),{1,2,3,4},1))>=65),--(CODE(MID(TRIM(H13),{1,2,3,4},1))<=90))=4,MID(TRIM(H13),5,1)="0"),"Valid","Invalid")) -> Valid | S13: =IF(TRIM(I13)="","Missing",IF(EXACT(TRIM(I13),"India"),"Valid","Invalid")) -> Valid | T13: =IF(TRIM(J13)="","Missing",IF(OR(EXACT(TRIM(J13),"Net 15"),EXACT(TRIM(J13),"Net 30"),EXACT(TRIM(J13),"Net 45"),EXACT(TRIM(J13),"Net 60")),"Valid","Invalid")) -> Invalid | U13: =COUNTIF(M13:T13,"<>Valid") -> 2 | V13: =SUBSTITUTE(SUBSTITUTE(SUBSTITUTE(F13," ",""),"-",""),"+","") -> 917119079030 | W13: V1203 | X13: =IF(COUNTIF($W$2:$W$229,W13)>1,"Duplicate","Unique") -> Duplicate
A14: V1179 | B14: Bluewave Printing Pvt Ltd | C14: TMCCM4236C | D14: 27TMCCM4236C1ZN | E14: ACCOUNTS@BLUEWAVEPRINTING.IN | F14: +91 96421 47649 | G14: 515837767499 | H14: UTIB0165926 | I14: india | J14: 60D | K14: Inactive | L14: 2024-10-03 | M14: =IF(TRIM(C14)="","Missing",IF(AND(LEN(TRIM(C14))=10,SUMPRODUCT(--(CODE(MID(TRIM(C14),{1,2,3,4,5,10},1))>=65),--(CODE(MID(TRIM(C14),{1,2,3,4,5,10},1))<=90))=6,ISNUMBER(--MID(TRIM(C14),6,4))),"Valid","Invalid")) -> Valid | N14: =IF(TRIM(D14)="","Missing",IF(AND(LEN(TRIM(D14))=15,MID(TRIM(D14),14,1)="Z"),IF(AND(TRIM(C14)<>"",MID(TRIM(D14),3,10)=TRIM(C14)),"Valid","PAN Mismatch"),"Invalid")) -> Valid | O14: =IF(TRIM(E14)="","Missing",IF(AND(ISNUMBER(FIND("@",E14)),ISERROR(FIND(" ",TRIM(E14))),IFERROR(FIND(".",E14,FIND("@",E14)),0)>0),"Valid","Invalid")) -> Valid | P14: =IF(TRIM(F14)="","Missing",IFERROR(IF(AND(ISNUMBER(--V14),OR(LEN(V14)=10,AND(LEN(V14)=12,LEFT(V14,2)="91")),VALUE(LEFT(RIGHT(V14,10),1))>=6),"Valid","Invalid"),"Invalid")) -> Valid | Q14: =IF(TRIM(G14)="","Missing",IFERROR(IF(AND(ISNUMBER(--TRIM(G14)),LEN(TRIM(G14))>=9,LEN(TRIM(G14))<=18,ISERROR(FIND(".",G14))),"Valid","Invalid"),"Invalid")) -> Valid | R14: =IF(TRIM(H14)="","Missing",IF(AND(LEN(TRIM(H14))=11,SUMPRODUCT(--(CODE(MID(TRIM(H14),{1,2,3,4},1))>=65),--(CODE(MID(TRIM(H14),{1,2,3,4},1))<=90))=4,MID(TRIM(H14),5,1)="0"),"Valid","Invalid")) -> Valid | S14: =IF(TRIM(I14)="","Missing",IF(EXACT(TRIM(I14),"India"),"Valid","Invalid")) -> Invalid | T14: =IF(TRIM(J14)="","Missing",IF(OR(EXACT(TRIM(J14),"Net 15"),EXACT(TRIM(J14),"Net 30"),EXACT(TRIM(J14),"Net 45"),EXACT(TRIM(J14),"Net 60")),"Valid","Invalid")) -> Invalid | U14: =COUNTIF(M14:T14,"<>Valid") -> 2 | V14: =SUBSTITUTE(SUBSTITUTE(SUBSTITUTE(F14," ",""),"-",""),"+","") -> 919642147649 | W14: V1179 | X14: =IF(COUNTIF($W$2:$W$229,W14)>1,"Duplicate","Unique") -> Unique
A15: V1073 | B15: Delta IT Services Limited | C15: CSSCB6234I | D15: 19CSSCB6234I1ZU | E15: accounts@deltaitservices.in | F15: +91 85743 13291 | G15: 127756185374 | H15: UTIB0411249 | I15: India | J15: 15D | K15: Active | L15: 2022-09-04 | M15: =IF(TRIM(C15)="","Missing",IF(AND(LEN(TRIM(C15))=10,SUMPRODUCT(--(CODE(MID(TRIM(C15),{1,2,3,4,5,10},1))>=65),--(CODE(MID(TRIM(C15),{1,2,3,4,5,10},1))<=90))=6,ISNUMBER(--MID(TRIM(C15),6,4))),"Valid","Invalid")) -> Valid | N15: =IF(TRIM(D15)="","Missing",IF(AND(LEN(TRIM(D15))=15,MID(TRIM(D15),14,1)="Z"),IF(AND(TRIM(C15)<>"",MID(TRIM(D15),3,10)=TRIM(C15)),"Valid","PAN Mismatch"),"Invalid")) -> Valid | O15: =IF(TRIM(E15)="","Missing",IF(AND(ISNUMBER(FIND("@",E15)),ISERROR(FIND(" ",TRIM(E15))),IFERROR(FIND(".",E15,FIND("@",E15)),0)>0),"Valid","Invalid")) -> Valid | P15: =IF(TRIM(F15)="","Missing",IFERROR(IF(AND(ISNUMBER(--V15),OR(LEN(V15)=10,AND(LEN(V15)=12,LEFT(V15,2)="91")),VALUE(LEFT(RIGHT(V15,10),1))>=6),"Valid","Invalid"),"Invalid")) -> Valid | Q15: =IF(TRIM(G15)="","Missing",IFERROR(IF(AND(ISNUMBER(--TRIM(G15)),LEN(TRIM(G15))>=9,LEN(TRIM(G15))<=18,ISERROR(FIND(".",G15))),"Valid","Invalid"),"Invalid")) -> Valid | R15: =IF(TRIM(H15)="","Missing",IF(AND(LEN(TRIM(H15))=11,SUMPRODUCT(--(CODE(MID(TRIM(H15),{1,2,3,4},1))>=65),--(CODE(MID(TRIM(H15),{1,2,3,4},1))<=90))=4,MID(TRIM(H15),5,1)="0"),"Valid","Invalid")) -> Valid | S15: =IF(TRIM(I15)="","Missing",IF(EXACT(TRIM(I15),"India"),"Valid","Invalid")) -> Valid | T15: =IF(TRIM(J15)="","Missing",IF(OR(EXACT(TRIM(J15),"Net 15"),EXACT(TRIM(J15),"Net 30"),EXACT(TRIM(J15),"Net 45"),EXACT(TRIM(J15),"Net 60")),"Valid","Invalid")) -> Invalid | U15: =COUNTIF(M15:T15,"<>Valid") -> 1 | V15: =SUBSTITUTE(SUBSTITUTE(SUBSTITUTE(F15," ",""),"-",""),"+","") -> 918574313291 | W15: V1073 | X15: =IF(COUNTIF($W$2:$W$229,W15)>1,"Duplicate","Unique") -> Unique
A16: V1131 | B16: Falcon Power Systems Private Limited | C16: OSWCG7145W | D16: 36OSWCG7145W1ZK | E16: ACCOUNTS@FALCONPOWERSYSTEMS.IN | F16: +91 61751 86892 | G16: 86025922220644 | H16: UTIB0421230 | I16: IN | J16: Net 45 | K16: Inactive | L16: 2024-07-31 | M16: =IF(TRIM(C16)="","Missing",IF(AND(LEN(TRIM(C16))=10,SUMPRODUCT(--(CODE(MID(TRIM(C16),{1,2,3,4,5,10},1))>=65),--(CODE(MID(TRIM(C16),{1,2,3,4,5,10},1))<=90))=6,ISNUMBER(--MID(TRIM(C16),6,4))),"Valid","Invalid")) -> Valid | N16: =IF(TRIM(D16)="","Missing",IF(AND(LEN(TRIM(D16))=15,MID(TRIM(D16),14,1)="Z"),IF(AND(TRIM(C16)<>"",MID(TRIM(D16),3,10)=TRIM(C16)),"Valid","PAN Mismatch"),"Invalid")) -> Valid | O16: =IF(TRIM(E16)="","Missing",IF(AND(ISNUMBER(FIND("@",E16)),ISERROR(FIND(" ",TRIM(E16))),IFERROR(FIND(".",E16,FIND("@",E16)),0)>0),"Valid","Invalid")) -> Valid | P16: =IF(TRIM(F16)="","Missing",IFERROR(IF(AND(ISNUMBER(--V16),OR(LEN(V16)=10,AND(LEN(V16)=12,LEFT(V16,2)="91")),VALUE(LEFT(RIGHT(V16,10),1))>=6),"Valid","Invalid"),"Invalid")) -> Valid | Q16: =IF(TRIM(G16)="","Missing",IFERROR(IF(AND(ISNUMBER(--TRIM(G16)),LEN(TRIM(G16))>=9,LEN(TRIM(G16))<=18,ISERROR(FIND(".",G16))),"Valid","Invalid"),"Invalid")) -> Valid | R16: =IF(TRIM(H16)="","Missing",IF(AND(LEN(TRIM(H16))=11,SUMPRODUCT(--(CODE(MID(TRIM(H16),{1,2,3,4},1))>=65),--(CODE(MID(TRIM(H16),{1,2,3,4},1))<=90))=4,MID(TRIM(H16),5,1)="0"),"Valid","Invalid")) -> Valid | S16: =IF(TRIM(I16)="","Missing",IF(EXACT(TRIM(I16),"India"),"Valid","Invalid")) -> Invalid | T16: =IF(TRIM(J16)="","Missing",IF(OR(EXACT(TRIM(J16),"Net 15"),EXACT(TRIM(J16),"Net 30"),EXACT(TRIM(J16),"Net 45"),EXACT(TRIM(J16),"Net 60")),"Valid","Invalid")) -> Valid | U16: =COUNTIF(M16:T16,"<>Valid") -> 1 | V16: =SUBSTITUTE(SUBSTITUTE(SUBSTITUTE(F16," ",""),"-",""),"+","") -> 916175186892 | W16: V1131 | X16: =IF(COUNTIF($W$2:$W$229,W16)>1,"Duplicate","Unique") -> Unique
A17: V1198 | B17: Western Engineering Works Limited | C17: MDTCY6399A | D17: 07MDTCY6399A1ZY | E17: ACCOUNTS@WESTERNENGINEERINGWORKS.IN | H17: UTIB0797232 | I17: India | J17: NET15 | K17: Inactive | L17: 2022-06-30 | M17: =IF(TRIM(C17)="","Missing",IF(AND(LEN(TRIM(C17))=10,SUMPRODUCT(--(CODE(MID(TRIM(C17),{1,2,3,4,5,10},1))>=65),--(CODE(MID(TRIM(C17),{1,2,3,4,5,10},1))<=90))=6,ISNUMBER(--MID(TRIM(C17),6,4))),"Valid","Invalid")) -> Valid | N17: =IF(TRIM(D17)="","Missing",IF(AND(LEN(TRIM(D17))=15,MID(TRIM(D17),14,1)="Z"),IF(AND(TRIM(C17)<>"",MID(TRIM(D17),3,10)=TRIM(C17)),"Valid","PAN Mismatch"),"Invalid")) -> Valid | O17: =IF(TRIM(E17)="","Missing",IF(AND(ISNUMBER(FIND("@",E17)),ISERROR(FIND(" ",TRIM(E17))),IFERROR(FIND(".",E17,FIND("@",E17)),0)>0),"Valid","Invalid")) -> Valid | P17: =IF(TRIM(F17)="","Missing",IFERROR(IF(AND(ISNUMBER(--V17),OR(LEN(V17)=10,AND(LEN(V17)=12,LEFT(V17,2)="91")),VALUE(LEFT(RIGHT(V17,10),1))>=6),"Valid","Invalid"),"Invalid")) -> Missing | Q17: =IF(TRIM(G17)="","Missing",IFERROR(IF(AND(ISNUMBER(--TRIM(G17)),LEN(TRIM(G17))>=9,LEN(TRIM(G17))<=18,ISERROR(FIND(".",G17))),"Valid","Invalid"),"Invalid")) -> Missing | R17: =IF(TRIM(H17)="","Missing",IF(AND(LEN(TRIM(H17))=11,SUMPRODUCT(--(CODE(MID(TRIM(H17),{1,2,3,4},1))>=65),--(CODE(MID(TRIM(H17),{1,2,3,4},1))<=90))=4,MID(TRIM(H17),5,1)="0"),"Valid","Invalid")) -> Valid | S17: =IF(TRIM(I17)="","Missing",IF(EXACT(TRIM(I17),"India"),"Valid","Invalid")) -> Valid | T17: =IF(TRIM(J17)="","Missing",IF(OR(EXACT(TRIM(J17),"Net 15"),EXACT(TRIM(J17),"Net 30"),EXACT(TRIM(J17),"Net 45"),EXACT(TRIM(J17),"Net 60")),"Valid","Invalid")) -> Invalid | U17: =COUNTIF(M17:T17,"<>Valid") -> 3 | V17: =SUBSTITUTE(SUBSTITUTE(SUBSTITUTE(F17," ",""),"-",""),"+","") | W17: V1198 | X17: =IF(COUNTIF($W$2:$W$229,W17)>1,"Duplicate","Unique") -> Unique
A18: V1161 | B18: Falcon Pest Control Limited | C18: SBECK7252B | D18: 33SBECK7252B1ZX | E18: ACCOUNTS@FALCONPESTCONTROL.IN | F18: 8044818321 | G18: 855445189520 | H18: ICIC0845765 | I18: India | J18: NET30 | K18: Active | L18: 2020-09-25 | M18: =IF(TRIM(C18)="","Missing",IF(AND(LEN(TRIM(C18))=10,SUMPRODUCT(--(CODE(MID(TRIM(C18),{1,2,3,4,5,10},1))>=65),--(CODE(MID(TRIM(C18),{1,2,3,4,5,10},1))<=90))=6,ISNUMBER(--MID(TRIM(C18),6,4))),"Valid","Invalid")) -> Valid | N18: =IF(TRIM(D18)="","Missing",IF(AND(LEN(TRIM(D18))=15,MID(TRIM(D18),14,1)="Z"),IF(AND(TRIM(C18)<>"",MID(TRIM(D18),3,10)=TRIM(C18)),"Valid","PAN Mismatch"),"Invalid")) -> Valid | O18: =IF(TRIM(E18)="","Missing",IF(AND(ISNUMBER(FIND("@",E18)),ISERROR(FIND(" ",TRIM(E18))),IFERROR(FIND(".",E18,FIND("@",E18)),0)>0),"Valid","Invalid")) -> Valid | P18: =IF(TRIM(F18)="","Missing",IFERROR(IF(AND(ISNUMBER(--V18),OR(LEN(V18)=10,AND(LEN(V18)=12,LEFT(V18,2)="91")),VALUE(LEFT(RIGHT(V18,10),1))>=6),"Valid","Invalid"),"Invalid")) -> Valid | Q18: =IF(TRIM(G18)="","Missing",IFERROR(IF(AND(ISNUMBER(--TRIM(G18)),LEN(TRIM(G18))>=9,LEN(TRIM(G18))<=18,ISERROR(FIND(".",G18))),"Valid","Invalid"),"Invalid")) -> Valid | R18: =IF(TRIM(H18)="","Missing",IF(AND(LEN(TRIM(H18))=11,SUMPRODUCT(--(CODE(MID(TRIM(H18),{1,2,3,4},1))>=65),--(CODE(MID(TRIM(H18),{1,2,3,4},1))<=90))=4,MID(TRIM(H18),5,1)="0"),"Valid","Invalid")) -> Valid | S18: =IF(TRIM(I18)="","Missing",IF(EXACT(TRIM(I18),"India"),"Valid","Invalid")) -> Valid | T18: =IF(TRIM(J18)="","Missing",IF(OR(EXACT(TRIM(J18),"Net 15"),EXACT(TRIM(J18),"Net 30"),EXACT(TRIM(J18),"Net 45"),EXACT(TRIM(J18),"Net 60")),"Valid","Invalid")) -> Invalid | U18: =COUNTIF(M18:T18,"<>Valid") -> 1 | V18: =SUBSTITUTE(SUBSTITUTE(SUBSTITUTE(F18," ",""),"-",""),"+","") -> 8044818321 | W18: V1161 | X18: =IF(COUNTIF($W$2:$W$229,W18)>1,"Duplicate","Unique") -> Unique
A19: V1010 | B19: Delta Maintenance Limited | C19: KROCN0366Y | D19: 24KROCN0366Y1ZB | E19: accounts@deltamaintenance.in | F19: +91 90546 68893 | G19: 34670656272980 | H19: UTIB0990162 | I19: India | J19: net 60 | K19: Active | L19: 2021-12-01 | M19: =IF(TRIM(C19)="","Missing",IF(AND(LEN(TRIM(C19))=10,SUMPRODUCT(--(CODE(MID(TRIM(C19),{1,2,3,4,5,10},1))>=65),--(CODE(MID(TRIM(C19),{1,2,3,4,5,10},1))<=90))=6,ISNUMBER(--MID(TRIM(C19),6,4))),"Valid","Invalid")) -> Valid | N19: =IF(TRIM(D19)="","Missing",IF(AND(LEN(TRIM(D19))=15,MID(TRIM(D19),14,1)="Z"),IF(AND(TRIM(C19)<>"",MID(TRIM(D19),3,10)=TRIM(C19)),"Valid","PAN Mismatch"),"Invalid")) -> Valid | O19: =IF(TRIM(E19)="","Missing",IF(AND(ISNUMBER(FIND("@",E19)),ISERROR(FIND(" ",TRIM(E19))),IFERROR(FIND(".",E19,FIND("@",E19)),0)>0),"Valid","Invalid")) -> Valid | P19: =IF(TRIM(F19)="","Missing",IFERROR(IF(AND(ISNUMBER(--V19),OR(LEN(V19)=10,AND(LEN(V19)=12,LEFT(V19,2)="91")),VALUE(LEFT(RIGHT(V19,10),1))>=6),"Valid","Invalid"),"Invalid")) -> Valid | Q19: =IF(TRIM(G19)="","Missing",IFERROR(IF(AND(ISNUMBER(--TRIM(G19)),LEN(TRIM(G19))>=9,LEN(TRIM(G19))<=18,ISERROR(FIND(".",G19))),"Valid","Invalid"),"Invalid")) -> Valid | R19: =IF(TRIM(H19)="","Missing",IF(AND(LEN(TRIM(H19))=11,SUMPRODUCT(--(CODE(MID(TRIM(H19),{1,2,3,4},1))>=65),--(CODE(MID(TRIM(H19),{1,2,3,4},1))<=90))=4,MID(TRIM(H19),5,1)="0"),"Valid","Invalid")) -> Valid | S19: =IF(TRIM(I19)="","Missing",IF(EXACT(TRIM(I19),"India"),"Valid","Invalid")) -> Valid | T19: =IF(TRIM(J19)="","Missing",IF(OR(EXACT(TRIM(J19),"Net 15"),EXACT(TRIM(J19),"Net 30"),EXACT(TRIM(J19),"Net 45"),EXACT(TRIM(J19),"Net 60")),"Valid","Invalid")) -> Invalid | U19: =COUNTIF(M19:T19,"<>Valid") -> 1 | V19: =SUBSTITUTE(SUBSTITUTE(SUBSTITUTE(F19," ",""),"-",""),"+","") -> 919054668893 | W19: V1010 | X19: =IF(COUNTIF($W$2:$W$229,W19)>1,"Duplicate","Unique") -> Unique
A20: V1104 | B20: Crestline Logistics LLP | C20: PZPCT0827F | D20: 29PGCQQ0827F1ZE | E20: accounts@crestlinelogistics.in | F20: +91 72225 91365 | G20: 77739260302 | I20: IN | J20: NET30 | K20: Inactive | L20: 2021-11-23 | M20: =IF(TRIM(C20)="","Missing",IF(AND(LEN(TRIM(C20))=10,SUMPRODUCT(--(CODE(MID(TRIM(C20),{1,2,3,4,5,10},1))>=65),--(CODE(MID(TRIM(C20),{1,2,3,4,5,10},1))<=90))=6,ISNUMBER(--MID(TRIM(C20),6,4))),"Valid","Invalid")) -> Valid | N20: =IF(TRIM(D20)="","Missing",IF(AND(LEN(TRIM(D20))=15,MID(TRIM(D20),14,1)="Z"),IF(AND(TRIM(C20)<>"",MID(TRIM(D20),3,10)=TRIM(C20)),"Valid","PAN Mismatch"),"Invalid")) -> PAN Mismatch | O20: =IF(TRIM(E20)="","Missing",IF(AND(ISNUMBER(FIND("@",E20)),ISERROR(FIND(" ",TRIM(E20))),IFERROR(FIND(".",E20,FIND("@",E20)),0)>0),"Valid","Invalid")) -> Valid | P20: =IF(TRIM(F20)="","Missing",IFERROR(IF(AND(ISNUMBER(--V20),OR(LEN(V20)=10,AND(LEN(V20)=12,LEFT(V20,2)="91")),VALUE(LEFT(RIGHT(V20,10),1))>=6),"Valid","Invalid"),"Invalid")) -> Valid | Q20: =IF(TRIM(G20)="","Missing",IFERROR(IF(AND(ISNUMBER(--TRIM(G20)),LEN(TRIM(G20))>=9,LEN(TRIM(G20))<=18,ISERROR(FIND(".",G20))),"Valid","Invalid"),"Invalid")) -> Valid | R20: =IF(TRIM(H20)="","Missing",IF(AND(LEN(TRIM(H20))=11,SUMPRODUCT(--(CODE(MID(TRIM(H20),{1,2,3,4},1))>=65),--(CODE(MID(TRIM(H20),{1,2,3,4},1))<=90))=4,MID(TRIM(H20),5,1)="0"),"Valid","Invalid")) -> Missing | S20: =IF(TRIM(I20)="","Missing",IF(EXACT(TRIM(I20),"India"),"Valid","Invalid")) -> Invalid | T20: =IF(TRIM(J20)="","Missing",IF(OR(EXACT(TRIM(J20),"Net 15"),EXACT(TRIM(J20),"Net 30"),EXACT(TRIM(J20),"Net 45"),EXACT(TRIM(J20),"Net 60")),"Valid","Invalid")) -> Invalid | U20: =COUNTIF(M20:T20,"<>Valid") -> 4 | V20: =SUBSTITUTE(SUBSTITUTE(SUBSTITUTE(F20," ",""),"-",""),"+","") -> 917222591365 | W20: V1104 | X20: =IF(COUNTIF($W$2:$W$229,W20)>1,"Duplicate","Unique") -> Unique
A21: V1199 | B21: Sunrise Landscaping Limited | C21: SNQCU5498Y | D21: 29SNQCU5498Y1ZJ | E21: ACCOUNTS@SUNRISELANDSCAPING.IN | F21: 8954508920 | G21: 880653331537 | H21: UTIB0959959 | I21: India | J21: Net 45 | K21: Active | L21: 2020-10-26 | M21: =IF(TRIM(C21)="","Missing",IF(AND(LEN(TRIM(C21))=10,SUMPRODUCT(--(CODE(MID(TRIM(C21),{1,2,3,4,5,10},1))>=65),--(CODE(MID(TRIM(C21),{1,2,3,4,5,10},1))<=90))=6,ISNUMBER(--MID(TRIM(C21),6,4))),"Valid","Invalid")) -> Valid | N21: =IF(TRIM(D21)="","Missing",IF(AND(LEN(TRIM(D21))=15,MID(TRIM(D21),14,1)="Z"),IF(AND(TRIM(C21)<>"",MID(TRIM(D21),3,10)=TRIM(C21)),"Valid","PAN Mismatch"),"Invalid")) -> Valid | O21: =IF(TRIM(E21)="","Missing",IF(AND(ISNUMBER(FIND("@",E21)),ISERROR(FIND(" ",TRIM(E21))),IFERROR(FIND(".",E21,FIND("@",E21)),0)>0),"Valid","Invalid")) -> Valid | P21: =IF(TRIM(F21)="","Missing",IFERROR(IF(AND(ISNUMBER(--V21),OR(LEN(V21)=10,AND(LEN(V21)=12,LEFT(V21,2)="91")),VALUE(LEFT(RIGHT(V21,10),1))>=6),"Valid","Invalid"),"Invalid")) -> Valid | Q21: =IF(TRIM(G21)="","Missing",IFERROR(IF(AND(ISNUMBER(--TRIM(G21)),LEN(TRIM(G21))>=9,LEN(TRIM(G21))<=18,ISERROR(FIND(".",G21))),"Valid","Invalid"),"Invalid")) -> Valid | R21: =IF(TRIM(H21)="","Missing",IF(AND(LEN(TRIM(H21))=11,SUMPRODUCT(--(CODE(MID(TRIM(H21),{1,2,3,4},1))>=65),--(CODE(MID(TRIM(H21),{1,2,3,4},1))<=90))=4,MID(TRIM(H21),5,1)="0"),"Valid","Invalid")) -> Valid | S21: =IF(TRIM(I21)="","Missing",IF(EXACT(TRIM(I21),"India"),"Valid","Invalid")) -> Valid | T21: =IF(TRIM(J21)="","Missing",IF(OR(EXACT(TRIM(J21),"Net 15"),EXACT(TRIM(J21),"Net 30"),EXACT(TRIM(J21),"Net 45"),EXACT(TRIM(J21),"Net 60")),"Valid","Invalid")) -> Valid | U21: =COUNTIF(M21:T21,"<>Valid") -> 0 | V21: =SUBSTITUTE(SUBSTITUTE(SUBSTITUTE(F21," ",""),"-",""),"+","") -> 8954508920 | W21: V1199 | X21: =IF(COUNTIF($W$2:$W$229,W21)>1,"Duplicate","Unique") -> Duplicate
A22: V1082 | B22: Horizon IT Services LLP | C22: GUECT4511M | D22: 24GUECT4511M1ZZ | E22: accounts@horizonitservices.in | F22: 88709-98616 | G22: 299911914856 | I22: INDIA | J22: NET30 | K22: Active | L22: 2020-08-12 | M22: =IF(TRIM(C22)="","Missing",IF(AND(LEN(TRIM(C22))=10,SUMPRODUCT(--(CODE(MID(TRIM(C22),{1,2,3,4,5,10},1))>=65),--(CODE(MID(TRIM(C22),{1,2,3,4,5,10},1))<=90))=6,ISNUMBER(--MID(TRIM(C22),6,4))),"Valid","Invalid")) -> Valid | N22: =IF(TRIM(D22)="","Missing",IF(AND(LEN(TRIM(D22))=15,MID(TRIM(D22),14,1)="Z"),IF(AND(TRIM(C22)<>"",MID(TRIM(D22),3,10)=TRIM(C22)),"Valid","PAN Mismatch"),"Invalid")) -> Valid | O22: =IF(TRIM(E22)="","Missing",IF(AND(ISNUMBER(FIND("@",E22)),ISERROR(FIND(" ",TRIM(E22))),IFERROR(FIND(".",E22,FIND("@",E22)),0)>0),"Valid","Invalid")) -> Valid | P22: =IF(TRIM(F22)="","Missing",IFERROR(IF(AND(ISNUMBER(--V22),OR(LEN(V22)=10,AND(LEN(V22)=12,LEFT(V22,2)="91")),VALUE(LEFT(RIGHT(V22,10),1))>=6),"Valid","Invalid"),"Invalid")) -> Valid | Q22: =IF(TRIM(G22)="","Missing",IFERROR(IF(AND(ISNUMBER(--TRIM(G22)),LEN(TRIM(G22))>=9,LEN(TRIM(G22))<=18,ISERROR(FIND(".",G22))),"Valid","Invalid"),"Invalid")) -> Valid | R22: =IF(TRIM(H22)="","Missing",IF(AND(LEN(TRIM(H22))=11,SUMPRODUCT(--(CODE(MID(TRIM(H22),{1,2,3,4},1))>=65),--(CODE(MID(TRIM(H22),{1,2,3,4},1))<=90))=4,MID(TRIM(H22),5,1)="0"),"Valid","Invalid")) -> Missing | S22: =IF(TRIM(I22)="","Missing",IF(EXACT(TRIM(I22),"India"),"Valid","Invalid")) -> Invalid | T22: =IF(TRIM(J22)="","Missing",IF(OR(EXACT(TRIM(J22),"Net 15"),EXACT(TRIM(J22),"Net 30"),EXACT(TRIM(J22),"Net 45"),EXACT(TRIM(J22),"Net 60")),"Valid","Invalid")) -> Invalid | U22: =COUNTIF(M22:T22,"<>Valid") -> 3 | V22: =SUBSTITUTE(SUBSTITUTE(SUBSTITUTE(F22," ",""),"-",""),"+","") -> 8870998616 | W22: V1082 | X22: =IF(COUNTIF($W$2:$W$229,W22)>1,"Duplicate","Unique") -> Unique
A23: V1024 | B23: Apex Landscaping Limited | C23: MOLCV8692N | D23: 36MOLCV8692N1ZG | E23: accounts@apexlandscaping.in | F23: 9405377351 | G23: 8506431713900 | H23: SBIN0329318 | I23: India | J23: net 30 | K23: Active | L23: 2021-08-12 | M23: =IF(TRIM(C23)="","Missing",IF(AND(LEN(TRIM(C23))=10,SUMPRODUCT(--(CODE(MID(TRIM(C23),{1,2,3,4,5,10},1))>=65),--(CODE(MID(TRIM(C23),{1,2,3,4,5,10},1))<=90))=6,ISNUMBER(--MID(TRIM(C23),6,4))),"Valid","Invalid")) -> Valid | N23: =IF(TRIM(D23)="","Missing",IF(AND(LEN(TRIM(D23))=15,MID(TRIM(D23),14,1)="Z"),IF(AND(TRIM(C23)<>"",MID(TRIM(D23),3,10)=TRIM(C23)),"Valid","PAN Mismatch"),"Invalid")) -> Valid | O23: =IF(TRIM(E23)="","Missing",IF(AND(ISNUMBER(FIND("@",E23)),ISERROR(FIND(" ",TRIM(E23))),IFERROR(FIND(".",E23,FIND("@",E23)),0)>0),"Valid","Invalid")) -> Valid | P23: =IF(TRIM(F23)="","Missing",IFERROR(IF(AND(ISNUMBER(--V23),OR(LEN(V23)=10,AND(LEN(V23)=12,LEFT(V23,2)="91")),VALUE(LEFT(RIGHT(V23,10),1))>=6),"Valid","Invalid"),"Invalid")) -> Valid | Q23: =IF(TRIM(G23)="","Missing",IFERROR(IF(AND(ISNUMBER(--TRIM(G23)),LEN(TRIM(G23))>=9,LEN(TRIM(G23))<=18,ISERROR(FIND(".",G23))),"Valid","Invalid"),"Invalid")) -> Valid | R23: =IF(TRIM(H23)="","Missing",IF(AND(LEN(TRIM(H23))=11,SUMPRODUCT(--(CODE(MID(TRIM(H23),{1,2,3,4},1))>=65),--(CODE(MID(TRIM(H23),{1,2,3,4},1))<=90))=4,MID(TRIM(H23),5,1)="0"),"Valid","Invalid")) -> Valid | S23: =IF(TRIM(I23)="","Missing",IF(EXACT(TRIM(I23),"India"),"Valid","Invalid")) -> Valid | T23: =IF(TRIM(J23)="","Missing",IF(OR(EXACT(TRIM(J23),"Net 15"),EXACT(TRIM(J23),"Net 30"),EXACT(TRIM(J23),"Net 45"),EXACT(TRIM(J23),"Net 60")),"Valid","Invalid")) -> Invalid | U23: =COUNTIF(M23:T23,"<>Valid") -> 1 | V23: =SUBSTITUTE(SUBSTITUTE(SUBSTITUTE(F23," ",""),"-",""),"+","") -> 9405377351 | W23: V1024 | X23: =IF(COUNTIF($W$2:$W$229,W23)>1,"Duplicate","Unique") -> Unique
A24: V1163 | B24: Lotus Stationers LLP | C24: BZVCQ9071I | E24: ACCOUNTS@LOTUSSTATIONERS.IN | F24: 61193-93250 | G24: 24955289389 | H24: HDFC0190833 | I24: India | J24: NET45 | K24: Active | L24: 2025-01-09 | M24: =IF(TRIM(C24)="","Missing",IF(AND(LEN(TRIM(C24))=10,SUMPRODUCT(--(CODE(MID(TRIM(C24),{1,2,3,4,5,10},1))>=65),--(CODE(MID(TRIM(C24),{1,2,3,4,5,10},1))<=90))=6,ISNUMBER(--MID(TRIM(C24),6,4))),"Valid","Invalid")) -> Valid | N24: =IF(TRIM(D24)="","Missing",IF(AND(LEN(TRIM(D24))=15,MID(TRIM(D24),14,1)="Z"),IF(AND(TRIM(C24)<>"",MID(TRIM(D24),3,10)=TRIM(C24)),"Valid","PAN Mismatch"),"Invalid")) -> Missing | O24: =IF(TRIM(E24)="","Missing",IF(AND(ISNUMBER(FIND("@",E24)),ISERROR(FIND(" ",TRIM(E24))),IFERROR(FIND(".",E24,FIND("@",E24)),0)>0),"Valid","Invalid")) -> Valid | P24: =IF(TRIM(F24)="","Missing",IFERROR(IF(AND(ISNUMBER(--V24),OR(LEN(V24)=10,AND(LEN(V24)=12,LEFT(V24,2)="91")),VALUE(LEFT(RIGHT(V24,10),1))>=6),"Valid","Invalid"),"Invalid")) -> Valid | Q24: =IF(TRIM(G24)="","Missing",IFERROR(IF(AND(ISNUMBER(--TRIM(G24)),LEN(TRIM(G24))>=9,LEN(TRIM(G24))<=18,ISERROR(FIND(".",G24))),"Valid","Invalid"),"Invalid")) -> Valid | R24: =IF(TRIM(H24)="","Missing",IF(AND(LEN(TRIM(H24))=11,SUMPRODUCT(--(CODE(MID(TRIM(H24),{1,2,3,4},1))>=65),--(CODE(MID(TRIM(H24),{1,2,3,4},1))<=90))=4,MID(TRIM(H24),5,1)="0"),"Valid","Invalid")) -> Valid | S24: =IF(TRIM(I24)="","Missing",IF(EXACT(TRIM(I24),"India"),"Valid","Invalid")) -> Valid | T24: =IF(TRIM(J24)="","Missing",IF(OR(EXACT(TRIM(J24),"Net 15"),EXACT(TRIM(J24),"Net 30"),EXACT(TRIM(J24),"Net 45"),EXACT(TRIM(J24),"Net 60")),"Valid","Invalid")) -> Invalid | U24: =COUNTIF(M24:T24,"<>Valid") -> 2 | V24: =SUBSTITUTE(SUBSTITUTE(SUBSTITUTE(F24," ",""),"-",""),"+","") -> 6119393250 | W24: V1163 | X24: =IF(COUNTIF($W$2:$W$229,W24)>1,"Duplicate","Unique") -> Unique
A25: V1095 | B25: Unity Logistics LLP | C25: IMKCJ7226T | D25: 36IMKCJ7226T1Z6 | E25: ACCOUNTS@UNITYLOGISTICS.IN | F25: 88333-94522 | G25: 1587996846081 | H25: HDFC0620034 | I25: IN | J25: Net 30 | K25: Active | L25: 2021-10-23 | M25: =IF(TRIM(C25)="","Missing",IF(AND(LEN(TRIM(C25))=10,SUMPRODUCT(--(CODE(MID(TRIM(C25),{1,2,3,4,5,10},1))>=65),--(CODE(MID(TRIM(C25),{1,2,3,4,5,10},1))<=90))=6,ISNUMBER(--MID(TRIM(C25),6,4))),"Valid","Invalid")) -> Valid | N25: =IF(TRIM(D25)="","Missing",IF(AND(LEN(TRIM(D25))=15,MID(TRIM(D25),14,1)="Z"),IF(AND(TRIM(C25)<>"",MID(TRIM(D25),3,10)=TRIM(C25)),"Valid","PAN Mismatch"),"Invalid")) -> Valid | O25: =IF(TRIM(E25)="","Missing",IF(AND(ISNUMBER(FIND("@",E25)),ISERROR(FIND(" ",TRIM(E25))),IFERROR(FIND(".",E25,FIND("@",E25)),0)>0),"Valid","Invalid")) -> Valid | P25: =IF(TRIM(F25)="","Missing",IFERROR(IF(AND(ISNUMBER(--V25),OR(LEN(V25)=10,AND(LEN(V25)=12,LEFT(V25,2)="91")),VALUE(LEFT(RIGHT(V25,10),1))>=6),"Valid","Invalid"),"Invalid")) -> Valid | Q25: =IF(TRIM(G25)="","Missing",IFERROR(IF(AND(ISNUMBER(--TRIM(G25)),LEN(TRIM(G25))>=9,LEN(TRIM(G25))<=18,ISERROR(FIND(".",G25))),"Valid","Invalid"),"Invalid")) -> Valid | R25: =IF(TRIM(H25)="","Missing",IF(AND(LEN(TRIM(H25))=11,SUMPRODUCT(--(CODE(MID(TRIM(H25),{1,2,3,4},1))>=65),--(CODE(MID(TRIM(H25),{1,2,3,4},1))<=90))=4,MID(TRIM(H25),5,1)="0"),"Valid","Invalid")) -> Valid | S25: =IF(TRIM(I25)="","Missing",IF(EXACT(TRIM(I25),"India"),"Valid","Invalid")) -> Invalid | T25: =IF(TRIM(J25)="","Missing",IF(OR(EXACT(TRIM(J25),"Net 15"),EXACT(TRIM(J25),"Net 30"),EXACT(TRIM(J25),"Net 45"),EXACT(TRIM(J25),"Net 60")),"Valid","Invalid")) -> Valid | U25: =COUNTIF(M25:T25,"<>Valid") -> 1 | V25: =SUBSTITUTE(SUBSTITUTE(SUBSTITUTE(F25," ",""),"-",""),"+","") -> 8833394522 | W25: V1095 | X25: =IF(COUNTIF($W$2:$W$229,W25)>1,"Duplicate","Unique") -> Duplicate
A26: V1208 | B26: LOTUS ELECTRICALS L.L.P. | C26: JCUCU1076Z | E26: accounts@lotuselectricals.in | F26: 717350583 | G26: 17911006512070 | H26: SBIN1961108 | I26: India | J26: 15D | K26: Active | L26: 2024-12-25 | M26: =IF(TRIM(C26)="","Missing",IF(AND(LEN(TRIM(C26))=10,SUMPRODUCT(--(CODE(MID(TRIM(C26),{1,2,3,4,5,10},1))>=65),--(CODE(MID(TRIM(C26),{1,2,3,4,5,10},1))<=90))=6,ISNUMBER(--MID(TRIM(C26),6,4))),"Valid","Invalid")) -> Valid | N26: =IF(TRIM(D26)="","Missing",IF(AND(LEN(TRIM(D26))=15,MID(TRIM(D26),14,1)="Z"),IF(AND(TRIM(C26)<>"",MID(TRIM(D26),3,10)=TRIM(C26)),"Valid","PAN Mismatch"),"Invalid")) -> Missing | O26: =IF(TRIM(E26)="","Missing",IF(AND(ISNUMBER(FIND("@",E26)),ISERROR(FIND(" ",TRIM(E26))),IFERROR(FIND(".",E26,FIND("@",E26)),0)>0),"Valid","Invalid")) -> Valid | P26: =IF(TRIM(F26)="","Missing",IFERROR(IF(AND(ISNUMBER(--V26),OR(LEN(V26)=10,AND(LEN(V26)=12,LEFT(V26,2)="91")),VALUE(LEFT(RIGHT(V26,10),1))>=6),"Valid","Invalid"),"Invalid")) -> Invalid | Q26: =IF(TRIM(G26)="","Missing",IFERROR(IF(AND(ISNUMBER(--TRIM(G26)),LEN(TRIM(G26))>=9,LEN(TRIM(G26))<=18,ISERROR(FIND(".",G26))),"Valid","Invalid"),"Invalid")) -> Valid | R26: =IF(TRIM(H26)="","Missing",IF(AND(LEN(TRIM(H26))=11,SUMPRODUCT(--(CODE(MID(TRIM(H26),{1,2,3,4},1))>=65),--(CODE(MID(TRIM(H26),{1,2,3,4},1))<=90))=4,MID(TRIM(H26),5,1)="0"),"Valid","Invalid")) -> Invalid | S26: =IF(TRIM(I26)="","Missing",IF(EXACT(TRIM(I26),"India"),"Valid","Invalid")) -> Valid | T26: =IF(TRIM(J26)="","Missing",IF(OR(EXACT(TRIM(J26),"Net 15"),EXACT(TRIM(J26),"Net 30"),EXACT(TRIM(J26),"Net 45"),EXACT(TRIM(J26),"Net 60")),"Valid","Invalid")) -> Invalid | U26: =COUNTIF(M26:T26,"<>Valid") -> 4 | V26: =SUBSTITUTE(SUBSTITUTE(SUBSTITUTE(F26," ",""),"-",""),"+","") -> 717350583 | W26: V1197 | X26: =IF(COUNTIF($W$2:$W$229,W26)>1,"Duplicate","Unique") -> Duplicate
A27: V1173 | B27: Evergreen Logistics Limited | C27: IJCCY3432O | D27: 36CIMCJ3432O1ZU | E27: accounts@evergreenlogistics.in | F27: +91 64177 65612 | G27: 8156985700272 | H27: HDFC0634591 | I27: INDIA | J27: Net 15 | K27: Active | L27: 2024-10-16 | M27: =IF(TRIM(C27)="","Missing",IF(AND(LEN(TRIM(C27))=10,SUMPRODUCT(--(CODE(MID(TRIM(C27),{1,2,3,4,5,10},1))>=65),--(CODE(MID(TRIM(C27),{1,2,3,4,5,10},1))<=90))=6,ISNUMBER(--MID(TRIM(C27),6,4))),"Valid","Invalid")) -> Valid | N27: =IF(TRIM(D27)="","Missing",IF(AND(LEN(TRIM(D27))=15,MID(TRIM(D27),14,1)="Z"),IF(AND(TRIM(C27)<>"",MID(TRIM(D27),3,10)=TRIM(C27)),"Valid","PAN Mismatch"),"Invalid")) -> PAN Mismatch | O27: =IF(TRIM(E27)="","Missing",IF(AND(ISNUMBER(FIND("@",E27)),ISERROR(FIND(" ",TRIM(E27))),IFERROR(FIND(".",E27,FIND("@",E27)),0)>0),"Valid","Invalid")) -> Valid | P27: =IF(TRIM(F27)="","Missing",IFERROR(IF(AND(ISNUMBER(--V27),OR(LEN(V27)=10,AND(LEN(V27)=12,LEFT(V27,2)="91")),VALUE(LEFT(RIGHT(V27,10),1))>=6),"Valid","Invalid"),"Invalid")) -> Valid | Q27: =IF(TRIM(G27)="","Missing",IFERROR(IF(AND(ISNUMBER(--TRIM(G27)),LEN(TRIM(G27))>=9,LEN(TRIM(G27))<=18,ISERROR(FIND(".",G27))),"Valid","Invalid"),"Invalid")) -> Valid | R27: =IF(TRIM(H27)="","Missing",IF(AND(LEN(TRIM(H27))=11,SUMPRODUCT(--(CODE(MID(TRIM(H27),{1,2,3,4},1))>=65),--(CODE(MID(TRIM(H27),{1,2,3,4},1))<=90))=4,MID(TRIM(H27),5,1)="0"),"Valid","Invalid")) -> Valid | S27: =IF(TRIM(I27)="","Missing",IF(EXACT(TRIM(I27),"India"),"Valid","Invalid")) -> Invalid | T27: =IF(TRIM(J27)="","Missing",IF(OR(EXACT(TRIM(J27),"Net 15"),EXACT(TRIM(J27),"Net 30"),EXACT(TRIM(J27),"Net 45"),EXACT(TRIM(J27),"Net 60")),"Valid","Invalid")) -> Valid | U27: =COUNTIF(M27:T27,"<>Valid") -> 2 | V27: =SUBSTITUTE(SUBSTITUTE(SUBSTITUTE(F27," ",""),"-",""),"+","") -> 916417765612 | W27: V1173 | X27: =IF(COUNTIF($W$2:$W$229,W27)>1,"Duplicate","Unique") -> Unique
A28: V1042 | B28: Falcon IT Services Private Limited | C28: QRDCK3714O | D28: 29QRDCK3714O1ZJ | E28: accounts@falconitservices.in | F28: +91 64696 32595 | G28: 278774701687 | H28: ICIC0395004 | I28: India | J28: NET60 | K28: Active | L28: 2024-04-11 | M28: =IF(TRIM(C28)="","Missing",IF(AND(LEN(TRIM(C28))=10,SUMPRODUCT(--(CODE(MID(TRIM(C28),{1,2,3,4,5,10},1))>=65),--(CODE(MID(TRIM(C28),{1,2,3,4,5,10},1))<=90))=6,ISNUMBER(--MID(TRIM(C28),6,4))),"Valid","Invalid")) -> Valid | N28: =IF(TRIM(D28)="","Missing",IF(AND(LEN(TRIM(D28))=15,MID(TRIM(D28),14,1)="Z"),IF(AND(TRIM(C28)<>"",MID(TRIM(D28),3,10)=TRIM(C28)),"Valid","PAN Mismatch"),"Invalid")) -> Valid | O28: =IF(TRIM(E28)="","Missing",IF(AND(ISNUMBER(FIND("@",E28)),ISERROR(FIND(" ",TRIM(E28))),IFERROR(FIND(".",E28,FIND("@",E28)),0)>0),"Valid","Invalid")) -> Valid | P28: =IF(TRIM(F28)="","Missing",IFERROR(IF(AND(ISNUMBER(--V28),OR(LEN(V28)=10,AND(LEN(V28)=12,LEFT(V28,2)="91")),VALUE(LEFT(RIGHT(V28,10),1))>=6),"Valid","Invalid"),"Invalid")) -> Valid | Q28: =IF(TRIM(G28)="","Missing",IFERROR(IF(AND(ISNUMBER(--TRIM(G28)),LEN(TRIM(G28))>=9,LEN(TRIM(G28))<=18,ISERROR(FIND(".",G28))),"Valid","Invalid"),"Invalid")) -> Valid | R28: =IF(TRIM(H28)="","Missing",IF(AND(LEN(TRIM(H28))=11,SUMPRODUCT(--(CODE(MID(TRIM(H28),{1,2,3,4},1))>=65),--(CODE(MID(TRIM(H28),{1,2,3,4},1))<=90))=4,MID(TRIM(H28),5,1)="0"),"Valid","Invalid")) -> Valid | S28: =IF(TRIM(I28)="","Missing",IF(EXACT(TRIM(I28),"India"),"Valid","Invalid")) -> Valid | T28: =IF(TRIM(J28)="","Missing",IF(OR(EXACT(TRIM(J28),"Net 15"),EXACT(TRIM(J28),"Net 30"),EXACT(TRIM(J28),"Net 45"),EXACT(TRIM(J28),"Net 60")),"Valid","Invalid")) -> Invalid | U28: =COUNTIF(M28:T28,"<>Valid") -> 1 | V28: =SUBSTITUTE(SUBSTITUTE(SUBSTITUTE(F28," ",""),"-",""),"+","") -> 916469632595 | W28: V1042 | X28: =IF(COUNTIF($W$2:$W$229,W28)>1,"Duplicate","Unique") -> Unique
A29: V1031 | B29: Pinnacle Engineering Works Private Limited | D29: 33EOCCP7449B1Z6 | E29: accounts@pinnacleengineeringworks.in | F29: +91 87700 54119 | G29: 79807935978207 | H29: HDFC1518203 | I29: India | J29: Net 60 | K29: Active | L29: 2024-11-16 | M29: =IF(TRIM(C29)="","Missing",IF(AND(LEN(TRIM(C29))=10,SUMPRODUCT(--(CODE(MID(TRIM(C29),{1,2,3,4,5,10},1))>=65),--(CODE(MID(TRIM(C29),{1,2,3,4,5,10},1))<=90))=6,ISNUMBER(--MID(TRIM(C29),6,4))),"Valid","Invalid")) -> Missing | N29: =IF(TRIM(D29)="","Missing",IF(AND(LEN(TRIM(D29))=15,MID(TRIM(D29),14,1)="Z"),IF(AND(TRIM(C29)<>"",MID(TRIM(D29),3,10)=TRIM(C29)),"Valid","PAN Mismatch"),"Invalid")) -> PAN Mismatch | O29: =IF(TRIM(E29)="","Missing",IF(AND(ISNUMBER(FIND("@",E29)),ISERROR(FIND(" ",TRIM(E29))),IFERROR(FIND(".",E29,FIND("@",E29)),0)>0),"Valid","Invalid")) -> Valid | P29: =IF(TRIM(F29)="","Missing",IFERROR(IF(AND(ISNUMBER(--V29),OR(LEN(V29)=10,AND(LEN(V29)=12,LEFT(V29,2)="91")),VALUE(LEFT(RIGHT(V29,10),1))>=6),"Valid","Invalid"),"Invalid")) -> Valid | Q29: =IF(TRIM(G29)="","Missing",IFERROR(IF(AND(ISNUMBER(--TRIM(G29)),LEN(TRIM(G29))>=9,LEN(TRIM(G29))<=18,ISERROR(FIND(".",G29))),"Valid","Invalid"),"Invalid")) -> Valid | R29: =IF(TRIM(H29)="","Missing",IF(AND(LEN(TRIM(H29))=11,SUMPRODUCT(--(CODE(MID(TRIM(H29),{1,2,3,4},1))>=65),--(CODE(MID(TRIM(H29),{1,2,3,4},1))<=90))=4,MID(TRIM(H29),5,1)="0"),"Valid","Invalid")) -> Invalid | S29: =IF(TRIM(I29)="","Missing",IF(EXACT(TRIM(I29),"India"),"Valid","Invalid")) -> Valid | T29: =IF(TRIM(J29)="","Missing",IF(OR(EXACT(TRIM(J29),"Net 15"),EXACT(TRIM(J29),"Net 30"),EXACT(TRIM(J29),"Net 45"),EXACT(TRIM(J29),"Net 60")),"Valid","Invalid")) -> Valid | U29: =COUNTIF(M29:T29,"<>Valid") -> 3 | V29: =SUBSTITUTE(SUBSTITUTE(SUBSTITUTE(F29," ",""),"-",""),"+","") -> 918770054119 | W29: V1031 | X29: =IF(COUNTIF($W$2:$W$229,W29)>1,"Duplicate","Unique") -> Unique
A30: V1014 | B30: Delta Security Solutions Pvt Ltd | C30: JIHCD3518Y | D30: 36JIHCD3518Y1ZL | F30: +91 77498 94134 | G30: 524082400842 | H30: UTIB0109477 | I30: IN | J30: 60 Days | K30: Active | L30: 2019-07-30 | M30: =IF(TRIM(C30)="","Missing",IF(AND(LEN(TRIM(C30))=10,SUMPRODUCT(--(CODE(MID(TRIM(C30),{1,2,3,4,5,10},1))>=65),--(CODE(MID(TRIM(C30),{1,2,3,4,5,10},1))<=90))=6,ISNUMBER(--MID(TRIM(C30),6,4))),"Valid","Invalid")) -> Valid | N30: =IF(TRIM(D30)="","Missing",IF(AND(LEN(TRIM(D30))=15,MID(TRIM(D30),14,1)="Z"),IF(AND(TRIM(C30)<>"",MID(TRIM(D30),3,10)=TRIM(C30)),"Valid","PAN Mismatch"),"Invalid")) -> Valid | O30: =IF(TRIM(E30)="","Missing",IF(AND(ISNUMBER(FIND("@",E30)),ISERROR(FIND(" ",TRIM(E30))),IFERROR(FIND(".",E30,FIND("@",E30)),0)>0),"Valid","Invalid")) -> Missing | P30: =IF(TRIM(F30)="","Missing",IFERROR(IF(AND(ISNUMBER(--V30),OR(LEN(V30)=10,AND(LEN(V30)=12,LEFT(V30,2)="91")),VALUE(LEFT(RIGHT(V30,10),1))>=6),"Valid","Invalid"),"Invalid")) -> Valid | Q30: =IF(TRIM(G30)="","Missing",IFERROR(IF(AND(ISNUMBER(--TRIM(G30)),LEN(TRIM(G30))>=9,LEN(TRIM(G30))<=18,ISERROR(FIND(".",G30))),"Valid","Invalid"),"Invalid")) -> Valid | R30: =IF(TRIM(H30)="","Missing",IF(AND(LEN(TRIM(H30))=11,SUMPRODUCT(--(CODE(MID(TRIM(H30),{1,2,3,4},1))>=65),--(CODE(MID(TRIM(H30),{1,2,3,4},1))<=90))=4,MID(TRIM(H30),5,1)="0"),"Valid","Invalid")) -> Valid | S30: =IF(TRIM(I30)="","Missing",IF(EXACT(TRIM(I30),"India"),"Valid","Invalid")) -> Invalid | T30: =IF(TRIM(J30)="","Missing",IF(OR(EXACT(TRIM(J30),"Net 15"),EXACT(TRIM(J30),"Net 30"),EXACT(TRIM(J30),"Net 45"),EXACT(TRIM(J30),"Net 60")),"Valid","Invalid")) -> Invalid | U30: =COUNTIF(M30:T30,"<>Valid") -> 3 | V30: =SUBSTITUTE(SUBSTITUTE(SUBSTITUTE(F30," ",""),"-",""),"+","") -> 917749894134 | W30: V1014 | X30: =IF(COUNTIF($W$2:$W$229,W30)>1,"Duplicate","Unique") -> Unique
A31: V1062 | B31: Western Power Systems Pvt Ltd | C31: MAXCT3796M | D31: 27MAXCT3796M1ZN | E31: ACCOUNTS@WESTERNPOWERSYSTEMS.IN | F31: 8191825537 | G31: 47859696915 | H31: SBIN0792499 | I31: India | J31: 15 Days | K31: Active | L31: 2022-07-06 | M31: =IF(TRIM(C31)="","Missing",IF(AND(LEN(TRIM(C31))=10,SUMPRODUCT(--(CODE(MID(TRIM(C31),{1,2,3,4,5,10},1))>=65),--(CODE(MID(TRIM(C31),{1,2,3,4,5,10},1))<=90))=6,ISNUMBER(--MID(TRIM(C31),6,4))),"Valid","Invalid")) -> Valid | N31: =IF(TRIM(D31)="","Missing",IF(AND(LEN(TRIM(D31))=15,MID(TRIM(D31),14,1)="Z"),IF(AND(TRIM(C31)<>"",MID(TRIM(D31),3,10)=TRIM(C31)),"Valid","PAN Mismatch"),"Invalid")) -> Valid | O31: =IF(TRIM(E31)="","Missing",IF(AND(ISNUMBER(FIND("@",E31)),ISERROR(FIND(" ",TRIM(E31))),IFERROR(FIND(".",E31,FIND("@",E31)),0)>0),"Valid","Invalid")) -> Valid | P31: =IF(TRIM(F31)="","Missing",IFERROR(IF(AND(ISNUMBER(--V31),OR(LEN(V31)=10,AND(LEN(V31)=12,LEFT(V31,2)="91")),VALUE(LEFT(RIGHT(V31,10),1))>=6),"Valid","Invalid"),"Invalid")) -> Valid | Q31: =IF(TRIM(G31)="","Missing",IFERROR(IF(AND(ISNUMBER(--TRIM(G31)),LEN(TRIM(G31))>=9,LEN(TRIM(G31))<=18,ISERROR(FIND(".",G31))),"Valid","Invalid"),"Invalid")) -> Valid | R31: =IF(TRIM(H31)="","Missing",IF(AND(LEN(TRIM(H31))=11,SUMPRODUCT(--(CODE(MID(TRIM(H31),{1,2,3,4},1))>=65),--(CODE(MID(TRIM(H31),{1,2,3,4},1))<=90))=4,MID(TRIM(H31),5,1)="0"),"Valid","Invalid")) -> Valid | S31: =IF(TRIM(I31)="","Missing",IF(EXACT(TRIM(I31),"India"),"Valid","Invalid")) -> Valid | T31: =IF(TRIM(J31)="","Missing",IF(OR(EXACT(TRIM(J31),"Net 15"),EXACT(TRIM(J31),"Net 30"),EXACT(TRIM(J31),"Net 45"),EXACT(TRIM(J31),"Net 60")),"Valid","Invalid")) -> Invalid | U31: =COUNTIF(M31:T31,"<>Valid") -> 1 | V31: =SUBSTITUTE(SUBSTITUTE(SUBSTITUTE(F31," ",""),"-",""),"+","") -> 8191825537 | W31: V1062 | X31: =IF(COUNTIF($W$2:$W$229,W31)>1,"Duplicate","Unique") -> Duplicate
A32: V1015 | B32: Vertex Power Systems Pvt Ltd | C32: ipdcc6719u | D32: 36IPDCC6719U1ZD | E32: accounts@vertexpowersystems.in | F32: +91 79413 18699 | G32: 867749649909 | H32: HDFC0334123 | I32: India | J32: Net 30 | K32: Active | L32: 2020-10-03 | M32: =IF(TRIM(C32)="","Missing",IF(AND(LEN(TRIM(C32))=10,SUMPRODUCT(--(CODE(MID(TRIM(C32),{1,2,3,4,5,10},1))>=65),--(CODE(MID(TRIM(C32),{1,2,3,4,5,10},1))<=90))=6,ISNUMBER(--MID(TRIM(C32),6,4))),"Valid","Invalid")) -> Invalid | N32: =IF(TRIM(D32)="","Missing",IF(AND(LEN(TRIM(D32))=15,MID(TRIM(D32),14,1)="Z"),IF(AND(TRIM(C32)<>"",MID(TRIM(D32),3,10)=TRIM(C32)),"Valid","PAN Mismatch"),"Invalid")) -> Valid | O32: =IF(TRIM(E32)="","Missing",IF(AND(ISNUMBER(FIND("@",E32)),ISERROR(FIND(" ",TRIM(E32))),IFERROR(FIND(".",E32,FIND("@",E32)),0)>0),"Valid","Invalid")) -> Valid | P32: =IF(TRIM(F32)="","Missing",IFERROR(IF(AND(ISNUMBER(--V32),OR(LEN(V32)=10,AND(LEN(V32)=12,LEFT(V32,2)="91")),VALUE(LEFT(RIGHT(V32,10),1))>=6),"Valid","Invalid"),"Invalid")) -> Valid | Q32: =IF(TRIM(G32)="","Missing",IFERROR(IF(AND(ISNUMBER(--TRIM(G32)),LEN(TRIM(G32))>=9,LEN(TRIM(G32))<=18,ISERROR(FIND(".",G32))),"Valid","Invalid"),"Invalid")) -> Valid | R32: =IF(TRIM(H32)="","Missing",IF(AND(LEN(TRIM(H32))=11,SUMPRODUCT(--(CODE(MID(TRIM(H32),{1,2,3,4},1))>=65),--(CODE(MID(TRIM(H32),{1,2,3,4},1))<=90))=4,MID(TRIM(H32),5,1)="0"),"Valid","Invalid")) -> Valid | S32: =IF(TRIM(I32)="","Missing",IF(EXACT(TRIM(I32),"India"),"Valid","Invalid")) -> Valid | T32: =IF(TRIM(J32)="","Missing",IF(OR(EXACT(TRIM(J32),"Net 15"),EXACT(TRIM(J32),"Net 30"),EXACT(TRIM(J32),"Net 45"),EXACT(TRIM(J32),"Net 60")),"Valid","Invalid")) -> Valid | U32: =COUNTIF(M32:T32,"<>Valid") -> 1 | V32: =SUBSTITUTE(SUBSTITUTE(SUBSTITUTE(F32," ",""),"-",""),"+","") -> 917941318699 | W32: V1015 | X32: =IF(COUNTIF($W$2:$W$229,W32)>1,"Duplicate","Unique") -> Unique
A33: V1132 | B33: Deccan Logistics Limited | C33: PRZCA9733S | D33: 36PRZCA9733S1Z4 | E33: accounts@deccanlogistics.in | G33: 022050209945 | H33: HDFC0016224 | I33: India | J33: 30D | K33: Active | L33: 2023-01-15 | M33: =IF(TRIM(C33)="","Missing",IF(AND(LEN(TRIM(C33))=10,SUMPRODUCT(--(CODE(MID(TRIM(C33),{1,2,3,4,5,10},1))>=65),--(CODE(MID(TRIM(C33),{1,2,3,4,5,10},1))<=90))=6,ISNUMBER(--MID(TRIM(C33),6,4))),"Valid","Invalid")) -> Valid | N33: =IF(TRIM(D33)="","Missing",IF(AND(LEN(TRIM(D33))=15,MID(TRIM(D33),14,1)="Z"),IF(AND(TRIM(C33)<>"",MID(TRIM(D33),3,10)=TRIM(C33)),"Valid","PAN Mismatch"),"Invalid")) -> Valid | O33: =IF(TRIM(E33)="","Missing",IF(AND(ISNUMBER(FIND("@",E33)),ISERROR(FIND(" ",TRIM(E33))),IFERROR(FIND(".",E33,FIND("@",E33)),0)>0),"Valid","Invalid")) -> Valid | P33: =IF(TRIM(F33)="","Missing",IFERROR(IF(AND(ISNUMBER(--V33),OR(LEN(V33)=10,AND(LEN(V33)=12,LEFT(V33,2)="91")),VALUE(LEFT(RIGHT(V33,10),1))>=6),"Valid","Invalid"),"Invalid")) -> Missing | Q33: =IF(TRIM(G33)="","Missing",IFERROR(IF(AND(ISNUMBER(--TRIM(G33)),LEN(TRIM(G33))>=9,LEN(TRIM(G33))<=18,ISERROR(FIND(".",G33))),"Valid","Invalid"),"Invalid")) -> Valid | R33: =IF(TRIM(H33)="","Missing",IF(AND(LEN(TRIM(H33))=11,SUMPRODUCT(--(CODE(MID(TRIM(H33),{1,2,3,4},1))>=65),--(CODE(MID(TRIM(H33),{1,2,3,4},1))<=90))=4,MID(TRIM(H33),5,1)="0"),"Valid","Invalid")) -> Valid | S33: =IF(TRIM(I33)="","Missing",IF(EXACT(TRIM(I33),"India"),"Valid","Invalid")) -> Valid | T33: =IF(TRIM(J33)="","Missing",IF(OR(EXACT(TRIM(J33),"Net 15"),EXACT(TRIM(J33),"Net 30"),EXACT(TRIM(J33),"Net 45"),EXACT(TRIM(J33),"Net 60")),"Valid","Invalid")) -> Invalid | U33: =COUNTIF(M33:T33,"<>Valid") -> 2 | V33: =SUBSTITUTE(SUBSTITUTE(SUBSTITUTE(F33," ",""),"-",""),"+","") | W33: V1132 | X33: =IF(COUNTIF($W$2:$W$229,W33)>1,"Duplicate","Unique") -> Unique
A34: V1157 | B34: Titan Facility Services LLP | C34: PLJCY0254O | D34: 29PLJCY0254O1ZK | E34: accounts@titanfacilityservices.in | F34: 7222310592 | H34: SBIN0106727 | I34: INDIA | J34: Net 45 | K34: Active | L34: 2025-02-15 | M34: =IF(TRIM(C34)="","Missing",IF(AND(LEN(TRIM(C34))=10,SUMPRODUCT(--(CODE(MID(TRIM(C34),{1,2,3,4,5,10},1))>=65),--(CODE(MID(TRIM(C34),{1,2,3,4,5,10},1))<=90))=6,ISNUMBER(--MID(TRIM(C34),6,4))),"Valid","Invalid")) -> Valid | N34: =IF(TRIM(D34)="","Missing",IF(AND(LEN(TRIM(D34))=15,MID(TRIM(D34),14,1)="Z"),IF(AND(TRIM(C34)<>"",MID(TRIM(D34),3,10)=TRIM(C34)),"Valid","PAN Mismatch"),"Invalid")) -> Valid | O34: =IF(TRIM(E34)="","Missing",IF(AND(ISNUMBER(FIND("@",E34)),ISERROR(FIND(" ",TRIM(E34))),IFERROR(FIND(".",E34,FIND("@",E34)),0)>0),"Valid","Invalid")) -> Valid | P34: =IF(TRIM(F34)="","Missing",IFERROR(IF(AND(ISNUMBER(--V34),OR(LEN(V34)=10,AND(LEN(V34)=12,LEFT(V34,2)="91")),VALUE(LEFT(RIGHT(V34,10),1))>=6),"Valid","Invalid"),"Invalid")) -> Valid | Q34: =IF(TRIM(G34)="","Missing",IFERROR(IF(AND(ISNUMBER(--TRIM(G34)),LEN(TRIM(G34))>=9,LEN(TRIM(G34))<=18,ISERROR(FIND(".",G34))),"Valid","Invalid"),"Invalid")) -> Missing | R34: =IF(TRIM(H34)="","Missing",IF(AND(LEN(TRIM(H34))=11,SUMPRODUCT(--(CODE(MID(TRIM(H34),{1,2,3,4},1))>=65),--(CODE(MID(TRIM(H34),{1,2,3,4},1))<=90))=4,MID(TRIM(H34),5,1)="0"),"Valid","Invalid")) -> Valid | S34: =IF(TRIM(I34)="","Missing",IF(EXACT(TRIM(I34),"India"),"Valid","Invalid")) -> Invalid | T34: =IF(TRIM(J34)="","Missing",IF(OR(EXACT(TRIM(J34),"Net 15"),EXACT(TRIM(J34),"Net 30"),EXACT(TRIM(J34),"Net 45"),EXACT(TRIM(J34),"Net 60")),"Valid","Invalid")) -> Valid | U34: =COUNTIF(M34:T34,"<>Valid") -> 2 | V34: =SUBSTITUTE(SUBSTITUTE(SUBSTITUTE(F34," ",""),"-",""),"+","") -> 7222310592 | W34: V1157 | X34: =IF(COUNTIF($W$2:$W$229,W34)>1,"Duplicate","Unique") -> Unique
A35: V1127 | B35: Sunrise Facility Services Private Limited | C35: WDKCP9812G | D35: 24ULUTL9812G1Z3 | E35: accounts@sunrisefacilityservices.in | F35: 6384576205 | G35: 5438404608432 | H35: SBIN0621689 | I35: India | J35: 30D | K35: Active | L35: 2020-09-17 | M35: =IF(TRIM(C35)="","Missing",IF(AND(LEN(TRIM(C35))=10,SUMPRODUCT(--(CODE(MID(TRIM(C35),{1,2,3,4,5,10},1))>=65),--(CODE(MID(TRIM(C35),{1,2,3,4,5,10},1))<=90))=6,ISNUMBER(--MID(TRIM(C35),6,4))),"Valid","Invalid")) -> Valid | N35: =IF(TRIM(D35)="","Missing",IF(AND(LEN(TRIM(D35))=15,MID(TRIM(D35),14,1)="Z"),IF(AND(TRIM(C35)<>"",MID(TRIM(D35),3,10)=TRIM(C35)),"Valid","PAN Mismatch"),"Invalid")) -> PAN Mismatch | O35: =IF(TRIM(E35)="","Missing",IF(AND(ISNUMBER(FIND("@",E35)),ISERROR(FIND(" ",TRIM(E35))),IFERROR(FIND(".",E35,FIND("@",E35)),0)>0),"Valid","Invalid")) -> Valid | P35: =IF(TRIM(F35)="","Missing",IFERROR(IF(AND(ISNUMBER(--V35),OR(LEN(V35)=10,AND(LEN(V35)=12,LEFT(V35,2)="91")),VALUE(LEFT(RIGHT(V35,10),1))>=6),"Valid","Invalid"),"Invalid")) -> Valid | Q35: =IF(TRIM(G35)="","Missing",IFERROR(IF(AND(ISNUMBER(--TRIM(G35)),LEN(TRIM(G35))>=9,LEN(TRIM(G35))<=18,ISERROR(FIND(".",G35))),"Valid","Invalid"),"Invalid")) -> Valid | R35: =IF(TRIM(H35)="","Missing",IF(AND(LEN(TRIM(H35))=11,SUMPRODUCT(--(CODE(MID(TRIM(H35),{1,2,3,4},1))>=65),--(CODE(MID(TRIM(H35),{1,2,3,4},1))<=90))=4,MID(TRIM(H35),5,1)="0"),"Valid","Invalid")) -> Valid | S35: =IF(TRIM(I35)="","Missing",IF(EXACT(TRIM(I35),"India"),"Valid","Invalid")) -> Valid | T35: =IF(TRIM(J35)="","Missing",IF(OR(EXACT(TRIM(J35),"Net 15"),EXACT(TRIM(J35),"Net 30"),EXACT(TRIM(J35),"Net 45"),EXACT(TRIM(J35),"Net 60")),"Valid","Invalid")) -> Invalid | U35: =COUNTIF(M35:T35,"<>Valid") -> 2 | V35: =SUBSTITUTE(SUBSTITUTE(SUBSTITUTE(F35," ",""),"-",""),"+","") -> 6384576205 | W35: V1127 | X35: =IF(COUNTIF($W$2:$W$229,W35)>1,"Duplicate","Unique") -> Unique
A36: V1077 | B36: Zenith Housekeeping LLP | C36: PBCCB3930Q | D36: 07PBCCB3930Q1ZA | E36: accounts@zenithhousekeeping.in | F36: 7252500292 | G36: 85156915452 | H36: ICIC0675289 | I36: India | J36: net 45 | K36: Active | L36: 2020-12-19 | M36: =IF(TRIM(C36)="","Missing",IF(AND(LEN(TRIM(C36))=10,SUMPRODUCT(--(CODE(MID(TRIM(C36),{1,2,3,4,5,10},1))>=65),--(CODE(MID(TRIM(C36),{1,2,3,4,5,10},1))<=90))=6,ISNUMBER(--MID(TRIM(C36),6,4))),"Valid","Invalid")) -> Valid | N36: =IF(TRIM(D36)="","Missing",IF(AND(LEN(TRIM(D36))=15,MID(TRIM(D36),14,1)="Z"),IF(AND(TRIM(C36)<>"",MID(TRIM(D36),3,10)=TRIM(C36)),"Valid","PAN Mismatch"),"Invalid")) -> Valid | O36: =IF(TRIM(E36)="","Missing",IF(AND(ISNUMBER(FIND("@",E36)),ISERROR(FIND(" ",TRIM(E36))),IFERROR(FIND(".",E36,FIND("@",E36)),0)>0),"Valid","Invalid")) -> Valid | P36: =IF(TRIM(F36)="","Missing",IFERROR(IF(AND(ISNUMBER(--V36),OR(LEN(V36)=10,AND(LEN(V36)=12,LEFT(V36,2)="91")),VALUE(LEFT(RIGHT(V36,10),1))>=6),"Valid","Invalid"),"Invalid")) -> Valid | Q36: =IF(TRIM(G36)="","Missing",IFERROR(IF(AND(ISNUMBER(--TRIM(G36)),LEN(TRIM(G36))>=9,LEN(TRIM(G36))<=18,ISERROR(FIND(".",G36))),"Valid","Invalid"),"Invalid")) -> Valid | R36: =IF(TRIM(H36)="","Missing",IF(AND(LEN(TRIM(H36))=11,SUMPRODUCT(--(CODE(MID(TRIM(H36),{1,2,3,4},1))>=65),--(CODE(MID(TRIM(H36),{1,2,3,4},1))<=90))=4,MID(TRIM(H36),5,1)="0"),"Valid","Invalid")) -> Valid | S36: =IF(TRIM(I36)="","Missing",IF(EXACT(TRIM(I36),"India"),"Valid","Invalid")) -> Valid | T36: =IF(TRIM(J36)="","Missing",IF(OR(EXACT(TRIM(J36),"Net 15"),EXACT(TRIM(J36),"Net 30"),EXACT(TRIM(J36),"Net 45"),EXACT(TRIM(J36),"Net 60")),"Valid","Invalid")) -> Invalid | U36: =COUNTIF(M36:T36,"<>Valid") -> 1 | V36: =SUBSTITUTE(SUBSTITUTE(SUBSTITUTE(F36," ",""),"-",""),"+","") -> 7252500292 | W36: V1077 | X36: =IF(COUNTIF($W$2:$W$229,W36)>1,"Duplicate","Unique") -> Unique
A37: V1204 | B37: IRONBRIDGE LANDSCAPING LIMITED | C37: NTXCE3226A | D37: 29NTXCE3226A1ZV | E37: accounts@ironbridgelandscaping.in | F37: +91 74216 07337 | H37: KKBK0501429 | I37: India | J37: Net 45 | K37: Inactive | L37: 2025-12-25 | M37: =IF(TRIM(C37)="","Missing",IF(AND(LEN(TRIM(C37))=10,SUMPRODUCT(--(CODE(MID(TRIM(C37),{1,2,3,4,5,10},1))>=65),--(CODE(MID(TRIM(C37),{1,2,3,4,5,10},1))<=90))=6,ISNUMBER(--MID(TRIM(C37),6,4))),"Valid","Invalid")) -> Valid | N37: =IF(TRIM(D37)="","Missing",IF(AND(LEN(TRIM(D37))=15,MID(TRIM(D37),14,1)="Z"),IF(AND(TRIM(C37)<>"",MID(TRIM(D37),3,10)=TRIM(C37)),"Valid","PAN Mismatch"),"Invalid")) -> Valid | O37: =IF(TRIM(E37)="","Missing",IF(AND(ISNUMBER(FIND("@",E37)),ISERROR(FIND(" ",TRIM(E37))),IFERROR(FIND(".",E37,FIND("@",E37)),0)>0),"Valid","Invalid")) -> Valid | P37: =IF(TRIM(F37)="","Missing",IFERROR(IF(AND(ISNUMBER(--V37),OR(LEN(V37)=10,AND(LEN(V37)=12,LEFT(V37,2)="91")),VALUE(LEFT(RIGHT(V37,10),1))>=6),"Valid","Invalid"),"Invalid")) -> Valid | Q37: =IF(TRIM(G37)="","Missing",IFERROR(IF(AND(ISNUMBER(--TRIM(G37)),LEN(TRIM(G37))>=9,LEN(TRIM(G37))<=18,ISERROR(FIND(".",G37))),"Valid","Invalid"),"Invalid")) -> Missing | R37: =IF(TRIM(H37)="","Missing",IF(AND(LEN(TRIM(H37))=11,SUMPRODUCT(--(CODE(MID(TRIM(H37),{1,2,3,4},1))>=65),--(CODE(MID(TRIM(H37),{1,2,3,4},1))<=90))=4,MID(TRIM(H37),5,1)="0"),"Valid","Invalid")) -> Valid | S37: =IF(TRIM(I37)="","Missing",IF(EXACT(TRIM(I37),"India"),"Valid","Invalid")) -> Valid | T37: =IF(TRIM(J37)="","Missing",IF(OR(EXACT(TRIM(J37),"Net 15"),EXACT(TRIM(J37),"Net 30"),EXACT(TRIM(J37),"Net 45"),EXACT(TRIM(J37),"Net 60")),"Valid","Invalid")) -> Valid | U37: =COUNTIF(M37:T37,"<>Valid") -> 1 | V37: =SUBSTITUTE(SUBSTITUTE(SUBSTITUTE(F37," ",""),"-",""),"+","") -> 917421607337 | W37: V1006 | X37: =IF(COUNTIF($W$2:$W$229,W37)>1,"Duplicate","Unique") -> Duplicate
A38: V1156 | B38: Kaveri Pest Control LLP | C38: dficd2723q | D38: 36DFICD2723Q1ZB | F38: 9827567043 | G38: 03856955798 | H38: KKBK0774924 | I38: INDIA | J38: Net 30 | K38: Active | L38: 2021-07-17 | M38: =IF(TRIM(C38)="","Missing",IF(AND(LEN(TRIM(C38))=10,SUMPRODUCT(--(CODE(MID(TRIM(C38),{1,2,3,4,5,10},1))>=65),--(CODE(MID(TRIM(C38),{1,2,3,4,5,10},1))<=90))=6,ISNUMBER(--MID(TRIM(C38),6,4))),"Valid","Invalid")) -> Invalid | N38: =IF(TRIM(D38)="","Missing",IF(AND(LEN(TRIM(D38))=15,MID(TRIM(D38),14,1)="Z"),IF(AND(TRIM(C38)<>"",MID(TRIM(D38),3,10)=TRIM(C38)),"Valid","PAN Mismatch"),"Invalid")) -> Valid | O38: =IF(TRIM(E38)="","Missing",IF(AND(ISNUMBER(FIND("@",E38)),ISERROR(FIND(" ",TRIM(E38))),IFERROR(FIND(".",E38,FIND("@",E38)),0)>0),"Valid","Invalid")) -> Missing | P38: =IF(TRIM(F38)="","Missing",IFERROR(IF(AND(ISNUMBER(--V38),OR(LEN(V38)=10,AND(LEN(V38)=12,LEFT(V38,2)="91")),VALUE(LEFT(RIGHT(V38,10),1))>=6),"Valid","Invalid"),"Invalid")) -> Valid | Q38: =IF(TRIM(G38)="","Missing",IFERROR(IF(AND(ISNUMBER(--TRIM(G38)),LEN(TRIM(G38))>=9,LEN(TRIM(G38))<=18,ISERROR(FIND(".",G38))),"Valid","Invalid"),"Invalid")) -> Valid | R38: =IF(TRIM(H38)="","Missing",IF(AND(LEN(TRIM(H38))=11,SUMPRODUCT(--(CODE(MID(TRIM(H38),{1,2,3,4},1))>=65),--(CODE(MID(TRIM(H38),{1,2,3,4},1))<=90))=4,MID(TRIM(H38),5,1)="0"),"Valid","Invalid")) -> Valid | S38: =IF(TRIM(I38)="","Missing",IF(EXACT(TRIM(I38),"India"),"Valid","Invalid")) -> Invalid | T38: =IF(TRIM(J38)="","Missing",IF(OR(EXACT(TRIM(J38),"Net 15"),EXACT(TRIM(J38),"Net 30"),EXACT(TRIM(J38),"Net 45"),EXACT(TRIM(J38),"Net 60")),"Valid","Invalid")) -> Valid | U38: =COUNTIF(M38:T38,"<>Valid") -> 3 | V38: =SUBSTITUTE(SUBSTITUTE(SUBSTITUTE(F38," ",""),"-",""),"+","") -> 9827567043 | W38: V1156 | X38: =IF(COUNTIF($W$2:$W$229,W38)>1,"Duplicate","Unique") -> Unique
A39: V1182 | B39: Ironbridge Pest Control Pvt Ltd | C39: AWGCA3723N | D39: 19AWGCA3723N1Z8 | E39: accounts@ironbridgepestcontrol.in | F39: 6472760122 | G39: 77079334960501 | H39: UTIB0679984 | I39: India | J39: 15D | K39: Active | L39: 2024-06-14 | M39: =IF(TRIM(C39)="","Missing",IF(AND(LEN(TRIM(C39))=10,SUMPRODUCT(--(CODE(MID(TRIM(C39),{1,2,3,4,5,10},1))>=65),--(CODE(MID(TRIM(C39),{1,2,3,4,5,10},1))<=90))=6,ISNUMBER(--MID(TRIM(C39),6,4))),"Valid","Invalid")) -> Valid | N39: =IF(TRIM(D39)="","Missing",IF(AND(LEN(TRIM(D39))=15,MID(TRIM(D39),14,1)="Z"),IF(AND(TRIM(C39)<>"",MID(TRIM(D39),3,10)=TRIM(C39)),"Valid","PAN Mismatch"),"Invalid")) -> Valid | O39: =IF(TRIM(E39)="","Missing",IF(AND(ISNUMBER(FIND("@",E39)),ISERROR(FIND(" ",TRIM(E39))),IFERROR(FIND(".",E39,FIND("@",E39)),0)>0),"Valid","Invalid")) -> Valid | P39: =IF(TRIM(F39)="","Missing",IFERROR(IF(AND(ISNUMBER(--V39),OR(LEN(V39)=10,AND(LEN(V39)=12,LEFT(V39,2)="91")),VALUE(LEFT(RIGHT(V39,10),1))>=6),"Valid","Invalid"),"Invalid")) -> Valid | Q39: =IF(TRIM(G39)="","Missing",IFERROR(IF(AND(ISNUMBER(--TRIM(G39)),LEN(TRIM(G39))>=9,LEN(TRIM(G39))<=18,ISERROR(FIND(".",G39))),"Valid","Invalid"),"Invalid")) -> Valid | R39: =IF(TRIM(H39)="","Missing",IF(AND(LEN(TRIM(H39))=11,SUMPRODUCT(--(CODE(MID(TRIM(H39),{1,2,3,4},1))>=65),--(CODE(MID(TRIM(H39),{1,2,3,4},1))<=90))=4,MID(TRIM(H39),5,1)="0"),"Valid","Invalid")) -> Valid | S39: =IF(TRIM(I39)="","Missing",IF(EXACT(TRIM(I39),"India"),"Valid","Invalid")) -> Valid | T39: =IF(TRIM(J39)="","Missing",IF(OR(EXACT(TRIM(J39),"Net 15"),EXACT(TRIM(J39),"Net 30"),EXACT(TRIM(J39),"Net 45"),EXACT(TRIM(J39),"Net 60")),"Valid","Invalid")) -> Invalid | U39: =COUNTIF(M39:T39,"<>Valid") -> 1 | V39: =SUBSTITUTE(SUBSTITUTE(SUBSTITUTE(F39," ",""),"-",""),"+","") -> 6472760122 | W39: V1182 | X39: =IF(COUNTIF($W$2:$W$229,W39)>1,"Duplicate","Unique") -> Unique
A40: V1166 | B40: Zenith Facility Services Private Limited | C40: DDICP7320D | D40: 36DDICP7320D1ZD | E40: accounts@zenithfacilityservices.in | F40: +91 90269 52499 | G40: 18773477848 | H40: SBIN0880061 | I40: India | J40: 60 Days | K40: Active | L40: 2023-03-22 | M40: =IF(TRIM(C40)="","Missing",IF(AND(LEN(TRIM(C40))=10,SUMPRODUCT(--(CODE(MID(TRIM(C40),{1,2,3,4,5,10},1))>=65),--(CODE(MID(TRIM(C40),{1,2,3,4,5,10},1))<=90))=6,ISNUMBER(--MID(TRIM(C40),6,4))),"Valid","Invalid")) -> Valid | N40: =IF(TRIM(D40)="","Missing",IF(AND(LEN(TRIM(D40))=15,MID(TRIM(D40),14,1)="Z"),IF(AND(TRIM(C40)<>"",MID(TRIM(D40),3,10)=TRIM(C40)),"Valid","PAN Mismatch"),"Invalid")) -> Valid | O40: =IF(TRIM(E40)="","Missing",IF(AND(ISNUMBER(FIND("@",E40)),ISERROR(FIND(" ",TRIM(E40))),IFERROR(FIND(".",E40,FIND("@",E40)),0)>0),"Valid","Invalid")) -> Valid | P40: =IF(TRIM(F40)="","Missing",IFERROR(IF(AND(ISNUMBER(--V40),OR(LEN(V40)=10,AND(LEN(V40)=12,LEFT(V40,2)="91")),VALUE(LEFT(RIGHT(V40,10),1))>=6),"Valid","Invalid"),"Invalid")) -> Valid | Q40: =IF(TRIM(G40)="","Missing",IFERROR(IF(AND(ISNUMBER(--TRIM(G40)),LEN(TRIM(G40))>=9,LEN(TRIM(G40))<=18,ISERROR(FIND(".",G40))),"Valid","Invalid"),"Invalid")) -> Valid | R40: =IF(TRIM(H40)="","Missing",IF(AND(LEN(TRIM(H40))=11,SUMPRODUCT(--(CODE(MID(TRIM(H40),{1,2,3,4},1))>=65),--(CODE(MID(TRIM(H40),{1,2,3,4},1))<=90))=4,MID(TRIM(H40),5,1)="0"),"Valid","Invalid")) -> Valid | S40: =IF(TRIM(I40)="","Missing",IF(EXACT(TRIM(I40),"India"),"Valid","Invalid")) -> Valid | T40: =IF(TRIM(J40)="","Missing",IF(OR(EXACT(TRIM(J40),"Net 15"),EXACT(TRIM(J40),"Net 30"),EXACT(TRIM(J40),"Net 45"),EXACT(TRIM(J40),"Net 60")),"Valid","Invalid")) -> Invalid | U40: =COUNTIF(M40:T40,"<>Valid") -> 1 | V40: =SUBSTITUTE(SUBSTITUTE(SUBSTITUTE(F40," ",""),"-",""),"+","") -> 919026952499 | W40: V1166 | X40: =IF(COUNTIF($W$2:$W$229,W40)>1,"Duplicate","Unique") -> Unique
A41: V1217 | B41: Titan IT Svcs Private Limited | C41: TOICW9735A | D41: 29TOICW9735A1ZD | E41: accounts@titanitservices.in | F41: +91 71442 70312 | G41: 73564757051 | H41: ICIC0046187 | I41: India | J41: Net 30 | K41: Active | L41: 2024-02-03 | M41: =IF(TRIM(C41)="","Missing",IF(AND(LEN(TRIM(C41))=10,SUMPRODUCT(--(CODE(MID(TRIM(C41),{1,2,3,4,5,10},1))>=65),--(CODE(MID(TRIM(C41),{1,2,3,4,5,10},1))<=90))=6,ISNUMBER(--MID(TRIM(C41),6,4))),"Valid","Invalid")) -> Valid | N41: =IF(TRIM(D41)="","Missing",IF(AND(LEN(TRIM(D41))=15,MID(TRIM(D41),14,1)="Z"),IF(AND(TRIM(C41)<>"",MID(TRIM(D41),3,10)=TRIM(C41)),"Valid","PAN Mismatch"),"Invalid")) -> Valid | O41: =IF(TRIM(E41)="","Missing",IF(AND(ISNUMBER(FIND("@",E41)),ISERROR(FIND(" ",TRIM(E41))),IFERROR(FIND(".",E41,FIND("@",E41)),0)>0),"Valid","Invalid")) -> Valid | P41: =IF(TRIM(F41)="","Missing",IFERROR(IF(AND(ISNUMBER(--V41),OR(LEN(V41)=10,AND(LEN(V41)=12,LEFT(V41,2)="91")),VALUE(LEFT(RIGHT(V41,10),1))>=6),"Valid","Invalid"),"Invalid")) -> Valid | Q41: =IF(TRIM(G41)="","Missing",IFERROR(IF(AND(ISNUMBER(--TRIM(G41)),LEN(TRIM(G41))>=9,LEN(TRIM(G41))<=18,ISERROR(FIND(".",G41))),"Valid","Invalid"),"Invalid")) -> Valid | R41: =IF(TRIM(H41)="","Missing",IF(AND(LEN(TRIM(H41))=11,SUMPRODUCT(--(CODE(MID(TRIM(H41),{1,2,3,4},1))>=65),--(CODE(MID(TRIM(H41),{1,2,3,4},1))<=90))=4,MID(TRIM(H41),5,1)="0"),"Valid","Invalid")) -> Valid | S41: =IF(TRIM(I41)="","Missing",IF(EXACT(TRIM(I41),"India"),"Valid","Invalid")) -> Valid | T41: =IF(TRIM(J41)="","Missing",IF(OR(EXACT(TRIM(J41),"Net 15"),EXACT(TRIM(J41),"Net 30"),EXACT(TRIM(J41),"Net 45"),EXACT(TRIM(J41),"Net 60")),"Valid","Invalid")) -> Valid | U41: =COUNTIF(M41:T41,"<>Valid") -> 0 | V41: =SUBSTITUTE(SUBSTITUTE(SUBSTITUTE(F41," ",""),"-",""),"+","") -> 917144270312 | W41: V1217 | X41: =IF(COUNTIF($W$2:$W$229,W41)>1,"Duplicate","Unique") -> Unique
A42: V1096 | B42: Deccan Maintenance Private Limited | C42: ebwcz4380l | D42: 19EBWCZ4380L1Z2 | E42: ACCOUNTS@DECCANMAINTENANCE.IN | F42: 78638-40666 | G42: 8004397359893 | H42: ICIC0472122 | I42: INDIA | J42: Net 15 | K42: Active | L42: 2023-10-22 | M42: =IF(TRIM(C42)="","Missing",IF(AND(LEN(TRIM(C42))=10,SUMPRODUCT(--(CODE(MID(TRIM(C42),{1,2,3,4,5,10},1))>=65),--(CODE(MID(TRIM(C42),{1,2,3,4,5,10},1))<=90))=6,ISNUMBER(--MID(TRIM(C42),6,4))),"Valid","Invalid")) -> Invalid | N42: =IF(TRIM(D42)="","Missing",IF(AND(LEN(TRIM(D42))=15,MID(TRIM(D42),14,1)="Z"),IF(AND(TRIM(C42)<>"",MID(TRIM(D42),3,10)=TRIM(C42)),"Valid","PAN Mismatch"),"Invalid")) -> Valid | O42: =IF(TRIM(E42)="","Missing",IF(AND(ISNUMBER(FIND("@",E42)),ISERROR(FIND(" ",TRIM(E42))),IFERROR(FIND(".",E42,FIND("@",E42)),0)>0),"Valid","Invalid")) -> Valid | P42: =IF(TRIM(F42)="","Missing",IFERROR(IF(AND(ISNUMBER(--V42),OR(LEN(V42)=10,AND(LEN(V42)=12,LEFT(V42,2)="91")),VALUE(LEFT(RIGHT(V42,10),1))>=6),"Valid","Invalid"),"Invalid")) -> Valid | Q42: =IF(TRIM(G42)="","Missing",IFERROR(IF(AND(ISNUMBER(--TRIM(G42)),LEN(TRIM(G42))>=9,LEN(TRIM(G42))<=18,ISERROR(FIND(".",G42))),"Valid","Invalid"),"Invalid")) -> Valid | R42: =IF(TRIM(H42)="","Missing",IF(AND(LEN(TRIM(H42))=11,SUMPRODUCT(--(CODE(MID(TRIM(H42),{1,2,3,4},1))>=65),--(CODE(MID(TRIM(H42),{1,2,3,4},1))<=90))=4,MID(TRIM(H42),5,1)="0"),"Valid","Invalid")) -> Valid | S42: =IF(TRIM(I42)="","Missing",IF(EXACT(TRIM(I42),"India"),"Valid","Invalid")) -> Invalid | T42: =IF(TRIM(J42)="","Missing",IF(OR(EXACT(TRIM(J42),"Net 15"),EXACT(TRIM(J42),"Net 30"),EXACT(TRIM(J42),"Net 45"),EXACT(TRIM(J42),"Net 60")),"Valid","Invalid")) -> Valid | U42: =COUNTIF(M42:T42,"<>Valid") -> 2 | V42: =SUBSTITUTE(SUBSTITUTE(SUBSTITUTE(F42," ",""),"-",""),"+","") -> 7863840666 | W42: V1096 | X42: =IF(COUNTIF($W$2:$W$229,W42)>1,"Duplicate","Unique") -> Duplicate
A43: V1084 | B43: Zenith IT Services Pvt Ltd | C43: SAFCG3030O | F43: +91 85786 10357 | G43: 27985524140602 | H43: KKBK0333346 | I43: India | J43: 15D | K43: Active | L43: 2019-02-06 | M43: =IF(TRIM(C43)="","Missing",IF(AND(LEN(TRIM(C43))=10,SUMPRODUCT(--(CODE(MID(TRIM(C43),{1,2,3,4,5,10},1))>=65),--(CODE(MID(TRIM(C43),{1,2,3,4,5,10},1))<=90))=6,ISNUMBER(--MID(TRIM(C43),6,4))),"Valid","Invalid")) -> Valid | N43: =IF(TRIM(D43)="","Missing",IF(AND(LEN(TRIM(D43))=15,MID(TRIM(D43),14,1)="Z"),IF(AND(TRIM(C43)<>"",MID(TRIM(D43),3,10)=TRIM(C43)),"Valid","PAN Mismatch"),"Invalid")) -> Missing | O43: =IF(TRIM(E43)="","Missing",IF(AND(ISNUMBER(FIND("@",E43)),ISERROR(FIND(" ",TRIM(E43))),IFERROR(FIND(".",E43,FIND("@",E43)),0)>0),"Valid","Invalid")) -> Missing | P43: =IF(TRIM(F43)="","Missing",IFERROR(IF(AND(ISNUMBER(--V43),OR(LEN(V43)=10,AND(LEN(V43)=12,LEFT(V43,2)="91")),VALUE(LEFT(RIGHT(V43,10),1))>=6),"Valid","Invalid"),"Invalid")) -> Valid | Q43: =IF(TRIM(G43)="","Missing",IFERROR(IF(AND(ISNUMBER(--TRIM(G43)),LEN(TRIM(G43))>=9,LEN(TRIM(G43))<=18,ISERROR(FIND(".",G43))),"Valid","Invalid"),"Invalid")) -> Valid | R43: =IF(TRIM(H43)="","Missing",IF(AND(LEN(TRIM(H43))=11,SUMPRODUCT(--(CODE(MID(TRIM(H43),{1,2,3,4},1))>=65),--(CODE(MID(TRIM(H43),{1,2,3,4},1))<=90))=4,MID(TRIM(H43),5,1)="0"),"Valid","Invalid")) -> Valid | S43: =IF(TRIM(I43)="","Missing",IF(EXACT(TRIM(I43),"India"),"Valid","Invalid")) -> Valid | T43: =IF(TRIM(J43)="","Missing",IF(OR(EXACT(TRIM(J43),"Net 15"),EXACT(TRIM(J43),"Net 30"),EXACT(TRIM(J43),"Net 45"),EXACT(TRIM(J43),"Net 60")),"Valid","Invalid")) -> Invalid | U43: =COUNTIF(M43:T43,"<>Valid") -> 3 | V43: =SUBSTITUTE(SUBSTITUTE(SUBSTITUTE(F43," ",""),"-",""),"+","") -> 918578610357 | W43: V1084 | X43: =IF(COUNTIF($W$2:$W$229,W43)>1,"Duplicate","Unique") -> Unique
A44: V1030 | B44: Ganga Electricals Private Limited | C44: ZTOCW5161H | D44: 07ZTOCW5161H1ZZ | E44: ACCOUNTS@GANGAELECTRICALS.IN | F44: 9453521818 | G44: 552312432921 | H44: ICIC0779979 | I44: India | J44: Net 45 | K44: Active | L44: 2022-07-18 | M44: =IF(TRIM(C44)="","Missing",IF(AND(LEN(TRIM(C44))=10,SUMPRODUCT(--(CODE(MID(TRIM(C44),{1,2,3,4,5,10},1))>=65),--(CODE(MID(TRIM(C44),{1,2,3,4,5,10},1))<=90))=6,ISNUMBER(--MID(TRIM(C44),6,4))),"Valid","Invalid")) -> Valid | N44: =IF(TRIM(D44)="","Missing",IF(AND(LEN(TRIM(D44))=15,MID(TRIM(D44),14,1)="Z"),IF(AND(TRIM(C44)<>"",MID(TRIM(D44),3,10)=TRIM(C44)),"Valid","PAN Mismatch"),"Invalid")) -> Valid | O44: =IF(TRIM(E44)="","Missing",IF(AND(ISNUMBER(FIND("@",E44)),ISERROR(FIND(" ",TRIM(E44))),IFERROR(FIND(".",E44,FIND("@",E44)),0)>0),"Valid","Invalid")) -> Valid | P44: =IF(TRIM(F44)="","Missing",IFERROR(IF(AND(ISNUMBER(--V44),OR(LEN(V44)=10,AND(LEN(V44)=12,LEFT(V44,2)="91")),VALUE(LEFT(RIGHT(V44,10),1))>=6),"Valid","Invalid"),"Invalid")) -> Valid | Q44: =IF(TRIM(G44)="","Missing",IFERROR(IF(AND(ISNUMBER(--TRIM(G44)),LEN(TRIM(G44))>=9,LEN(TRIM(G44))<=18,ISERROR(FIND(".",G44))),"Valid","Invalid"),"Invalid")) -> Valid | R44: =IF(TRIM(H44)="","Missing",IF(AND(LEN(TRIM(H44))=11,SUMPRODUCT(--(CODE(MID(TRIM(H44),{1,2,3,4},1))>=65),--(CODE(MID(TRIM(H44),{1,2,3,4},1))<=90))=4,MID(TRIM(H44),5,1)="0"),"Valid","Invalid")) -> Valid | S44: =IF(TRIM(I44)="","Missing",IF(EXACT(TRIM(I44),"India"),"Valid","Invalid")) -> Valid | T44: =IF(TRIM(J44)="","Missing",IF(OR(EXACT(TRIM(J44),"Net 15"),EXACT(TRIM(J44),"Net 30"),EXACT(TRIM(J44),"Net 45"),EXACT(TRIM(J44),"Net 60")),"Valid","Invalid")) -> Valid | U44: =COUNTIF(M44:T44,"<>Valid") -> 0 | V44: =SUBSTITUTE(SUBSTITUTE(SUBSTITUTE(F44," ",""),"-",""),"+","") -> 9453521818 | W44: V1030 | X44: =IF(COUNTIF($W$2:$W$229,W44)>1,"Duplicate","Unique") -> Unique
A45: V1041 | B45: Deccan Water Solutions Private Limited | C45: SSECF9959B | D45: 19SSECF9959B1ZB | E45: accounts@deccanwatersolutions.in | F45: +91 69439 69078 | G45: 4736471027677 | H45: ICIC1592555 | I45: IN | J45: 60 Days | K45: Active | L45: 2023-02-26 | M45: =IF(TRIM(C45)="","Missing",IF(AND(LEN(TRIM(C45))=10,SUMPRODUCT(--(CODE(MID(TRIM(C45),{1,2,3,4,5,10},1))>=65),--(CODE(MID(TRIM(C45),{1,2,3,4,5,10},1))<=90))=6,ISNUMBER(--MID(TRIM(C45),6,4))),"Valid","Invalid")) -> Valid | N45: =IF(TRIM(D45)="","Missing",IF(AND(LEN(TRIM(D45))=15,MID(TRIM(D45),14,1)="Z"),IF(AND(TRIM(C45)<>"",MID(TRIM(D45),3,10)=TRIM(C45)),"Valid","PAN Mismatch"),"Invalid")) -> Valid | O45: =IF(TRIM(E45)="","Missing",IF(AND(ISNUMBER(FIND("@",E45)),ISERROR(FIND(" ",TRIM(E45))),IFERROR(FIND(".",E45,FIND("@",E45)),0)>0),"Valid","Invalid")) -> Valid | P45: =IF(TRIM(F45)="","Missing",IFERROR(IF(AND(ISNUMBER(--V45),OR(LEN(V45)=10,AND(LEN(V45)=12,LEFT(V45,2)="91")),VALUE(LEFT(RIGHT(V45,10),1))>=6),"Valid","Invalid"),"Invalid")) -> Valid | Q45: =IF(TRIM(G45)="","Missing",IFERROR(IF(AND(ISNUMBER(--TRIM(G45)),LEN(TRIM(G45))>=9,LEN(TRIM(G45))<=18,ISERROR(FIND(".",G45))),"Valid","Invalid"),"Invalid")) -> Valid | R45: =IF(TRIM(H45)="","Missing",IF(AND(LEN(TRIM(H45))=11,SUMPRODUCT(--(CODE(MID(TRIM(H45),{1,2,3,4},1))>=65),--(CODE(MID(TRIM(H45),{1,2,3,4},1))<=90))=4,MID(TRIM(H45),5,1)="0"),"Valid","Invalid")) -> Invalid | S45: =IF(TRIM(I45)="","Missing",IF(EXACT(TRIM(I45),"India"),"Valid","Invalid")) -> Invalid | T45: =IF(TRIM(J45)="","Missing",IF(OR(EXACT(TRIM(J45),"Net 15"),EXACT(TRIM(J45),"Net 30"),EXACT(TRIM(J45),"Net 45"),EXACT(TRIM(J45),"Net 60")),"Valid","Invalid")) -> Invalid | U45: =COUNTIF(M45:T45,"<>Valid") -> 3 | V45: =SUBSTITUTE(SUBSTITUTE(SUBSTITUTE(F45," ",""),"-",""),"+","") -> 916943969078 | W45: V1041 | X45: =IF(COUNTIF($W$2:$W$229,W45)>1,"Duplicate","Unique") -> Unique
A46: V1145 | B46: Ganga Pest Control Limited | C46: TUICK4414U | D46: 24TUICK4414U1ZZ | E46: accounts@gangapestcontrol.in | F46: +91 79385 25800 | G46: 06181753443 | H46: HDFC0091093 | I46: India | J46: net 15 | K46: Active | L46: 2020-05-06 | M46: =IF(TRIM(C46)="","Missing",IF(AND(LEN(TRIM(C46))=10,SUMPRODUCT(--(CODE(MID(TRIM(C46),{1,2,3,4,5,10},1))>=65),--(CODE(MID(TRIM(C46),{1,2,3,4,5,10},1))<=90))=6,ISNUMBER(--MID(TRIM(C46),6,4))),"Valid","Invalid")) -> Valid | N46: =IF(TRIM(D46)="","Missing",IF(AND(LEN(TRIM(D46))=15,MID(TRIM(D46),14,1)="Z"),IF(AND(TRIM(C46)<>"",MID(TRIM(D46),3,10)=TRIM(C46)),"Valid","PAN Mismatch"),"Invalid")) -> Valid | O46: =IF(TRIM(E46)="","Missing",IF(AND(ISNUMBER(FIND("@",E46)),ISERROR(FIND(" ",TRIM(E46))),IFERROR(FIND(".",E46,FIND("@",E46)),0)>0),"Valid","Invalid")) -> Valid | P46: =IF(TRIM(F46)="","Missing",IFERROR(IF(AND(ISNUMBER(--V46),OR(LEN(V46)=10,AND(LEN(V46)=12,LEFT(V46,2)="91")),VALUE(LEFT(RIGHT(V46,10),1))>=6),"Valid","Invalid"),"Invalid")) -> Valid | Q46: =IF(TRIM(G46)="","Missing",IFERROR(IF(AND(ISNUMBER(--TRIM(G46)),LEN(TRIM(G46))>=9,LEN(TRIM(G46))<=18,ISERROR(FIND(".",G46))),"Valid","Invalid"),"Invalid")) -> Valid | R46: =IF(TRIM(H46)="","Missing",IF(AND(LEN(TRIM(H46))=11,SUMPRODUCT(--(CODE(MID(TRIM(H46),{1,2,3,4},1))>=65),--(CODE(MID(TRIM(H46),{1,2,3,4},1))<=90))=4,MID(TRIM(H46),5,1)="0"),"Valid","Invalid")) -> Valid | S46: =IF(TRIM(I46)="","Missing",IF(EXACT(TRIM(I46),"India"),"Valid","Invalid")) -> Valid | T46: =IF(TRIM(J46)="","Missing",IF(OR(EXACT(TRIM(J46),"Net 15"),EXACT(TRIM(J46),"Net 30"),EXACT(TRIM(J46),"Net 45"),EXACT(TRIM(J46),"Net 60")),"Valid","Invalid")) -> Invalid | U46: =COUNTIF(M46:T46,"<>Valid") -> 1 | V46: =SUBSTITUTE(SUBSTITUTE(SUBSTITUTE(F46," ",""),"-",""),"+","") -> 917938525800 | W46: V1145 | X46: =IF(COUNTIF($W$2:$W$229,W46)>1,"Duplicate","Unique") -> Unique
A47: V1048 | B47: Delta Water Solutions Private Limited | C47: nqkcc6122p | D47: 33NQKCC6122P | E47: accountsdeltawatersolutions.in | F47: +91 86374 54990 | G47: 5301742684145 | H47: KKBK0332727 | I47: India | J47: NET45 | K47: Active | L47: 2025-02-27 | M47: =IF(TRIM(C47)="","Missing",IF(AND(LEN(TRIM(C47))=10,SUMPRODUCT(--(CODE(MID(TRIM(C47),{1,2,3,4,5,10},1))>=65),--(CODE(MID(TRIM(C47),{1,2,3,4,5,10},1))<=90))=6,ISNUMBER(--MID(TRIM(C47),6,4))),"Valid","Invalid")) -> Invalid | N47: =IF(TRIM(D47)="","Missing",IF(AND(LEN(TRIM(D47))=15,MID(TRIM(D47),14,1)="Z"),IF(AND(TRIM(C47)<>"",MID(TRIM(D47),3,10)=TRIM(C47)),"Valid","PAN Mismatch"),"Invalid")) -> Invalid | O47: =IF(TRIM(E47)="","Missing",IF(AND(ISNUMBER(FIND("@",E47)),ISERROR(FIND(" ",TRIM(E47))),IFERROR(FIND(".",E47,FIND("@",E47)),0)>0),"Valid","Invalid")) -> Invalid | P47: =IF(TRIM(F47)="","Missing",IFERROR(IF(AND(ISNUMBER(--V47),OR(LEN(V47)=10,AND(LEN(V47)=12,LEFT(V47,2)="91")),VALUE(LEFT(RIGHT(V47,10),1))>=6),"Valid","Invalid"),"Invalid")) -> Valid | Q47: =IF(TRIM(G47)="","Missing",IFERROR(IF(AND(ISNUMBER(--TRIM(G47)),LEN(TRIM(G47))>=9,LEN(TRIM(G47))<=18,ISERROR(FIND(".",G47))),"Valid","Invalid"),"Invalid")) -> Valid | R47: =IF(TRIM(H47)="","Missing",IF(AND(LEN(TRIM(H47))=11,SUMPRODUCT(--(CODE(MID(TRIM(H47),{1,2,3,4},1))>=65),--(CODE(MID(TRIM(H47),{1,2,3,4},1))<=90))=4,MID(TRIM(H47),5,1)="0"),"Valid","Invalid")) -> Valid | S47: =IF(TRIM(I47)="","Missing",IF(EXACT(TRIM(I47),"India"),"Valid","Invalid")) -> Valid | T47: =IF(TRIM(J47)="","Missing",IF(OR(EXACT(TRIM(J47),"Net 15"),EXACT(TRIM(J47),"Net 30"),EXACT(TRIM(J47),"Net 45"),EXACT(TRIM(J47),"Net 60")),"Valid","Invalid")) -> Invalid | U47: =COUNTIF(M47:T47,"<>Valid") -> 4 | V47: =SUBSTITUTE(SUBSTITUTE(SUBSTITUTE(F47," ",""),"-",""),"+","") -> 918637454990 | W47: V1048 | X47: =IF(COUNTIF($W$2:$W$229,W47)>1,"Duplicate","Unique") -> Unique
A48: V1142 | B48: Chola Electricals LLP | C48: OMLCH2690S | D48: 07OMLCH2690S1ZP | E48: ACCOUNTS@CHOLAELECTRICALS.IN | F48: +91 98950 09751 | G48: 12847818913718 | H48: KKBK0490580 | I48: india | J48: Net 60 | K48: Active | L48: 2024-04-05 | M48: =IF(TRIM(C48)="","Missing",IF(AND(LEN(TRIM(C48))=10,SUMPRODUCT(--(CODE(MID(TRIM(C48),{1,2,3,4,5,10},1))>=65),--(CODE(MID(TRIM(C48),{1,2,3,4,5,10},1))<=90))=6,ISNUMBER(--MID(TRIM(C48),6,4))),"Valid","Invalid")) -> Valid | N48: =IF(TRIM(D48)="","Missing",IF(AND(LEN(TRIM(D48))=15,MID(TRIM(D48),14,1)="Z"),IF(AND(TRIM(C48)<>"",MID(TRIM(D48),3,10)=TRIM(C48)),"Valid","PAN Mismatch"),"Invalid")) -> Valid | O48: =IF(TRIM(E48)="","Missing",IF(AND(ISNUMBER(FIND("@",E48)),ISERROR(FIND(" ",TRIM(E48))),IFERROR(FIND(".",E48,FIND("@",E48)),0)>0),"Valid","Invalid")) -> Valid | P48: =IF(TRIM(F48)="","Missing",IFERROR(IF(AND(ISNUMBER(--V48),OR(LEN(V48)=10,AND(LEN(V48)=12,LEFT(V48,2)="91")),VALUE(LEFT(RIGHT(V48,10),1))>=6),"Valid","Invalid"),"Invalid")) -> Valid | Q48: =IF(TRIM(G48)="","Missing",IFERROR(IF(AND(ISNUMBER(--TRIM(G48)),LEN(TRIM(G48))>=9,LEN(TRIM(G48))<=18,ISERROR(FIND(".",G48))),"Valid","Invalid"),"Invalid")) -> Valid | R48: =IF(TRIM(H48)="","Missing",IF(AND(LEN(TRIM(H48))=11,SUMPRODUCT(--(CODE(MID(TRIM(H48),{1,2,3,4},1))>=65),--(CODE(MID(TRIM(H48),{1,2,3,4},1))<=90))=4,MID(TRIM(H48),5,1)="0"),"Valid","Invalid")) -> Valid | S48: =IF(TRIM(I48)="","Missing",IF(EXACT(TRIM(I48),"India"),"Valid","Invalid")) -> Invalid | T48: =IF(TRIM(J48)="","Missing",IF(OR(EXACT(TRIM(J48),"Net 15"),EXACT(TRIM(J48),"Net 30"),EXACT(TRIM(J48),"Net 45"),EXACT(TRIM(J48),"Net 60")),"Valid","Invalid")) -> Valid | U48: =COUNTIF(M48:T48,"<>Valid") -> 1 | V48: =SUBSTITUTE(SUBSTITUTE(SUBSTITUTE(F48," ",""),"-",""),"+","") -> 919895009751 | W48: V1142 | X48: =IF(COUNTIF($W$2:$W$229,W48)>1,"Duplicate","Unique") -> Unique
A49: V1139 | B49: Jupiter Security Solutions Private Limited | C49: OFJCY5992Q | D49: 27FDHDJ5992Q1ZZ | E49: accounts@jupitersecuritysolutions.in | F49: 88148-76963 | G49: 827615396695 | H49: KKBK0321971 | I49: INDIA | J49: Net 60 | K49: Active | L49: 2020-02-04 | M49: =IF(TRIM(C49)="","Missing",IF(AND(LEN(TRIM(C49))=10,SUMPRODUCT(--(CODE(MID(TRIM(C49),{1,2,3,4,5,10},1))>=65),--(CODE(MID(TRIM(C49),{1,2,3,4,5,10},1))<=90))=6,ISNUMBER(--MID(TRIM(C49),6,4))),"Valid","Invalid")) -> Valid | N49: =IF(TRIM(D49)="","Missing",IF(AND(LEN(TRIM(D49))=15,MID(TRIM(D49),14,1)="Z"),IF(AND(TRIM(C49)<>"",MID(TRIM(D49),3,10)=TRIM(C49)),"Valid","PAN Mismatch"),"Invalid")) -> PAN Mismatch | O49: =IF(TRIM(E49)="","Missing",IF(AND(ISNUMBER(FIND("@",E49)),ISERROR(FIND(" ",TRIM(E49))),IFERROR(FIND(".",E49,FIND("@",E49)),0)>0),"Valid","Invalid")) -> Valid | P49: =IF(TRIM(F49)="","Missing",IFERROR(IF(AND(ISNUMBER(--V49),OR(LEN(V49)=10,AND(LEN(V49)=12,LEFT(V49,2)="91")),VALUE(LEFT(RIGHT(V49,10),1))>=6),"Valid","Invalid"),"Invalid")) -> Valid | Q49: =IF(TRIM(G49)="","Missing",IFERROR(IF(AND(ISNUMBER(--TRIM(G49)),LEN(TRIM(G49))>=9,LEN(TRIM(G49))<=18,ISERROR(FIND(".",G49))),"Valid","Invalid"),"Invalid")) -> Valid | R49: =IF(TRIM(H49)="","Missing",IF(AND(LEN(TRIM(H49))=11,SUMPRODUCT(--(CODE(MID(TRIM(H49),{1,2,3,4},1))>=65),--(CODE(MID(TRIM(H49),{1,2,3,4},1))<=90))=4,MID(TRIM(H49),5,1)="0"),"Valid","Invalid")) -> Valid | S49: =IF(TRIM(I49)="","Missing",IF(EXACT(TRIM(I49),"India"),"Valid","Invalid")) -> Invalid | T49: =IF(TRIM(J49)="","Missing",IF(OR(EXACT(TRIM(J49),"Net 15"),EXACT(TRIM(J49),"Net 30"),EXACT(TRIM(J49),"Net 45"),EXACT(TRIM(J49),"Net 60")),"Valid","Invalid")) -> Valid | U49: =COUNTIF(M49:T49,"<>Valid") -> 2 | V49: =SUBSTITUTE(SUBSTITUTE(SUBSTITUTE(F49," ",""),"-",""),"+","") -> 8814876963 | W49: V1139 | X49: =IF(COUNTIF($W$2:$W$229,W49)>1,"Duplicate","Unique") -> Unique
A50: V1123 | B50: Deccan Engineering Works Private Limited | C50: GKACY4888S | D50: 24GKACY4888S1ZJ | E50: accounts@deccanengineeringworks.in | F50: 6752245933 | G50: 4196931572791 | H50: KKBK0409610 | I50: India | J50: 45 Days | K50: Active | L50: 2023-11-14 | M50: =IF(TRIM(C50)="","Missing",IF(AND(LEN(TRIM(C50))=10,SUMPRODUCT(--(CODE(MID(TRIM(C50),{1,2,3,4,5,10},1))>=65),--(CODE(MID(TRIM(C50),{1,2,3,4,5,10},1))<=90))=6,ISNUMBER(--MID(TRIM(C50),6,4))),"Valid","Invalid")) -> Valid | N50: =IF(TRIM(D50)="","Missing",IF(AND(LEN(TRIM(D50))=15,MID(TRIM(D50),14,1)="Z"),IF(AND(TRIM(C50)<>"",MID(TRIM(D50),3,10)=TRIM(C50)),"Valid","PAN Mismatch"),"Invalid")) -> Valid | O50: =IF(TRIM(E50)="","Missing",IF(AND(ISNUMBER(FIND("@",E50)),ISERROR(FIND(" ",TRIM(E50))),IFERROR(FIND(".",E50,FIND("@",E50)),0)>0),"Valid","Invalid")) -> Valid | P50: =IF(TRIM(F50)="","Missing",IFERROR(IF(AND(ISNUMBER(--V50),OR(LEN(V50)=10,AND(LEN(V50)=12,LEFT(V50,2)="91")),VALUE(LEFT(RIGHT(V50,10),1))>=6),"Valid","Invalid"),"Invalid")) -> Valid | Q50: =IF(TRIM(G50)="","Missing",IFERROR(IF(AND(ISNUMBER(--TRIM(G50)),LEN(TRIM(G50))>=9,LEN(TRIM(G50))<=18,ISERROR(FIND(".",G50))),"Valid","Invalid"),"Invalid")) -> Valid | R50: =IF(TRIM(H50)="","Missing",IF(AND(LEN(TRIM(H50))=11,SUMPRODUCT(--(CODE(MID(TRIM(H50),{1,2,3,4},1))>=65),--(CODE(MID(TRIM(H50),{1,2,3,4},1))<=90))=4,MID(TRIM(H50),5,1)="0"),"Valid","Invalid")) -> Valid | S50: =IF(TRIM(I50)="","Missing",IF(EXACT(TRIM(I50),"India"),"Valid","Invalid")) -> Valid | T50: =IF(TRIM(J50)="","Missing",IF(OR(EXACT(TRIM(J50),"Net 15"),EXACT(TRIM(J50),"Net 30"),EXACT(TRIM(J50),"Net 45"),EXACT(TRIM(J50),"Net 60")),"Valid","Invalid")) -> Invalid | U50: =COUNTIF(M50:T50,"<>Valid") -> 1 | V50: =SUBSTITUTE(SUBSTITUTE(SUBSTITUTE(F50," ",""),"-",""),"+","") -> 6752245933 | W50: V1123 | X50: =IF(COUNTIF($W$2:$W$229,W50)>1,"Duplicate","Unique") -> Unique
A51: V1141 | B51: Evergreen Security Solutions LLP | C51: bawcr5140h | D51: 07BAWCR5140H1ZZ | E51: accounts@evergreensecuritysolutions.in | F51: 9666832723 | G51: 56242201027621 | H51: ICIC0679692 | I51: India | J51: Net 60 | K51: Active | L51: 2025-03-11 | M51: =IF(TRIM(C51)="","Missing",IF(AND(LEN(TRIM(C51))=10,SUMPRODUCT(--(CODE(MID(TRIM(C51),{1,2,3,4,5,10},1))>=65),--(CODE(MID(TRIM(C51),{1,2,3,4,5,10},1))<=90))=6,ISNUMBER(--MID(TRIM(C51),6,4))),"Valid","Invalid")) -> Invalid | N51: =IF(TRIM(D51)="","Missing",IF(AND(LEN(TRIM(D51))=15,MID(TRIM(D51),14,1)="Z"),IF(AND(TRIM(C51)<>"",MID(TRIM(D51),3,10)=TRIM(C51)),"Valid","PAN Mismatch"),"Invalid")) -> Valid | O51: =IF(TRIM(E51)="","Missing",IF(AND(ISNUMBER(FIND("@",E51)),ISERROR(FIND(" ",TRIM(E51))),IFERROR(FIND(".",E51,FIND("@",E51)),0)>0),"Valid","Invalid")) -> Valid | P51: =IF(TRIM(F51)="","Missing",IFERROR(IF(AND(ISNUMBER(--V51),OR(LEN(V51)=10,AND(LEN(V51)=12,LEFT(V51,2)="91")),VALUE(LEFT(RIGHT(V51,10),1))>=6),"Valid","Invalid"),"Invalid")) -> Valid | Q51: =IF(TRIM(G51)="","Missing",IFERROR(IF(AND(ISNUMBER(--TRIM(G51)),LEN(TRIM(G51))>=9,LEN(TRIM(G51))<=18,ISERROR(FIND(".",G51))),"Valid","Invalid"),"Invalid")) -> Valid | R51: =IF(TRIM(H51)="","Missing",IF(AND(LEN(TRIM(H51))=11,SUMPRODUCT(--(CODE(MID(TRIM(H51),{1,2,3,4},1))>=65),--(CODE(MID(TRIM(H51),{1,2,3,4},1))<=90))=4,MID(TRIM(H51),5,1)="0"),"Valid","Invalid")) -> Valid | S51: =IF(TRIM(I51)="","Missing",IF(EXACT(TRIM(I51),"India"),"Valid","Invalid")) -> Valid | T51: =IF(TRIM(J51)="","Missing",IF(OR(EXACT(TRIM(J51),"Net 15"),EXACT(TRIM(J51),"Net 30"),EXACT(TRIM(J51),"Net 45"),EXACT(TRIM(J51),"Net 60")),"Valid","Invalid")) -> Valid | U51: =COUNTIF(M51:T51,"<>Valid") -> 1 | V51: =SUBSTITUTE(SUBSTITUTE(SUBSTITUTE(F51," ",""),"-",""),"+","") -> 9666832723 | W51: V1141 | X51: =IF(COUNTIF($W$2:$W$229,W51)>1,"Duplicate","Unique") -> Unique
A52: V1036 | B52: Apex Housekeeping LLP | C52: CQRCQ8806P | D52: 27CQRCQ8806P1ZY | E52: accounts@apexhousekeeping.in | F52: +91 80515 31952 | G52: 58527722170 | I52: INDIA | J52: net 60 | K52: Active | L52: 2025-02-02 | M52: =IF(TRIM(C52)="","Missing",IF(AND(LEN(TRIM(C52))=10,SUMPRODUCT(--(CODE(MID(TRIM(C52),{1,2,3,4,5,10},1))>=65),--(CODE(MID(TRIM(C52),{1,2,3,4,5,10},1))<=90))=6,ISNUMBER(--MID(TRIM(C52),6,4))),"Valid","Invalid")) -> Valid | N52: =IF(TRIM(D52)="","Missing",IF(AND(LEN(TRIM(D52))=15,MID(TRIM(D52),14,1)="Z"),IF(AND(TRIM(C52)<>"",MID(TRIM(D52),3,10)=TRIM(C52)),"Valid","PAN Mismatch"),"Invalid")) -> Valid | O52: =IF(TRIM(E52)="","Missing",IF(AND(ISNUMBER(FIND("@",E52)),ISERROR(FIND(" ",TRIM(E52))),IFERROR(FIND(".",E52,FIND("@",E52)),0)>0),"Valid","Invalid")) -> Valid | P52: =IF(TRIM(F52)="","Missing",IFERROR(IF(AND(ISNUMBER(--V52),OR(LEN(V52)=10,AND(LEN(V52)=12,LEFT(V52,2)="91")),VALUE(LEFT(RIGHT(V52,10),1))>=6),"Valid","Invalid"),"Invalid")) -> Valid | Q52: =IF(TRIM(G52)="","Missing",IFERROR(IF(AND(ISNUMBER(--TRIM(G52)),LEN(TRIM(G52))>=9,LEN(TRIM(G52))<=18,ISERROR(FIND(".",G52))),"Valid","Invalid"),"Invalid")) -> Valid | R52: =IF(TRIM(H52)="","Missing",IF(AND(LEN(TRIM(H52))=11,SUMPRODUCT(--(CODE(MID(TRIM(H52),{1,2,3,4},1))>=65),--(CODE(MID(TRIM(H52),{1,2,3,4},1))<=90))=4,MID(TRIM(H52),5,1)="0"),"Valid","Invalid")) -> Missing | S52: =IF(TRIM(I52)="","Missing",IF(EXACT(TRIM(I52),"India"),"Valid","Invalid")) -> Invalid | T52: =IF(TRIM(J52)="","Missing",IF(OR(EXACT(TRIM(J52),"Net 15"),EXACT(TRIM(J52),"Net 30"),EXACT(TRIM(J52),"Net 45"),EXACT(TRIM(J52),"Net 60")),"Valid","Invalid")) -> Invalid | U52: =COUNTIF(M52:T52,"<>Valid") -> 3 | V52: =SUBSTITUTE(SUBSTITUTE(SUBSTITUTE(F52," ",""),"-",""),"+","") -> 918051531952 | W52: V1036 | X52: =IF(COUNTIF($W$2:$W$229,W52)>1,"Duplicate","Unique") -> Duplicate
A53: V1027 | B53: Chola Security Solutions LLP | D53: 27CCCCC6152R1Z9 | E53: accounts@cholasecuritysolutions.in | F53: +91 66560 49451 | G53: 273158514936 | I53: INDIA | J53: 15D | K53: Active | L53: 2022-06-19 | M53: =IF(TRIM(C53)="","Missing",IF(AND(LEN(TRIM(C53))=10,SUMPRODUCT(--(CODE(MID(TRIM(C53),{1,2,3,4,5,10},1))>=65),--(CODE(MID(TRIM(C53),{1,2,3,4,5,10},1))<=90))=6,ISNUMBER(--MID(TRIM(C53),6,4))),"Valid","Invalid")) -> Missing | N53: =IF(TRIM(D53)="","Missing",IF(AND(LEN(TRIM(D53))=15,MID(TRIM(D53),14,1)="Z"),IF(AND(TRIM(C53)<>"",MID(TRIM(D53),3,10)=TRIM(C53)),"Valid","PAN Mismatch"),"Invalid")) -> PAN Mismatch | O53: =IF(TRIM(E53)="","Missing",IF(AND(ISNUMBER(FIND("@",E53)),ISERROR(FIND(" ",TRIM(E53))),IFERROR(FIND(".",E53,FIND("@",E53)),0)>0),"Valid","Invalid")) -> Valid | P53: =IF(TRIM(F53)="","Missing",IFERROR(IF(AND(ISNUMBER(--V53),OR(LEN(V53)=10,AND(LEN(V53)=12,LEFT(V53,2)="91")),VALUE(LEFT(RIGHT(V53,10),1))>=6),"Valid","Invalid"),"Invalid")) -> Valid | Q53: =IF(TRIM(G53)="","Missing",IFERROR(IF(AND(ISNUMBER(--TRIM(G53)),LEN(TRIM(G53))>=9,LEN(TRIM(G53))<=18,ISERROR(FIND(".",G53))),"Valid","Invalid"),"Invalid")) -> Valid | R53: =IF(TRIM(H53)="","Missing",IF(AND(LEN(TRIM(H53))=11,SUMPRODUCT(--(CODE(MID(TRIM(H53),{1,2,3,4},1))>=65),--(CODE(MID(TRIM(H53),{1,2,3,4},1))<=90))=4,MID(TRIM(H53),5,1)="0"),"Valid","Invalid")) -> Missing | S53: =IF(TRIM(I53)="","Missing",IF(EXACT(TRIM(I53),"India"),"Valid","Invalid")) -> Invalid | T53: =IF(TRIM(J53)="","Missing",IF(OR(EXACT(TRIM(J53),"Net 15"),EXACT(TRIM(J53),"Net 30"),EXACT(TRIM(J53),"Net 45"),EXACT(TRIM(J53),"Net 60")),"Valid","Invalid")) -> Invalid | U53: =COUNTIF(M53:T53,"<>Valid") -> 5 | V53: =SUBSTITUTE(SUBSTITUTE(SUBSTITUTE(F53," ",""),"-",""),"+","") -> 916656049451 | W53: V1027 | X53: =IF(COUNTIF($W$2:$W$229,W53)>1,"Duplicate","Unique") -> Unique
A54: V1058 | B54: Crestline Pest Control Limited | C54: RQNCD0158C | D54: 24RQNCD0158C1ZU | E54: accountscrestlinepestcontrol.in | F54: 6466183982 | G54: 22444721264647 | H54: HDFC0543799 | I54: INDIA | J54: NET30 | K54: Active | L54: 2020-07-08 | M54: =IF(TRIM(C54)="","Missing",IF(AND(LEN(TRIM(C54))=10,SUMPRODUCT(--(CODE(MID(TRIM(C54),{1,2,3,4,5,10},1))>=65),--(CODE(MID(TRIM(C54),{1,2,3,4,5,10},1))<=90))=6,ISNUMBER(--MID(TRIM(C54),6,4))),"Valid","Invalid")) -> Valid | N54: =IF(TRIM(D54)="","Missing",IF(AND(LEN(TRIM(D54))=15,MID(TRIM(D54),14,1)="Z"),IF(AND(TRIM(C54)<>"",MID(TRIM(D54),3,10)=TRIM(C54)),"Valid","PAN Mismatch"),"Invalid")) -> Valid | O54: =IF(TRIM(E54)="","Missing",IF(AND(ISNUMBER(FIND("@",E54)),ISERROR(FIND(" ",TRIM(E54))),IFERROR(FIND(".",E54,FIND("@",E54)),0)>0),"Valid","Invalid")) -> Invalid | P54: =IF(TRIM(F54)="","Missing",IFERROR(IF(AND(ISNUMBER(--V54),OR(LEN(V54)=10,AND(LEN(V54)=12,LEFT(V54,2)="91")),VALUE(LEFT(RIGHT(V54,10),1))>=6),"Valid","Invalid"),"Invalid")) -> Valid | Q54: =IF(TRIM(G54)="","Missing",IFERROR(IF(AND(ISNUMBER(--TRIM(G54)),LEN(TRIM(G54))>=9,LEN(TRIM(G54))<=18,ISERROR(FIND(".",G54))),"Valid","Invalid"),"Invalid")) -> Valid | R54: =IF(TRIM(H54)="","Missing",IF(AND(LEN(TRIM(H54))=11,SUMPRODUCT(--(CODE(MID(TRIM(H54),{1,2,3,4},1))>=65),--(CODE(MID(TRIM(H54),{1,2,3,4},1))<=90))=4,MID(TRIM(H54),5,1)="0"),"Valid","Invalid")) -> Valid | S54: =IF(TRIM(I54)="","Missing",IF(EXACT(TRIM(I54),"India"),"Valid","Invalid")) -> Invalid | T54: =IF(TRIM(J54)="","Missing",IF(OR(EXACT(TRIM(J54),"Net 15"),EXACT(TRIM(J54),"Net 30"),EXACT(TRIM(J54),"Net 45"),EXACT(TRIM(J54),"Net 60")),"Valid","Invalid")) -> Invalid | U54: =COUNTIF(M54:T54,"<>Valid") -> 3 | V54: =SUBSTITUTE(SUBSTITUTE(SUBSTITUTE(F54," ",""),"-",""),"+","") -> 6466183982 | W54: V1058 | X54: =IF(COUNTIF($W$2:$W$229,W54)>1,"Duplicate","Unique") -> Unique
A55: V1017 | B55: Bluewave Security Solutions Private Limited | C55: TIACC3990Y | E55: accounts@bluewavesecuritysolutions.in | F55: +91 77874 29671 | G55: 56551256746807 | H55: HDFC0545168 | I55: IN | J55: net 15 | K55: Active | L55: 2025-01-31 | M55: =IF(TRIM(C55)="","Missing",IF(AND(LEN(TRIM(C55))=10,SUMPRODUCT(--(CODE(MID(TRIM(C55),{1,2,3,4,5,10},1))>=65),--(CODE(MID(TRIM(C55),{1,2,3,4,5,10},1))<=90))=6,ISNUMBER(--MID(TRIM(C55),6,4))),"Valid","Invalid")) -> Valid | N55: =IF(TRIM(D55)="","Missing",IF(AND(LEN(TRIM(D55))=15,MID(TRIM(D55),14,1)="Z"),IF(AND(TRIM(C55)<>"",MID(TRIM(D55),3,10)=TRIM(C55)),"Valid","PAN Mismatch"),"Invalid")) -> Missing | O55: =IF(TRIM(E55)="","Missing",IF(AND(ISNUMBER(FIND("@",E55)),ISERROR(FIND(" ",TRIM(E55))),IFERROR(FIND(".",E55,FIND("@",E55)),0)>0),"Valid","Invalid")) -> Valid | P55: =IF(TRIM(F55)="","Missing",IFERROR(IF(AND(ISNUMBER(--V55),OR(LEN(V55)=10,AND(LEN(V55)=12,LEFT(V55,2)="91")),VALUE(LEFT(RIGHT(V55,10),1))>=6),"Valid","Invalid"),"Invalid")) -> Valid | Q55: =IF(TRIM(G55)="","Missing",IFERROR(IF(AND(ISNUMBER(--TRIM(G55)),LEN(TRIM(G55))>=9,LEN(TRIM(G55))<=18,ISERROR(FIND(".",G55))),"Valid","Invalid"),"Invalid")) -> Valid | R55: =IF(TRIM(H55)="","Missing",IF(AND(LEN(TRIM(H55))=11,SUMPRODUCT(--(CODE(MID(TRIM(H55),{1,2,3,4},1))>=65),--(CODE(MID(TRIM(H55),{1,2,3,4},1))<=90))=4,MID(TRIM(H55),5,1)="0"),"Valid","Invalid")) -> Valid | S55: =IF(TRIM(I55)="","Missing",IF(EXACT(TRIM(I55),"India"),"Valid","Invalid")) -> Invalid | T55: =IF(TRIM(J55)="","Missing",IF(OR(EXACT(TRIM(J55),"Net 15"),EXACT(TRIM(J55),"Net 30"),EXACT(TRIM(J55),"Net 45"),EXACT(TRIM(J55),"Net 60")),"Valid","Invalid")) -> Invalid | U55: =COUNTIF(M55:T55,"<>Valid") -> 3 | V55: =SUBSTITUTE(SUBSTITUTE(SUBSTITUTE(F55," ",""),"-",""),"+","") -> 917787429671 | W55: V1017 | X55: =IF(COUNTIF($W$2:$W$229,W55)>1,"Duplicate","Unique") -> Unique
A56: V1069 | B56: Ironbridge Engineering Works Private Limited | C56: MSNCL8271A | D56: 24MSNCL8271A1ZE | E56: accounts@ironbridgeengineeringworks.in | F56: 8300684866 | G56: 18892414183285 | H56: UTIB0914630 | I56: India | J56: NET30 | K56: Inactive | L56: 2023-11-15 | M56: =IF(TRIM(C56)="","Missing",IF(AND(LEN(TRIM(C56))=10,SUMPRODUCT(--(CODE(MID(TRIM(C56),{1,2,3,4,5,10},1))>=65),--(CODE(MID(TRIM(C56),{1,2,3,4,5,10},1))<=90))=6,ISNUMBER(--MID(TRIM(C56),6,4))),"Valid","Invalid")) -> Valid | N56: =IF(TRIM(D56)="","Missing",IF(AND(LEN(TRIM(D56))=15,MID(TRIM(D56),14,1)="Z"),IF(AND(TRIM(C56)<>"",MID(TRIM(D56),3,10)=TRIM(C56)),"Valid","PAN Mismatch"),"Invalid")) -> Valid | O56: =IF(TRIM(E56)="","Missing",IF(AND(ISNUMBER(FIND("@",E56)),ISERROR(FIND(" ",TRIM(E56))),IFERROR(FIND(".",E56,FIND("@",E56)),0)>0),"Valid","Invalid")) -> Valid | P56: =IF(TRIM(F56)="","Missing",IFERROR(IF(AND(ISNUMBER(--V56),OR(LEN(V56)=10,AND(LEN(V56)=12,LEFT(V56,2)="91")),VALUE(LEFT(RIGHT(V56,10),1))>=6),"Valid","Invalid"),"Invalid")) -> Valid | Q56: =IF(TRIM(G56)="","Missing",IFERROR(IF(AND(ISNUMBER(--TRIM(G56)),LEN(TRIM(G56))>=9,LEN(TRIM(G56))<=18,ISERROR(FIND(".",G56))),"Valid","Invalid"),"Invalid")) -> Valid | R56: =IF(TRIM(H56)="","Missing",IF(AND(LEN(TRIM(H56))=11,SUMPRODUCT(--(CODE(MID(TRIM(H56),{1,2,3,4},1))>=65),--(CODE(MID(TRIM(H56),{1,2,3,4},1))<=90))=4,MID(TRIM(H56),5,1)="0"),"Valid","Invalid")) -> Valid | S56: =IF(TRIM(I56)="","Missing",IF(EXACT(TRIM(I56),"India"),"Valid","Invalid")) -> Valid | T56: =IF(TRIM(J56)="","Missing",IF(OR(EXACT(TRIM(J56),"Net 15"),EXACT(TRIM(J56),"Net 30"),EXACT(TRIM(J56),"Net 45"),EXACT(TRIM(J56),"Net 60")),"Valid","Invalid")) -> Invalid | U56: =COUNTIF(M56:T56,"<>Valid") -> 1 | V56: =SUBSTITUTE(SUBSTITUTE(SUBSTITUTE(F56," ",""),"-",""),"+","") -> 8300684866 | W56: V1069 | X56: =IF(COUNTIF($W$2:$W$229,W56)>1,"Duplicate","Unique") -> Unique
A57: V1087 | B57: Aaryan Water Solutions LLP | C57: BUSCS9173Q | D57: 27BUSCS9173Q1ZY | E57: accounts@aaryanwatersolutions.in | F57: 9022356972 | G57: 2175250074329 | H57: ICIC0712966 | I57: India | J57: 60 Days | K57: Active | L57: 2024-05-09 | M57: =IF(TRIM(C57)="","Missing",IF(AND(LEN(TRIM(C57))=10,SUMPRODUCT(--(CODE(MID(TRIM(C57),{1,2,3,4,5,10},1))>=65),--(CODE(MID(TRIM(C57),{1,2,3,4,5,10},1))<=90))=6,ISNUMBER(--MID(TRIM(C57),6,4))),"Valid","Invalid")) -> Valid | N57: =IF(TRIM(D57)="","Missing",IF(AND(LEN(TRIM(D57))=15,MID(TRIM(D57),14,1)="Z"),IF(AND(TRIM(C57)<>"",MID(TRIM(D57),3,10)=TRIM(C57)),"Valid","PAN Mismatch"),"Invalid")) -> Valid | O57: =IF(TRIM(E57)="","Missing",IF(AND(ISNUMBER(FIND("@",E57)),ISERROR(FIND(" ",TRIM(E57))),IFERROR(FIND(".",E57,FIND("@",E57)),0)>0),"Valid","Invalid")) -> Valid | P57: =IF(TRIM(F57)="","Missing",IFERROR(IF(AND(ISNUMBER(--V57),OR(LEN(V57)=10,AND(LEN(V57)=12,LEFT(V57,2)="91")),VALUE(LEFT(RIGHT(V57,10),1))>=6),"Valid","Invalid"),"Invalid")) -> Valid | Q57: =IF(TRIM(G57)="","Missing",IFERROR(IF(AND(ISNUMBER(--TRIM(G57)),LEN(TRIM(G57))>=9,LEN(TRIM(G57))<=18,ISERROR(FIND(".",G57))),"Valid","Invalid"),"Invalid")) -> Valid | R57: =IF(TRIM(H57)="","Missing",IF(AND(LEN(TRIM(H57))=11,SUMPRODUCT(--(CODE(MID(TRIM(H57),{1,2,3,4},1))>=65),--(CODE(MID(TRIM(H57),{1,2,3,4},1))<=90))=4,MID(TRIM(H57),5,1)="0"),"Valid","Invalid")) -> Valid | S57: =IF(TRIM(I57)="","Missing",IF(EXACT(TRIM(I57),"India"),"Valid","Invalid")) -> Valid | T57: =IF(TRIM(J57)="","Missing",IF(OR(EXACT(TRIM(J57),"Net 15"),EXACT(TRIM(J57),"Net 30"),EXACT(TRIM(J57),"Net 45"),EXACT(TRIM(J57),"Net 60")),"Valid","Invalid")) -> Invalid | U57: =COUNTIF(M57:T57,"<>Valid") -> 1 | V57: =SUBSTITUTE(SUBSTITUTE(SUBSTITUTE(F57," ",""),"-",""),"+","") -> 9022356972 | W57: V1087 | X57: =IF(COUNTIF($W$2:$W$229,W57)>1,"Duplicate","Unique") -> Duplicate
A58: V1143 | B58: Aaryan Electricals LLP | C58: SXKCN5442B | D58: 36SXKCN5442B1ZT | E58: ACCOUNTS@AARYANELECTRICALS.IN | F58: +91 67929 04904 | G58: 12814429444019 | H58: ICIC0927524 | I58: India | J58: 30 Days | K58: Active | L58: 2024-11-30 | M58: =IF(TRIM(C58)="","Missing",IF(AND(LEN(TRIM(C58))=10,SUMPRODUCT(--(CODE(MID(TRIM(C58),{1,2,3,4,5,10},1))>=65),--(CODE(MID(TRIM(C58),{1,2,3,4,5,10},1))<=90))=6,ISNUMBER(--MID(TRIM(C58),6,4))),"Valid","Invalid")) -> Valid | N58: =IF(TRIM(D58)="","Missing",IF(AND(LEN(TRIM(D58))=15,MID(TRIM(D58),14,1)="Z"),IF(AND(TRIM(C58)<>"",MID(TRIM(D58),3,10)=TRIM(C58)),"Valid","PAN Mismatch"),"Invalid")) -> Valid | O58: =IF(TRIM(E58)="","Missing",IF(AND(ISNUMBER(FIND("@",E58)),ISERROR(FIND(" ",TRIM(E58))),IFERROR(FIND(".",E58,FIND("@",E58)),0)>0),"Valid","Invalid")) -> Valid | P58: =IF(TRIM(F58)="","Missing",IFERROR(IF(AND(ISNUMBER(--V58),OR(LEN(V58)=10,AND(LEN(V58)=12,LEFT(V58,2)="91")),VALUE(LEFT(RIGHT(V58,10),1))>=6),"Valid","Invalid"),"Invalid")) -> Valid | Q58: =IF(TRIM(G58)="","Missing",IFERROR(IF(AND(ISNUMBER(--TRIM(G58)),LEN(TRIM(G58))>=9,LEN(TRIM(G58))<=18,ISERROR(FIND(".",G58))),"Valid","Invalid"),"Invalid")) -> Valid | R58: =IF(TRIM(H58)="","Missing",IF(AND(LEN(TRIM(H58))=11,SUMPRODUCT(--(CODE(MID(TRIM(H58),{1,2,3,4},1))>=65),--(CODE(MID(TRIM(H58),{1,2,3,4},1))<=90))=4,MID(TRIM(H58),5,1)="0"),"Valid","Invalid")) -> Valid | S58: =IF(TRIM(I58)="","Missing",IF(EXACT(TRIM(I58),"India"),"Valid","Invalid")) -> Valid | T58: =IF(TRIM(J58)="","Missing",IF(OR(EXACT(TRIM(J58),"Net 15"),EXACT(TRIM(J58),"Net 30"),EXACT(TRIM(J58),"Net 45"),EXACT(TRIM(J58),"Net 60")),"Valid","Invalid")) -> Invalid | U58: =COUNTIF(M58:T58,"<>Valid") -> 1 | V58: =SUBSTITUTE(SUBSTITUTE(SUBSTITUTE(F58," ",""),"-",""),"+","") -> 916792904904 | W58: V1143 | X58: =IF(COUNTIF($W$2:$W$229,W58)>1,"Duplicate","Unique") -> Unique
A59: V1112 | B59: Falcon Housekeeping Limited | C59: frich4795l | D59: 29FRICH4795L1Z5 | E59: accounts@falconhousekeeping.in | F59: +91 76556 47292 | G59: 143866322702 | H59: UTIB0728857 | I59: India | J59: Net 45 | K59: Active | L59: 2019-07-15 | M59: =IF(TRIM(C59)="","Missing",IF(AND(LEN(TRIM(C59))=10,SUMPRODUCT(--(CODE(MID(TRIM(C59),{1,2,3,4,5,10},1))>=65),--(CODE(MID(TRIM(C59),{1,2,3,4,5,10},1))<=90))=6,ISNUMBER(--MID(TRIM(C59),6,4))),"Valid","Invalid")) -> Invalid | N59: =IF(TRIM(D59)="","Missing",IF(AND(LEN(TRIM(D59))=15,MID(TRIM(D59),14,1)="Z"),IF(AND(TRIM(C59)<>"",MID(TRIM(D59),3,10)=TRIM(C59)),"Valid","PAN Mismatch"),"Invalid")) -> Valid | O59: =IF(TRIM(E59)="","Missing",IF(AND(ISNUMBER(FIND("@",E59)),ISERROR(FIND(" ",TRIM(E59))),IFERROR(FIND(".",E59,FIND("@",E59)),0)>0),"Valid","Invalid")) -> Valid | P59: =IF(TRIM(F59)="","Missing",IFERROR(IF(AND(ISNUMBER(--V59),OR(LEN(V59)=10,AND(LEN(V59)=12,LEFT(V59,2)="91")),VALUE(LEFT(RIGHT(V59,10),1))>=6),"Valid","Invalid"),"Invalid")) -> Valid | Q59: =IF(TRIM(G59)="","Missing",IFERROR(IF(AND(ISNUMBER(--TRIM(G59)),LEN(TRIM(G59))>=9,LEN(TRIM(G59))<=18,ISERROR(FIND(".",G59))),"Valid","Invalid"),"Invalid")) -> Valid | R59: =IF(TRIM(H59)="","Missing",IF(AND(LEN(TRIM(H59))=11,SUMPRODUCT(--(CODE(MID(TRIM(H59),{1,2,3,4},1))>=65),--(CODE(MID(TRIM(H59),{1,2,3,4},1))<=90))=4,MID(TRIM(H59),5,1)="0"),"Valid","Invalid")) -> Valid | S59: =IF(TRIM(I59)="","Missing",IF(EXACT(TRIM(I59),"India"),"Valid","Invalid")) -> Valid | T59: =IF(TRIM(J59)="","Missing",IF(OR(EXACT(TRIM(J59),"Net 15"),EXACT(TRIM(J59),"Net 30"),EXACT(TRIM(J59),"Net 45"),EXACT(TRIM(J59),"Net 60")),"Valid","Invalid")) -> Valid | U59: =COUNTIF(M59:T59,"<>Valid") -> 1 | V59: =SUBSTITUTE(SUBSTITUTE(SUBSTITUTE(F59," ",""),"-",""),"+","") -> 917655647292 | W59: V1112 | X59: =IF(COUNTIF($W$2:$W$229,W59)>1,"Duplicate","Unique") -> Unique
A60: V1178 | B60: Redwood Engineering Works Pvt Ltd | C60: SVSCG9089F | D60: 07SVSCG9089F1ZE | E60: accounts@redwoodengineeringworks.in | F60: 91504-16591 | G60: 2017774905097 | H60: SBIN0923045 | I60: India | J60: net 15 | K60: Active | L60: 2025-02-19 | M60: =IF(TRIM(C60)="","Missing",IF(AND(LEN(TRIM(C60))=10,SUMPRODUCT(--(CODE(MID(TRIM(C60),{1,2,3,4,5,10},1))>=65),--(CODE(MID(TRIM(C60),{1,2,3,4,5,10},1))<=90))=6,ISNUMBER(--MID(TRIM(C60),6,4))),"Valid","Invalid")) -> Valid | N60: =IF(TRIM(D60)="","Missing",IF(AND(LEN(TRIM(D60))=15,MID(TRIM(D60),14,1)="Z"),IF(AND(TRIM(C60)<>"",MID(TRIM(D60),3,10)=TRIM(C60)),"Valid","PAN Mismatch"),"Invalid")) -> Valid | O60: =IF(TRIM(E60)="","Missing",IF(AND(ISNUMBER(FIND("@",E60)),ISERROR(FIND(" ",TRIM(E60))),IFERROR(FIND(".",E60,FIND("@",E60)),0)>0),"Valid","Invalid")) -> Valid | P60: =IF(TRIM(F60)="","Missing",IFERROR(IF(AND(ISNUMBER(--V60),OR(LEN(V60)=10,AND(LEN(V60)=12,LEFT(V60,2)="91")),VALUE(LEFT(RIGHT(V60,10),1))>=6),"Valid","Invalid"),"Invalid")) -> Valid | Q60: =IF(TRIM(G60)="","Missing",IFERROR(IF(AND(ISNUMBER(--TRIM(G60)),LEN(TRIM(G60))>=9,LEN(TRIM(G60))<=18,ISERROR(FIND(".",G60))),"Valid","Invalid"),"Invalid")) -> Valid | R60: =IF(TRIM(H60)="","Missing",IF(AND(LEN(TRIM(H60))=11,SUMPRODUCT(--(CODE(MID(TRIM(H60),{1,2,3,4},1))>=65),--(CODE(MID(TRIM(H60),{1,2,3,4},1))<=90))=4,MID(TRIM(H60),5,1)="0"),"Valid","Invalid")) -> Valid | S60: =IF(TRIM(I60)="","Missing",IF(EXACT(TRIM(I60),"India"),"Valid","Invalid")) -> Valid | T60: =IF(TRIM(J60)="","Missing",IF(OR(EXACT(TRIM(J60),"Net 15"),EXACT(TRIM(J60),"Net 30"),EXACT(TRIM(J60),"Net 45"),EXACT(TRIM(J60),"Net 60")),"Valid","Invalid")) -> Invalid | U60: =COUNTIF(M60:T60,"<>Valid") -> 1 | V60: =SUBSTITUTE(SUBSTITUTE(SUBSTITUTE(F60," ",""),"-",""),"+","") -> 9150416591 | W60: V1178 | X60: =IF(COUNTIF($W$2:$W$229,W60)>1,"Duplicate","Unique") -> Unique
A61: V1227 | B61: Pinnacle Engneering Works Private Limited | E61: accounts@pinnacleengineeringworks.in | F61: 87700-54119 | G61: 79807935978207 | H61: HDFC1518203 | I61: India | J61: net 60 | K61: Active | L61: 2026-03-04 | M61: =IF(TRIM(C61)="","Missing",IF(AND(LEN(TRIM(C61))=10,SUMPRODUCT(--(CODE(MID(TRIM(C61),{1,2,3,4,5,10},1))>=65),--(CODE(MID(TRIM(C61),{1,2,3,4,5,10},1))<=90))=6,ISNUMBER(--MID(TRIM(C61),6,4))),"Valid","Invalid")) -> Missing | N61: =IF(TRIM(D61)="","Missing",IF(AND(LEN(TRIM(D61))=15,MID(TRIM(D61),14,1)="Z"),IF(AND(TRIM(C61)<>"",MID(TRIM(D61),3,10)=TRIM(C61)),"Valid","PAN Mismatch"),"Invalid")) -> Missing | O61: =IF(TRIM(E61)="","Missing",IF(AND(ISNUMBER(FIND("@",E61)),ISERROR(FIND(" ",TRIM(E61))),IFERROR(FIND(".",E61,FIND("@",E61)),0)>0),"Valid","Invalid")) -> Valid | P61: =IF(TRIM(F61)="","Missing",IFERROR(IF(AND(ISNUMBER(--V61),OR(LEN(V61)=10,AND(LEN(V61)=12,LEFT(V61,2)="91")),VALUE(LEFT(RIGHT(V61,10),1))>=6),"Valid","Invalid"),"Invalid")) -> Valid | Q61: =IF(TRIM(G61)="","Missing",IFERROR(IF(AND(ISNUMBER(--TRIM(G61)),LEN(TRIM(G61))>=9,LEN(TRIM(G61))<=18,ISERROR(FIND(".",G61))),"Valid","Invalid"),"Invalid")) -> Valid | R61: =IF(TRIM(H61)="","Missing",IF(AND(LEN(TRIM(H61))=11,SUMPRODUCT(--(CODE(MID(TRIM(H61),{1,2,3,4},1))>=65),--(CODE(MID(TRIM(H61),{1,2,3,4},1))<=90))=4,MID(TRIM(H61),5,1)="0"),"Valid","Invalid")) -> Invalid | S61: =IF(TRIM(I61)="","Missing",IF(EXACT(TRIM(I61),"India"),"Valid","Invalid")) -> Valid | T61: =IF(TRIM(J61)="","Missing",IF(OR(EXACT(TRIM(J61),"Net 15"),EXACT(TRIM(J61),"Net 30"),EXACT(TRIM(J61),"Net 45"),EXACT(TRIM(J61),"Net 60")),"Valid","Invalid")) -> Invalid | U61: =COUNTIF(M61:T61,"<>Valid") -> 4 | V61: =SUBSTITUTE(SUBSTITUTE(SUBSTITUTE(F61," ",""),"-",""),"+","") -> 8770054119 | W61: V1227 | X61: =IF(COUNTIF($W$2:$W$229,W61)>1,"Duplicate","Unique") -> Unique
A62: V1149 | B62: Aaryan Power Systems LLP | C62: PUACP9032A | D62: 29PUACP9032A1ZD | F62: +91 67929 11179 | G62: 136565198253 | H62: hdfc0925114 | I62: India | J62: 30 Days | K62: Active | L62: 2020-11-19 | M62: =IF(TRIM(C62)="","Missing",IF(AND(LEN(TRIM(C62))=10,SUMPRODUCT(--(CODE(MID(TRIM(C62),{1,2,3,4,5,10},1))>=65),--(CODE(MID(TRIM(C62),{1,2,3,4,5,10},1))<=90))=6,ISNUMBER(--MID(TRIM(C62),6,4))),"Valid","Invalid")) -> Valid | N62: =IF(TRIM(D62)="","Missing",IF(AND(LEN(TRIM(D62))=15,MID(TRIM(D62),14,1)="Z"),IF(AND(TRIM(C62)<>"",MID(TRIM(D62),3,10)=TRIM(C62)),"Valid","PAN Mismatch"),"Invalid")) -> Valid | O62: =IF(TRIM(E62)="","Missing",IF(AND(ISNUMBER(FIND("@",E62)),ISERROR(FIND(" ",TRIM(E62))),IFERROR(FIND(".",E62,FIND("@",E62)),0)>0),"Valid","Invalid")) -> Missing | P62: =IF(TRIM(F62)="","Missing",IFERROR(IF(AND(ISNUMBER(--V62),OR(LEN(V62)=10,AND(LEN(V62)=12,LEFT(V62,2)="91")),VALUE(LEFT(RIGHT(V62,10),1))>=6),"Valid","Invalid"),"Invalid")) -> Valid | Q62: =IF(TRIM(G62)="","Missing",IFERROR(IF(AND(ISNUMBER(--TRIM(G62)),LEN(TRIM(G62))>=9,LEN(TRIM(G62))<=18,ISERROR(FIND(".",G62))),"Valid","Invalid"),"Invalid")) -> Valid | R62: =IF(TRIM(H62)="","Missing",IF(AND(LEN(TRIM(H62))=11,SUMPRODUCT(--(CODE(MID(TRIM(H62),{1,2,3,4},1))>=65),--(CODE(MID(TRIM(H62),{1,2,3,4},1))<=90))=4,MID(TRIM(H62),5,1)="0"),"Valid","Invalid")) -> Invalid | S62: =IF(TRIM(I62)="","Missing",IF(EXACT(TRIM(I62),"India"),"Valid","Invalid")) -> Valid | T62: =IF(TRIM(J62)="","Missing",IF(OR(EXACT(TRIM(J62),"Net 15"),EXACT(TRIM(J62),"Net 30"),EXACT(TRIM(J62),"Net 45"),EXACT(TRIM(J62),"Net 60")),"Valid","Invalid")) -> Invalid | U62: =COUNTIF(M62:T62,"<>Valid") -> 3 | V62: =SUBSTITUTE(SUBSTITUTE(SUBSTITUTE(F62," ",""),"-",""),"+","") -> 916792911179 | W62: V1149 | X62: =IF(COUNTIF($W$2:$W$229,W62)>1,"Duplicate","Unique") -> Unique
A63: V1165 | B63: Apex IT Services Limited | C63: gczcp5207v | D63: 27GCZCP5207V1ZZ | E63: accounts@apexitservices.in | F63: 6126691215 | G63: 539613674994 | H63: UTIB0579678 | I63: India | J63: Net 45 | K63: Active | L63: 2024-02-06 | M63: =IF(TRIM(C63)="","Missing",IF(AND(LEN(TRIM(C63))=10,SUMPRODUCT(--(CODE(MID(TRIM(C63),{1,2,3,4,5,10},1))>=65),--(CODE(MID(TRIM(C63),{1,2,3,4,5,10},1))<=90))=6,ISNUMBER(--MID(TRIM(C63),6,4))),"Valid","Invalid")) -> Invalid | N63: =IF(TRIM(D63)="","Missing",IF(AND(LEN(TRIM(D63))=15,MID(TRIM(D63),14,1)="Z"),IF(AND(TRIM(C63)<>"",MID(TRIM(D63),3,10)=TRIM(C63)),"Valid","PAN Mismatch"),"Invalid")) -> Valid | O63: =IF(TRIM(E63)="","Missing",IF(AND(ISNUMBER(FIND("@",E63)),ISERROR(FIND(" ",TRIM(E63))),IFERROR(FIND(".",E63,FIND("@",E63)),0)>0),"Valid","Invalid")) -> Valid | P63: =IF(TRIM(F63)="","Missing",IFERROR(IF(AND(ISNUMBER(--V63),OR(LEN(V63)=10,AND(LEN(V63)=12,LEFT(V63,2)="91")),VALUE(LEFT(RIGHT(V63,10),1))>=6),"Valid","Invalid"),"Invalid")) -> Valid | Q63: =IF(TRIM(G63)="","Missing",IFERROR(IF(AND(ISNUMBER(--TRIM(G63)),LEN(TRIM(G63))>=9,LEN(TRIM(G63))<=18,ISERROR(FIND(".",G63))),"Valid","Invalid"),"Invalid")) -> Valid | R63: =IF(TRIM(H63)="","Missing",IF(AND(LEN(TRIM(H63))=11,SUMPRODUCT(--(CODE(MID(TRIM(H63),{1,2,3,4},1))>=65),--(CODE(MID(TRIM(H63),{1,2,3,4},1))<=90))=4,MID(TRIM(H63),5,1)="0"),"Valid","Invalid")) -> Valid | S63: =IF(TRIM(I63)="","Missing",IF(EXACT(TRIM(I63),"India"),"Valid","Invalid")) -> Valid | T63: =IF(TRIM(J63)="","Missing",IF(OR(EXACT(TRIM(J63),"Net 15"),EXACT(TRIM(J63),"Net 30"),EXACT(TRIM(J63),"Net 45"),EXACT(TRIM(J63),"Net 60")),"Valid","Invalid")) -> Valid | U63: =COUNTIF(M63:T63,"<>Valid") -> 1 | V63: =SUBSTITUTE(SUBSTITUTE(SUBSTITUTE(F63," ",""),"-",""),"+","") -> 6126691215 | W63: V1165 | X63: =IF(COUNTIF($W$2:$W$229,W63)>1,"Duplicate","Unique") -> Unique
A64: V1219 | B64: Unity Logis. LLP | C64: IMKCJ7226T | D64: 36IMKCJ7226T1Z6 | E64: accounts@unitylogistics.in | F64: 88333-94522 | G64: 1587996846081 | H64: HDFC0620034 | I64: IN | J64: net 30 | K64: Active | L64: 2024-02-09 | M64: =IF(TRIM(C64)="","Missing",IF(AND(LEN(TRIM(C64))=10,SUMPRODUCT(--(CODE(MID(TRIM(C64),{1,2,3,4,5,10},1))>=65),--(CODE(MID(TRIM(C64),{1,2,3,4,5,10},1))<=90))=6,ISNUMBER(--MID(TRIM(C64),6,4))),"Valid","Invalid")) -> Valid | N64: =IF(TRIM(D64)="","Missing",IF(AND(LEN(TRIM(D64))=15,MID(TRIM(D64),14,1)="Z"),IF(AND(TRIM(C64)<>"",MID(TRIM(D64),3,10)=TRIM(C64)),"Valid","PAN Mismatch"),"Invalid")) -> Valid | O64: =IF(TRIM(E64)="","Missing",IF(AND(ISNUMBER(FIND("@",E64)),ISERROR(FIND(" ",TRIM(E64))),IFERROR(FIND(".",E64,FIND("@",E64)),0)>0),"Valid","Invalid")) -> Valid | P64: =IF(TRIM(F64)="","Missing",IFERROR(IF(AND(ISNUMBER(--V64),OR(LEN(V64)=10,AND(LEN(V64)=12,LEFT(V64,2)="91")),VALUE(LEFT(RIGHT(V64,10),1))>=6),"Valid","Invalid"),"Invalid")) -> Valid | Q64: =IF(TRIM(G64)="","Missing",IFERROR(IF(AND(ISNUMBER(--TRIM(G64)),LEN(TRIM(G64))>=9,LEN(TRIM(G64))<=18,ISERROR(FIND(".",G64))),"Valid","Invalid"),"Invalid")) -> Valid | R64: =IF(TRIM(H64)="","Missing",IF(AND(LEN(TRIM(H64))=11,SUMPRODUCT(--(CODE(MID(TRIM(H64),{1,2,3,4},1))>=65),--(CODE(MID(TRIM(H64),{1,2,3,4},1))<=90))=4,MID(TRIM(H64),5,1)="0"),"Valid","Invalid")) -> Valid | S64: =IF(TRIM(I64)="","Missing",IF(EXACT(TRIM(I64),"India"),"Valid","Invalid")) -> Invalid | T64: =IF(TRIM(J64)="","Missing",IF(OR(EXACT(TRIM(J64),"Net 15"),EXACT(TRIM(J64),"Net 30"),EXACT(TRIM(J64),"Net 45"),EXACT(TRIM(J64),"Net 60")),"Valid","Invalid")) -> Invalid | U64: =COUNTIF(M64:T64,"<>Valid") -> 2 | V64: =SUBSTITUTE(SUBSTITUTE(SUBSTITUTE(F64," ",""),"-",""),"+","") -> 8833394522 | W64: V1095 | X64: =IF(COUNTIF($W$2:$W$229,W64)>1,"Duplicate","Unique") -> Duplicate
A65: V1081 | B65: Metro Landscaping Private Limited | C65: IOOCI3490 | D65: 19IOOCI3490E1ZG | E65: ACCOUNTS@METROLANDSCAPING.IN | F65: 88693-80686 | G65: 93741608989921 | I65: india | J65: 60D | K65: Inactive | L65: 2023-11-19 | M65: =IF(TRIM(C65)="","Missing",IF(AND(LEN(TRIM(C65))=10,SUMPRODUCT(--(CODE(MID(TRIM(C65),{1,2,3,4,5,10},1))>=65),--(CODE(MID(TRIM(C65),{1,2,3,4,5,10},1))<=90))=6,ISNUMBER(--MID(TRIM(C65),6,4))),"Valid","Invalid")) -> #VALUE! | N65: =IF(TRIM(D65)="","Missing",IF(AND(LEN(TRIM(D65))=15,MID(TRIM(D65),14,1)="Z"),IF(AND(TRIM(C65)<>"",MID(TRIM(D65),3,10)=TRIM(C65)),"Valid","PAN Mismatch"),"Invalid")) -> PAN Mismatch | O65: =IF(TRIM(E65)="","Missing",IF(AND(ISNUMBER(FIND("@",E65)),ISERROR(FIND(" ",TRIM(E65))),IFERROR(FIND(".",E65,FIND("@",E65)),0)>0),"Valid","Invalid")) -> Valid | P65: =IF(TRIM(F65)="","Missing",IFERROR(IF(AND(ISNUMBER(--V65),OR(LEN(V65)=10,AND(LEN(V65)=12,LEFT(V65,2)="91")),VALUE(LEFT(RIGHT(V65,10),1))>=6),"Valid","Invalid"),"Invalid")) -> Valid | Q65: =IF(TRIM(G65)="","Missing",IFERROR(IF(AND(ISNUMBER(--TRIM(G65)),LEN(TRIM(G65))>=9,LEN(TRIM(G65))<=18,ISERROR(FIND(".",G65))),"Valid","Invalid"),"Invalid")) -> Valid | R65: =IF(TRIM(H65)="","Missing",IF(AND(LEN(TRIM(H65))=11,SUMPRODUCT(--(CODE(MID(TRIM(H65),{1,2,3,4},1))>=65),--(CODE(MID(TRIM(H65),{1,2,3,4},1))<=90))=4,MID(TRIM(H65),5,1)="0"),"Valid","Invalid")) -> Missing | S65: =IF(TRIM(I65)="","Missing",IF(EXACT(TRIM(I65),"India"),"Valid","Invalid")) -> Invalid | T65: =IF(TRIM(J65)="","Missing",IF(OR(EXACT(TRIM(J65),"Net 15"),EXACT(TRIM(J65),"Net 30"),EXACT(TRIM(J65),"Net 45"),EXACT(TRIM(J65),"Net 60")),"Valid","Invalid")) -> Invalid | U65: =COUNTIF(M65:T65,"<>Valid") -> 5 | V65: =SUBSTITUTE(SUBSTITUTE(SUBSTITUTE(F65," ",""),"-",""),"+","") -> 8869380686 | W65: V1081 | X65: =IF(COUNTIF($W$2:$W$229,W65)>1,"Duplicate","Unique") -> Unique
A66: V1155 | B66: Delta Pest Control Limited | C66: URWCC8325H | D66: 24URWCC8325H1ZH | E66: ACCOUNTS@DELTAPESTCONTROL.IN | F66: 735548640 | G66: 5778817884795 | H66: HDFC0371162 | I66: India | J66: NET45 | K66: Active | L66: 2019-11-12 | M66: =IF(TRIM(C66)="","Missing",IF(AND(LEN(TRIM(C66))=10,SUMPRODUCT(--(CODE(MID(TRIM(C66),{1,2,3,4,5,10},1))>=65),--(CODE(MID(TRIM(C66),{1,2,3,4,5,10},1))<=90))=6,ISNUMBER(--MID(TRIM(C66),6,4))),"Valid","Invalid")) -> Valid | N66: =IF(TRIM(D66)="","Missing",IF(AND(LEN(TRIM(D66))=15,MID(TRIM(D66),14,1)="Z"),IF(AND(TRIM(C66)<>"",MID(TRIM(D66),3,10)=TRIM(C66)),"Valid","PAN Mismatch"),"Invalid")) -> Valid | O66: =IF(TRIM(E66)="","Missing",IF(AND(ISNUMBER(FIND("@",E66)),ISERROR(FIND(" ",TRIM(E66))),IFERROR(FIND(".",E66,FIND("@",E66)),0)>0),"Valid","Invalid")) -> Valid | P66: =IF(TRIM(F66)="","Missing",IFERROR(IF(AND(ISNUMBER(--V66),OR(LEN(V66)=10,AND(LEN(V66)=12,LEFT(V66,2)="91")),VALUE(LEFT(RIGHT(V66,10),1))>=6),"Valid","Invalid"),"Invalid")) -> Invalid | Q66: =IF(TRIM(G66)="","Missing",IFERROR(IF(AND(ISNUMBER(--TRIM(G66)),LEN(TRIM(G66))>=9,LEN(TRIM(G66))<=18,ISERROR(FIND(".",G66))),"Valid","Invalid"),"Invalid")) -> Valid | R66: =IF(TRIM(H66)="","Missing",IF(AND(LEN(TRIM(H66))=11,SUMPRODUCT(--(CODE(MID(TRIM(H66),{1,2,3,4},1))>=65),--(CODE(MID(TRIM(H66),{1,2,3,4},1))<=90))=4,MID(TRIM(H66),5,1)="0"),"Valid","Invalid")) -> Valid | S66: =IF(TRIM(I66)="","Missing",IF(EXACT(TRIM(I66),"India"),"Valid","Invalid")) -> Valid | T66: =IF(TRIM(J66)="","Missing",IF(OR(EXACT(TRIM(J66),"Net 15"),EXACT(TRIM(J66),"Net 30"),EXACT(TRIM(J66),"Net 45"),EXACT(TRIM(J66),"Net 60")),"Valid","Invalid")) -> Invalid | U66: =COUNTIF(M66:T66,"<>Valid") -> 2 | V66: =SUBSTITUTE(SUBSTITUTE(SUBSTITUTE(F66," ",""),"-",""),"+","") -> 735548640 | W66: V1155 | X66: =IF(COUNTIF($W$2:$W$229,W66)>1,"Duplicate","Unique") -> Unique
A67: V1100 | B67: Eastern Stationers Private Limited | C67: XMZCZ8424V | D67: 19XMZCZ8424V1ZX | E67: ACCOUNTS@EASTERNSTATIONERS.IN | F67: +91 71009 96881 | G67: 3536822239431 | H67: ICIC0908781 | I67: India | J67: Net 45 | K67: Active | L67: 2021-10-23 | M67: =IF(TRIM(C67)="","Missing",IF(AND(LEN(TRIM(C67))=10,SUMPRODUCT(--(CODE(MID(TRIM(C67),{1,2,3,4,5,10},1))>=65),--(CODE(MID(TRIM(C67),{1,2,3,4,5,10},1))<=90))=6,ISNUMBER(--MID(TRIM(C67),6,4))),"Valid","Invalid")) -> Valid | N67: =IF(TRIM(D67)="","Missing",IF(AND(LEN(TRIM(D67))=15,MID(TRIM(D67),14,1)="Z"),IF(AND(TRIM(C67)<>"",MID(TRIM(D67),3,10)=TRIM(C67)),"Valid","PAN Mismatch"),"Invalid")) -> Valid | O67: =IF(TRIM(E67)="","Missing",IF(AND(ISNUMBER(FIND("@",E67)),ISERROR(FIND(" ",TRIM(E67))),IFERROR(FIND(".",E67,FIND("@",E67)),0)>0),"Valid","Invalid")) -> Valid | P67: =IF(TRIM(F67)="","Missing",IFERROR(IF(AND(ISNUMBER(--V67),OR(LEN(V67)=10,AND(LEN(V67)=12,LEFT(V67,2)="91")),VALUE(LEFT(RIGHT(V67,10),1))>=6),"Valid","Invalid"),"Invalid")) -> Valid | Q67: =IF(TRIM(G67)="","Missing",IFERROR(IF(AND(ISNUMBER(--TRIM(G67)),LEN(TRIM(G67))>=9,LEN(TRIM(G67))<=18,ISERROR(FIND(".",G67))),"Valid","Invalid"),"Invalid")) -> Valid | R67: =IF(TRIM(H67)="","Missing",IF(AND(LEN(TRIM(H67))=11,SUMPRODUCT(--(CODE(MID(TRIM(H67),{1,2,3,4},1))>=65),--(CODE(MID(TRIM(H67),{1,2,3,4},1))<=90))=4,MID(TRIM(H67),5,1)="0"),"Valid","Invalid")) -> Valid | S67: =IF(TRIM(I67)="","Missing",IF(EXACT(TRIM(I67),"India"),"Valid","Invalid")) -> Valid | T67: =IF(TRIM(J67)="","Missing",IF(OR(EXACT(TRIM(J67),"Net 15"),EXACT(TRIM(J67),"Net 30"),EXACT(TRIM(J67),"Net 45"),EXACT(TRIM(J67),"Net 60")),"Valid","Invalid")) -> Valid | U67: =COUNTIF(M67:T67,"<>Valid") -> 0 | V67: =SUBSTITUTE(SUBSTITUTE(SUBSTITUTE(F67," ",""),"-",""),"+","") -> 917100996881 | W67: V1100 | X67: =IF(COUNTIF($W$2:$W$229,W67)>1,"Duplicate","Unique") -> Unique
A68: V1115 | B68: Jupiter Facility Services Private Limited | C68: JHHCX4722Q | D68: 19JHHCX4722Q1ZK | E68: accounts@jupiterfacilityservices.in | F68: +91 65577 84872 | I68: India | J68: net 45 | K68: Inactive | L68: 2024-11-13 | M68: =IF(TRIM(C68)="","Missing",IF(AND(LEN(TRIM(C68))=10,SUMPRODUCT(--(CODE(MID(TRIM(C68),{1,2,3,4,5,10},1))>=65),--(CODE(MID(TRIM(C68),{1,2,3,4,5,10},1))<=90))=6,ISNUMBER(--MID(TRIM(C68),6,4))),"Valid","Invalid")) -> Valid | N68: =IF(TRIM(D68)="","Missing",IF(AND(LEN(TRIM(D68))=15,MID(TRIM(D68),14,1)="Z"),IF(AND(TRIM(C68)<>"",MID(TRIM(D68),3,10)=TRIM(C68)),"Valid","PAN Mismatch"),"Invalid")) -> Valid | O68: =IF(TRIM(E68)="","Missing",IF(AND(ISNUMBER(FIND("@",E68)),ISERROR(FIND(" ",TRIM(E68))),IFERROR(FIND(".",E68,FIND("@",E68)),0)>0),"Valid","Invalid")) -> Valid | P68: =IF(TRIM(F68)="","Missing",IFERROR(IF(AND(ISNUMBER(--V68),OR(LEN(V68)=10,AND(LEN(V68)=12,LEFT(V68,2)="91")),VALUE(LEFT(RIGHT(V68,10),1))>=6),"Valid","Invalid"),"Invalid")) -> Valid | Q68: =IF(TRIM(G68)="","Missing",IFERROR(IF(AND(ISNUMBER(--TRIM(G68)),LEN(TRIM(G68))>=9,LEN(TRIM(G68))<=18,ISERROR(FIND(".",G68))),"Valid","Invalid"),"Invalid")) -> Missing | R68: =IF(TRIM(H68)="","Missing",IF(AND(LEN(TRIM(H68))=11,SUMPRODUCT(--(CODE(MID(TRIM(H68),{1,2,3,4},1))>=65),--(CODE(MID(TRIM(H68),{1,2,3,4},1))<=90))=4,MID(TRIM(H68),5,1)="0"),"Valid","Invalid")) -> Missing | S68: =IF(TRIM(I68)="","Missing",IF(EXACT(TRIM(I68),"India"),"Valid","Invalid")) -> Valid | T68: =IF(TRIM(J68)="","Missing",IF(OR(EXACT(TRIM(J68),"Net 15"),EXACT(TRIM(J68),"Net 30"),EXACT(TRIM(J68),"Net 45"),EXACT(TRIM(J68),"Net 60")),"Valid","Invalid")) -> Invalid | U68: =COUNTIF(M68:T68,"<>Valid") -> 3 | V68: =SUBSTITUTE(SUBSTITUTE(SUBSTITUTE(F68," ",""),"-",""),"+","") -> 916557784872 | W68: V1115 | X68: =IF(COUNTIF($W$2:$W$229,W68)>1,"Duplicate","Unique") -> Unique
A69: V1034 | B69: Vertex Water Solutions Private Limited | C69: ZTECI0758D | D69: 36ZTECI0758D1Z7 | E69: accounts@vertexwatersolutions.in | F69: 8124782613 | G69: 50606853615305 | I69: India | J69: Net 30 | K69: Active | L69: 2024-04-05 | M69: =IF(TRIM(C69)="","Missing",IF(AND(LEN(TRIM(C69))=10,SUMPRODUCT(--(CODE(MID(TRIM(C69),{1,2,3,4,5,10},1))>=65),--(CODE(MID(TRIM(C69),{1,2,3,4,5,10},1))<=90))=6,ISNUMBER(--MID(TRIM(C69),6,4))),"Valid","Invalid")) -> Valid | N69: =IF(TRIM(D69)="","Missing",IF(AND(LEN(TRIM(D69))=15,MID(TRIM(D69),14,1)="Z"),IF(AND(TRIM(C69)<>"",MID(TRIM(D69),3,10)=TRIM(C69)),"Valid","PAN Mismatch"),"Invalid")) -> Valid | O69: =IF(TRIM(E69)="","Missing",IF(AND(ISNUMBER(FIND("@",E69)),ISERROR(FIND(" ",TRIM(E69))),IFERROR(FIND(".",E69,FIND("@",E69)),0)>0),"Valid","Invalid")) -> Valid | P69: =IF(TRIM(F69)="","Missing",IFERROR(IF(AND(ISNUMBER(--V69),OR(LEN(V69)=10,AND(LEN(V69)=12,LEFT(V69,2)="91")),VALUE(LEFT(RIGHT(V69,10),1))>=6),"Valid","Invalid"),"Invalid")) -> Valid | Q69: =IF(TRIM(G69)="","Missing",IFERROR(IF(AND(ISNUMBER(--TRIM(G69)),LEN(TRIM(G69))>=9,LEN(TRIM(G69))<=18,ISERROR(FIND(".",G69))),"Valid","Invalid"),"Invalid")) -> Valid | R69: =IF(TRIM(H69)="","Missing",IF(AND(LEN(TRIM(H69))=11,SUMPRODUCT(--(CODE(MID(TRIM(H69),{1,2,3,4},1))>=65),--(CODE(MID(TRIM(H69),{1,2,3,4},1))<=90))=4,MID(TRIM(H69),5,1)="0"),"Valid","Invalid")) -> Missing | S69: =IF(TRIM(I69)="","Missing",IF(EXACT(TRIM(I69),"India"),"Valid","Invalid")) -> Valid | T69: =IF(TRIM(J69)="","Missing",IF(OR(EXACT(TRIM(J69),"Net 15"),EXACT(TRIM(J69),"Net 30"),EXACT(TRIM(J69),"Net 45"),EXACT(TRIM(J69),"Net 60")),"Valid","Invalid")) -> Valid | U69: =COUNTIF(M69:T69,"<>Valid") -> 1 | V69: =SUBSTITUTE(SUBSTITUTE(SUBSTITUTE(F69," ",""),"-",""),"+","") -> 8124782613 | W69: V1034 | X69: =IF(COUNTIF($W$2:$W$229,W69)>1,"Duplicate","Unique") -> Unique
A70: V1013 | B70: Titan Landscaping LLP | C70: KAPCK2735Z | D70: 33KAPCK2735Z1ZV | G70: 777014363495 | H70: UTIB0885685 | I70: India | J70: NET45 | K70: Active | L70: 2022-01-14 | M70: =IF(TRIM(C70)="","Missing",IF(AND(LEN(TRIM(C70))=10,SUMPRODUCT(--(CODE(MID(TRIM(C70),{1,2,3,4,5,10},1))>=65),--(CODE(MID(TRIM(C70),{1,2,3,4,5,10},1))<=90))=6,ISNUMBER(--MID(TRIM(C70),6,4))),"Valid","Invalid")) -> Valid | N70: =IF(TRIM(D70)="","Missing",IF(AND(LEN(TRIM(D70))=15,MID(TRIM(D70),14,1)="Z"),IF(AND(TRIM(C70)<>"",MID(TRIM(D70),3,10)=TRIM(C70)),"Valid","PAN Mismatch"),"Invalid")) -> Valid | O70: =IF(TRIM(E70)="","Missing",IF(AND(ISNUMBER(FIND("@",E70)),ISERROR(FIND(" ",TRIM(E70))),IFERROR(FIND(".",E70,FIND("@",E70)),0)>0),"Valid","Invalid")) -> Missing | P70: =IF(TRIM(F70)="","Missing",IFERROR(IF(AND(ISNUMBER(--V70),OR(LEN(V70)=10,AND(LEN(V70)=12,LEFT(V70,2)="91")),VALUE(LEFT(RIGHT(V70,10),1))>=6),"Valid","Invalid"),"Invalid")) -> Missing | Q70: =IF(TRIM(G70)="","Missing",IFERROR(IF(AND(ISNUMBER(--TRIM(G70)),LEN(TRIM(G70))>=9,LEN(TRIM(G70))<=18,ISERROR(FIND(".",G70))),"Valid","Invalid"),"Invalid")) -> Valid | R70: =IF(TRIM(H70)="","Missing",IF(AND(LEN(TRIM(H70))=11,SUMPRODUCT(--(CODE(MID(TRIM(H70),{1,2,3,4},1))>=65),--(CODE(MID(TRIM(H70),{1,2,3,4},1))<=90))=4,MID(TRIM(H70),5,1)="0"),"Valid","Invalid")) -> Valid | S70: =IF(TRIM(I70)="","Missing",IF(EXACT(TRIM(I70),"India"),"Valid","Invalid")) -> Valid | T70: =IF(TRIM(J70)="","Missing",IF(OR(EXACT(TRIM(J70),"Net 15"),EXACT(TRIM(J70),"Net 30"),EXACT(TRIM(J70),"Net 45"),EXACT(TRIM(J70),"Net 60")),"Valid","Invalid")) -> Invalid | U70: =COUNTIF(M70:T70,"<>Valid") -> 3 | V70: =SUBSTITUTE(SUBSTITUTE(SUBSTITUTE(F70," ",""),"-",""),"+","") | W70: V1013 | X70: =IF(COUNTIF($W$2:$W$229,W70)>1,"Duplicate","Unique") -> Unique
A71: V1052 | B71: Jupiter IT Services Limited | C71: UVNCR7056Z | E71: ACCOUNTS@JUPITERITSERVICES.IN | F71: 92462-87334 | G71: 708668826343 | H71: SBIN0175183 | I71: India | J71: 15 Days | K71: Active | L71: 2019-06-11 | M71: =IF(TRIM(C71)="","Missing",IF(AND(LEN(TRIM(C71))=10,SUMPRODUCT(--(CODE(MID(TRIM(C71),{1,2,3,4,5,10},1))>=65),--(CODE(MID(TRIM(C71),{1,2,3,4,5,10},1))<=90))=6,ISNUMBER(--MID(TRIM(C71),6,4))),"Valid","Invalid")) -> Valid | N71: =IF(TRIM(D71)="","Missing",IF(AND(LEN(TRIM(D71))=15,MID(TRIM(D71),14,1)="Z"),IF(AND(TRIM(C71)<>"",MID(TRIM(D71),3,10)=TRIM(C71)),"Valid","PAN Mismatch"),"Invalid")) -> Missing | O71: =IF(TRIM(E71)="","Missing",IF(AND(ISNUMBER(FIND("@",E71)),ISERROR(FIND(" ",TRIM(E71))),IFERROR(FIND(".",E71,FIND("@",E71)),0)>0),"Valid","Invalid")) -> Valid | P71: =IF(TRIM(F71)="","Missing",IFERROR(IF(AND(ISNUMBER(--V71),OR(LEN(V71)=10,AND(LEN(V71)=12,LEFT(V71,2)="91")),VALUE(LEFT(RIGHT(V71,10),1))>=6),"Valid","Invalid"),"Invalid")) -> Valid | Q71: =IF(TRIM(G71)="","Missing",IFERROR(IF(AND(ISNUMBER(--TRIM(G71)),LEN(TRIM(G71))>=9,LEN(TRIM(G71))<=18,ISERROR(FIND(".",G71))),"Valid","Invalid"),"Invalid")) -> Valid | R71: =IF(TRIM(H71)="","Missing",IF(AND(LEN(TRIM(H71))=11,SUMPRODUCT(--(CODE(MID(TRIM(H71),{1,2,3,4},1))>=65),--(CODE(MID(TRIM(H71),{1,2,3,4},1))<=90))=4,MID(TRIM(H71),5,1)="0"),"Valid","Invalid")) -> Valid | S71: =IF(TRIM(I71)="","Missing",IF(EXACT(TRIM(I71),"India"),"Valid","Invalid")) -> Valid | T71: =IF(TRIM(J71)="","Missing",IF(OR(EXACT(TRIM(J71),"Net 15"),EXACT(TRIM(J71),"Net 30"),EXACT(TRIM(J71),"Net 45"),EXACT(TRIM(J71),"Net 60")),"Valid","Invalid")) -> Invalid | U71: =COUNTIF(M71:T71,"<>Valid") -> 2 | V71: =SUBSTITUTE(SUBSTITUTE(SUBSTITUTE(F71," ",""),"-",""),"+","") -> 9246287334 | W71: V1052 | X71: =IF(COUNTIF($W$2:$W$229,W71)>1,"Duplicate","Unique") -> Unique
A72: V1055 | B72: Titan Power Systems LLP | C72: VPACA8860A | D72: 24VPACA8860A1ZR | E72: accounts@titanpowersystems.in | F72: 68621-18233 | G72: 5461567933410 | H72: HDFC1666870 | I72: India | J72: 15D | K72: Active | L72: 2019-12-05 | M72: =IF(TRIM(C72)="","Missing",IF(AND(LEN(TRIM(C72))=10,SUMPRODUCT(--(CODE(MID(TRIM(C72),{1,2,3,4,5,10},1))>=65),--(CODE(MID(TRIM(C72),{1,2,3,4,5,10},1))<=90))=6,ISNUMBER(--MID(TRIM(C72),6,4))),"Valid","Invalid")) -> Valid | N72: =IF(TRIM(D72)="","Missing",IF(AND(LEN(TRIM(D72))=15,MID(TRIM(D72),14,1)="Z"),IF(AND(TRIM(C72)<>"",MID(TRIM(D72),3,10)=TRIM(C72)),"Valid","PAN Mismatch"),"Invalid")) -> Valid | O72: =IF(TRIM(E72)="","Missing",IF(AND(ISNUMBER(FIND("@",E72)),ISERROR(FIND(" ",TRIM(E72))),IFERROR(FIND(".",E72,FIND("@",E72)),0)>0),"Valid","Invalid")) -> Valid | P72: =IF(TRIM(F72)="","Missing",IFERROR(IF(AND(ISNUMBER(--V72),OR(LEN(V72)=10,AND(LEN(V72)=12,LEFT(V72,2)="91")),VALUE(LEFT(RIGHT(V72,10),1))>=6),"Valid","Invalid"),"Invalid")) -> Valid | Q72: =IF(TRIM(G72)="","Missing",IFERROR(IF(AND(ISNUMBER(--TRIM(G72)),LEN(TRIM(G72))>=9,LEN(TRIM(G72))<=18,ISERROR(FIND(".",G72))),"Valid","Invalid"),"Invalid")) -> Valid | R72: =IF(TRIM(H72)="","Missing",IF(AND(LEN(TRIM(H72))=11,SUMPRODUCT(--(CODE(MID(TRIM(H72),{1,2,3,4},1))>=65),--(CODE(MID(TRIM(H72),{1,2,3,4},1))<=90))=4,MID(TRIM(H72),5,1)="0"),"Valid","Invalid")) -> Invalid | S72: =IF(TRIM(I72)="","Missing",IF(EXACT(TRIM(I72),"India"),"Valid","Invalid")) -> Valid | T72: =IF(TRIM(J72)="","Missing",IF(OR(EXACT(TRIM(J72),"Net 15"),EXACT(TRIM(J72),"Net 30"),EXACT(TRIM(J72),"Net 45"),EXACT(TRIM(J72),"Net 60")),"Valid","Invalid")) -> Invalid | U72: =COUNTIF(M72:T72,"<>Valid") -> 2 | V72: =SUBSTITUTE(SUBSTITUTE(SUBSTITUTE(F72," ",""),"-",""),"+","") -> 6862118233 | W72: V1055 | X72: =IF(COUNTIF($W$2:$W$229,W72)>1,"Duplicate","Unique") -> Unique
A73: V1154 | B73: Sunrise Water Solutions Limited | C73: HUCCA7427S | E73: accounts@sunrisewatersolutions.in | F73: +91 92625 70165 | G73: 46498931950 | H73: KKBK0501657 | I73: India | J73: Net 15 | K73: Active | L73: 2020-12-18 | M73: =IF(TRIM(C73)="","Missing",IF(AND(LEN(TRIM(C73))=10,SUMPRODUCT(--(CODE(MID(TRIM(C73),{1,2,3,4,5,10},1))>=65),--(CODE(MID(TRIM(C73),{1,2,3,4,5,10},1))<=90))=6,ISNUMBER(--MID(TRIM(C73),6,4))),"Valid","Invalid")) -> Valid | N73: =IF(TRIM(D73)="","Missing",IF(AND(LEN(TRIM(D73))=15,MID(TRIM(D73),14,1)="Z"),IF(AND(TRIM(C73)<>"",MID(TRIM(D73),3,10)=TRIM(C73)),"Valid","PAN Mismatch"),"Invalid")) -> Missing | O73: =IF(TRIM(E73)="","Missing",IF(AND(ISNUMBER(FIND("@",E73)),ISERROR(FIND(" ",TRIM(E73))),IFERROR(FIND(".",E73,FIND("@",E73)),0)>0),"Valid","Invalid")) -> Valid | P73: =IF(TRIM(F73)="","Missing",IFERROR(IF(AND(ISNUMBER(--V73),OR(LEN(V73)=10,AND(LEN(V73)=12,LEFT(V73,2)="91")),VALUE(LEFT(RIGHT(V73,10),1))>=6),"Valid","Invalid"),"Invalid")) -> Valid | Q73: =IF(TRIM(G73)="","Missing",IFERROR(IF(AND(ISNUMBER(--TRIM(G73)),LEN(TRIM(G73))>=9,LEN(TRIM(G73))<=18,ISERROR(FIND(".",G73))),"Valid","Invalid"),"Invalid")) -> Valid | R73: =IF(TRIM(H73)="","Missing",IF(AND(LEN(TRIM(H73))=11,SUMPRODUCT(--(CODE(MID(TRIM(H73),{1,2,3,4},1))>=65),--(CODE(MID(TRIM(H73),{1,2,3,4},1))<=90))=4,MID(TRIM(H73),5,1)="0"),"Valid","Invalid")) -> Valid | S73: =IF(TRIM(I73)="","Missing",IF(EXACT(TRIM(I73),"India"),"Valid","Invalid")) -> Valid | T73: =IF(TRIM(J73)="","Missing",IF(OR(EXACT(TRIM(J73),"Net 15"),EXACT(TRIM(J73),"Net 30"),EXACT(TRIM(J73),"Net 45"),EXACT(TRIM(J73),"Net 60")),"Valid","Invalid")) -> Valid | U73: =COUNTIF(M73:T73,"<>Valid") -> 1 | V73: =SUBSTITUTE(SUBSTITUTE(SUBSTITUTE(F73," ",""),"-",""),"+","") -> 919262570165 | W73: V1154 | X73: =IF(COUNTIF($W$2:$W$229,W73)>1,"Duplicate","Unique") -> Unique
A74: V1159 | B74: Unity IT Services LLP | C74: BVLCM2656L | D74: 27BVLCM2656L1ZS | E74: ACCOUNTS@UNITYITSERVICES.IN | F74: 8478137674 | G74: 662991234785 | H74: HDFC0961064 | I74: India | J74: 60D | K74: Active | L74: 2024-03-07 | M74: =IF(TRIM(C74)="","Missing",IF(AND(LEN(TRIM(C74))=10,SUMPRODUCT(--(CODE(MID(TRIM(C74),{1,2,3,4,5,10},1))>=65),--(CODE(MID(TRIM(C74),{1,2,3,4,5,10},1))<=90))=6,ISNUMBER(--MID(TRIM(C74),6,4))),"Valid","Invalid")) -> Valid | N74: =IF(TRIM(D74)="","Missing",IF(AND(LEN(TRIM(D74))=15,MID(TRIM(D74),14,1)="Z"),IF(AND(TRIM(C74)<>"",MID(TRIM(D74),3,10)=TRIM(C74)),"Valid","PAN Mismatch"),"Invalid")) -> Valid | O74: =IF(TRIM(E74)="","Missing",IF(AND(ISNUMBER(FIND("@",E74)),ISERROR(FIND(" ",TRIM(E74))),IFERROR(FIND(".",E74,FIND("@",E74)),0)>0),"Valid","Invalid")) -> Valid | P74: =IF(TRIM(F74)="","Missing",IFERROR(IF(AND(ISNUMBER(--V74),OR(LEN(V74)=10,AND(LEN(V74)=12,LEFT(V74,2)="91")),VALUE(LEFT(RIGHT(V74,10),1))>=6),"Valid","Invalid"),"Invalid")) -> Valid | Q74: =IF(TRIM(G74)="","Missing",IFERROR(IF(AND(ISNUMBER(--TRIM(G74)),LEN(TRIM(G74))>=9,LEN(TRIM(G74))<=18,ISERROR(FIND(".",G74))),"Valid","Invalid"),"Invalid")) -> Valid | R74: =IF(TRIM(H74)="","Missing",IF(AND(LEN(TRIM(H74))=11,SUMPRODUCT(--(CODE(MID(TRIM(H74),{1,2,3,4},1))>=65),--(CODE(MID(TRIM(H74),{1,2,3,4},1))<=90))=4,MID(TRIM(H74),5,1)="0"),"Valid","Invalid")) -> Valid | S74: =IF(TRIM(I74)="","Missing",IF(EXACT(TRIM(I74),"India"),"Valid","Invalid")) -> Valid | T74: =IF(TRIM(J74)="","Missing",IF(OR(EXACT(TRIM(J74),"Net 15"),EXACT(TRIM(J74),"Net 30"),EXACT(TRIM(J74),"Net 45"),EXACT(TRIM(J74),"Net 60")),"Valid","Invalid")) -> Invalid | U74: =COUNTIF(M74:T74,"<>Valid") -> 1 | V74: =SUBSTITUTE(SUBSTITUTE(SUBSTITUTE(F74," ",""),"-",""),"+","") -> 8478137674 | W74: V1159 | X74: =IF(COUNTIF($W$2:$W$229,W74)>1,"Duplicate","Unique") -> Unique
A75: V1218 | B75: West. Power Systems Pvt Ltd | C75: MAXCT3796M | D75: 27MAXCT3796M1ZN | E75: accounts@westernpowersystems | F75: 819182553 | H75: SBIN0792499 | I75: IN | J75: Net 15 | K75: Active | L75: 2023-12-31 | M75: =IF(TRIM(C75)="","Missing",IF(AND(LEN(TRIM(C75))=10,SUMPRODUCT(--(CODE(MID(TRIM(C75),{1,2,3,4,5,10},1))>=65),--(CODE(MID(TRIM(C75),{1,2,3,4,5,10},1))<=90))=6,ISNUMBER(--MID(TRIM(C75),6,4))),"Valid","Invalid")) -> Valid | N75: =IF(TRIM(D75)="","Missing",IF(AND(LEN(TRIM(D75))=15,MID(TRIM(D75),14,1)="Z"),IF(AND(TRIM(C75)<>"",MID(TRIM(D75),3,10)=TRIM(C75)),"Valid","PAN Mismatch"),"Invalid")) -> Valid | O75: =IF(TRIM(E75)="","Missing",IF(AND(ISNUMBER(FIND("@",E75)),ISERROR(FIND(" ",TRIM(E75))),IFERROR(FIND(".",E75,FIND("@",E75)),0)>0),"Valid","Invalid")) -> Invalid | P75: =IF(TRIM(F75)="","Missing",IFERROR(IF(AND(ISNUMBER(--V75),OR(LEN(V75)=10,AND(LEN(V75)=12,LEFT(V75,2)="91")),VALUE(LEFT(RIGHT(V75,10),1))>=6),"Valid","Invalid"),"Invalid")) -> Invalid | Q75: =IF(TRIM(G75)="","Missing",IFERROR(IF(AND(ISNUMBER(--TRIM(G75)),LEN(TRIM(G75))>=9,LEN(TRIM(G75))<=18,ISERROR(FIND(".",G75))),"Valid","Invalid"),"Invalid")) -> Missing | R75: =IF(TRIM(H75)="","Missing",IF(AND(LEN(TRIM(H75))=11,SUMPRODUCT(--(CODE(MID(TRIM(H75),{1,2,3,4},1))>=65),--(CODE(MID(TRIM(H75),{1,2,3,4},1))<=90))=4,MID(TRIM(H75),5,1)="0"),"Valid","Invalid")) -> Valid | S75: =IF(TRIM(I75)="","Missing",IF(EXACT(TRIM(I75),"India"),"Valid","Invalid")) -> Invalid | T75: =IF(TRIM(J75)="","Missing",IF(OR(EXACT(TRIM(J75),"Net 15"),EXACT(TRIM(J75),"Net 30"),EXACT(TRIM(J75),"Net 45"),EXACT(TRIM(J75),"Net 60")),"Valid","Invalid")) -> Valid | U75: =COUNTIF(M75:T75,"<>Valid") -> 4 | V75: =SUBSTITUTE(SUBSTITUTE(SUBSTITUTE(F75," ",""),"-",""),"+","") -> 819182553 | W75: V1062 | X75: =IF(COUNTIF($W$2:$W$229,W75)>1,"Duplicate","Unique") -> Duplicate
A76: V1061 | B76: Western Landscaping LLP | C76: ELACP1461D | D76: 19ELACP1461D1ZJ | E76: accounts@westernlandscaping.in | F76: 8573875717 | G76: 51401051238282 | H76: SBIN0867362 | I76: India | J76: Net 30 | K76: Active | L76: 2023-11-06 | M76: =IF(TRIM(C76)="","Missing",IF(AND(LEN(TRIM(C76))=10,SUMPRODUCT(--(CODE(MID(TRIM(C76),{1,2,3,4,5,10},1))>=65),--(CODE(MID(TRIM(C76),{1,2,3,4,5,10},1))<=90))=6,ISNUMBER(--MID(TRIM(C76),6,4))),"Valid","Invalid")) -> Valid | N76: =IF(TRIM(D76)="","Missing",IF(AND(LEN(TRIM(D76))=15,MID(TRIM(D76),14,1)="Z"),IF(AND(TRIM(C76)<>"",MID(TRIM(D76),3,10)=TRIM(C76)),"Valid","PAN Mismatch"),"Invalid")) -> Valid | O76: =IF(TRIM(E76)="","Missing",IF(AND(ISNUMBER(FIND("@",E76)),ISERROR(FIND(" ",TRIM(E76))),IFERROR(FIND(".",E76,FIND("@",E76)),0)>0),"Valid","Invalid")) -> Valid | P76: =IF(TRIM(F76)="","Missing",IFERROR(IF(AND(ISNUMBER(--V76),OR(LEN(V76)=10,AND(LEN(V76)=12,LEFT(V76,2)="91")),VALUE(LEFT(RIGHT(V76,10),1))>=6),"Valid","Invalid"),"Invalid")) -> Valid | Q76: =IF(TRIM(G76)="","Missing",IFERROR(IF(AND(ISNUMBER(--TRIM(G76)),LEN(TRIM(G76))>=9,LEN(TRIM(G76))<=18,ISERROR(FIND(".",G76))),"Valid","Invalid"),"Invalid")) -> Valid | R76: =IF(TRIM(H76)="","Missing",IF(AND(LEN(TRIM(H76))=11,SUMPRODUCT(--(CODE(MID(TRIM(H76),{1,2,3,4},1))>=65),--(CODE(MID(TRIM(H76),{1,2,3,4},1))<=90))=4,MID(TRIM(H76),5,1)="0"),"Valid","Invalid")) -> Valid | S76: =IF(TRIM(I76)="","Missing",IF(EXACT(TRIM(I76),"India"),"Valid","Invalid")) -> Valid | T76: =IF(TRIM(J76)="","Missing",IF(OR(EXACT(TRIM(J76),"Net 15"),EXACT(TRIM(J76),"Net 30"),EXACT(TRIM(J76),"Net 45"),EXACT(TRIM(J76),"Net 60")),"Valid","Invalid")) -> Valid | U76: =COUNTIF(M76:T76,"<>Valid") -> 0 | V76: =SUBSTITUTE(SUBSTITUTE(SUBSTITUTE(F76," ",""),"-",""),"+","") -> 8573875717 | W76: V1061 | X76: =IF(COUNTIF($W$2:$W$229,W76)>1,"Duplicate","Unique") -> Unique
A77: V1205 | B77: SUNRISE LANDSCAPING LIMITED | C77: snqcu5498y | D77: 29SNQCU5498Y1ZJ | E77: accounts@sunriselandscaping.in | F77: 8954508920 | G77: 880653331537 | H77: UTIB0959959 | I77: India | J77: NET45 | K77: Active | L77: 2022-04-24 | M77: =IF(TRIM(C77)="","Missing",IF(AND(LEN(TRIM(C77))=10,SUMPRODUCT(--(CODE(MID(TRIM(C77),{1,2,3,4,5,10},1))>=65),--(CODE(MID(TRIM(C77),{1,2,3,4,5,10},1))<=90))=6,ISNUMBER(--MID(TRIM(C77),6,4))),"Valid","Invalid")) -> Invalid | N77: =IF(TRIM(D77)="","Missing",IF(AND(LEN(TRIM(D77))=15,MID(TRIM(D77),14,1)="Z"),IF(AND(TRIM(C77)<>"",MID(TRIM(D77),3,10)=TRIM(C77)),"Valid","PAN Mismatch"),"Invalid")) -> Valid | O77: =IF(TRIM(E77)="","Missing",IF(AND(ISNUMBER(FIND("@",E77)),ISERROR(FIND(" ",TRIM(E77))),IFERROR(FIND(".",E77,FIND("@",E77)),0)>0),"Valid","Invalid")) -> Valid | P77: =IF(TRIM(F77)="","Missing",IFERROR(IF(AND(ISNUMBER(--V77),OR(LEN(V77)=10,AND(LEN(V77)=12,LEFT(V77,2)="91")),VALUE(LEFT(RIGHT(V77,10),1))>=6),"Valid","Invalid"),"Invalid")) -> Valid | Q77: =IF(TRIM(G77)="","Missing",IFERROR(IF(AND(ISNUMBER(--TRIM(G77)),LEN(TRIM(G77))>=9,LEN(TRIM(G77))<=18,ISERROR(FIND(".",G77))),"Valid","Invalid"),"Invalid")) -> Valid | R77: =IF(TRIM(H77)="","Missing",IF(AND(LEN(TRIM(H77))=11,SUMPRODUCT(--(CODE(MID(TRIM(H77),{1,2,3,4},1))>=65),--(CODE(MID(TRIM(H77),{1,2,3,4},1))<=90))=4,MID(TRIM(H77),5,1)="0"),"Valid","Invalid")) -> Valid | S77: =IF(TRIM(I77)="","Missing",IF(EXACT(TRIM(I77),"India"),"Valid","Invalid")) -> Valid | T77: =IF(TRIM(J77)="","Missing",IF(OR(EXACT(TRIM(J77),"Net 15"),EXACT(TRIM(J77),"Net 30"),EXACT(TRIM(J77),"Net 45"),EXACT(TRIM(J77),"Net 60")),"Valid","Invalid")) -> Invalid | U77: =COUNTIF(M77:T77,"<>Valid") -> 2 | V77: =SUBSTITUTE(SUBSTITUTE(SUBSTITUTE(F77," ",""),"-",""),"+","") -> 8954508920 | W77: V1199 | X77: =IF(COUNTIF($W$2:$W$229,W77)>1,"Duplicate","Unique") -> Duplicate
A78: V1130 | B78: Evergreen Facility Services Pvt Ltd | C78: QUWCZ0817O | D78: 19QUWCZ0817O1ZC | E78: ACCOUNTS@EVERGREENFACILITYSERVICES.IN | F78: +91 90868 03476 | G78: 4726490827718 | H78: HDFC0298266 | I78: IN | J78: Net 45 | K78: Active | L78: 2021-01-02 | M78: =IF(TRIM(C78)="","Missing",IF(AND(LEN(TRIM(C78))=10,SUMPRODUCT(--(CODE(MID(TRIM(C78),{1,2,3,4,5,10},1))>=65),--(CODE(MID(TRIM(C78),{1,2,3,4,5,10},1))<=90))=6,ISNUMBER(--MID(TRIM(C78),6,4))),"Valid","Invalid")) -> Valid | N78: =IF(TRIM(D78)="","Missing",IF(AND(LEN(TRIM(D78))=15,MID(TRIM(D78),14,1)="Z"),IF(AND(TRIM(C78)<>"",MID(TRIM(D78),3,10)=TRIM(C78)),"Valid","PAN Mismatch"),"Invalid")) -> Valid | O78: =IF(TRIM(E78)="","Missing",IF(AND(ISNUMBER(FIND("@",E78)),ISERROR(FIND(" ",TRIM(E78))),IFERROR(FIND(".",E78,FIND("@",E78)),0)>0),"Valid","Invalid")) -> Valid | P78: =IF(TRIM(F78)="","Missing",IFERROR(IF(AND(ISNUMBER(--V78),OR(LEN(V78)=10,AND(LEN(V78)=12,LEFT(V78,2)="91")),VALUE(LEFT(RIGHT(V78,10),1))>=6),"Valid","Invalid"),"Invalid")) -> Valid | Q78: =IF(TRIM(G78)="","Missing",IFERROR(IF(AND(ISNUMBER(--TRIM(G78)),LEN(TRIM(G78))>=9,LEN(TRIM(G78))<=18,ISERROR(FIND(".",G78))),"Valid","Invalid"),"Invalid")) -> Valid | R78: =IF(TRIM(H78)="","Missing",IF(AND(LEN(TRIM(H78))=11,SUMPRODUCT(--(CODE(MID(TRIM(H78),{1,2,3,4},1))>=65),--(CODE(MID(TRIM(H78),{1,2,3,4},1))<=90))=4,MID(TRIM(H78),5,1)="0"),"Valid","Invalid")) -> Valid | S78: =IF(TRIM(I78)="","Missing",IF(EXACT(TRIM(I78),"India"),"Valid","Invalid")) -> Invalid | T78: =IF(TRIM(J78)="","Missing",IF(OR(EXACT(TRIM(J78),"Net 15"),EXACT(TRIM(J78),"Net 30"),EXACT(TRIM(J78),"Net 45"),EXACT(TRIM(J78),"Net 60")),"Valid","Invalid")) -> Valid | U78: =COUNTIF(M78:T78,"<>Valid") -> 1 | V78: =SUBSTITUTE(SUBSTITUTE(SUBSTITUTE(F78," ",""),"-",""),"+","") -> 919086803476 | W78: V1130 | X78: =IF(COUNTIF($W$2:$W$229,W78)>1,"Duplicate","Unique") -> Unique
A79: V1225 | B79: Falcon Houekeeping Limited | E79: ACCOUNTS@FALCONHOUSEKEEPING.IN | F79: 792407553 | H79: UTIB0728857 | I79: India | J79: Net 45 | K79: Active | L79: 2021-04-06 | M79: =IF(TRIM(C79)="","Missing",IF(AND(LEN(TRIM(C79))=10,SUMPRODUCT(--(CODE(MID(TRIM(C79),{1,2,3,4,5,10},1))>=65),--(CODE(MID(TRIM(C79),{1,2,3,4,5,10},1))<=90))=6,ISNUMBER(--MID(TRIM(C79),6,4))),"Valid","Invalid")) -> Missing | N79: =IF(TRIM(D79)="","Missing",IF(AND(LEN(TRIM(D79))=15,MID(TRIM(D79),14,1)="Z"),IF(AND(TRIM(C79)<>"",MID(TRIM(D79),3,10)=TRIM(C79)),"Valid","PAN Mismatch"),"Invalid")) -> Missing | O79: =IF(TRIM(E79)="","Missing",IF(AND(ISNUMBER(FIND("@",E79)),ISERROR(FIND(" ",TRIM(E79))),IFERROR(FIND(".",E79,FIND("@",E79)),0)>0),"Valid","Invalid")) -> Valid | P79: =IF(TRIM(F79)="","Missing",IFERROR(IF(AND(ISNUMBER(--V79),OR(LEN(V79)=10,AND(LEN(V79)=12,LEFT(V79,2)="91")),VALUE(LEFT(RIGHT(V79,10),1))>=6),"Valid","Invalid"),"Invalid")) -> Invalid | Q79: =IF(TRIM(G79)="","Missing",IFERROR(IF(AND(ISNUMBER(--TRIM(G79)),LEN(TRIM(G79))>=9,LEN(TRIM(G79))<=18,ISERROR(FIND(".",G79))),"Valid","Invalid"),"Invalid")) -> Missing | R79: =IF(TRIM(H79)="","Missing",IF(AND(LEN(TRIM(H79))=11,SUMPRODUCT(--(CODE(MID(TRIM(H79),{1,2,3,4},1))>=65),--(CODE(MID(TRIM(H79),{1,2,3,4},1))<=90))=4,MID(TRIM(H79),5,1)="0"),"Valid","Invalid")) -> Valid | S79: =IF(TRIM(I79)="","Missing",IF(EXACT(TRIM(I79),"India"),"Valid","Invalid")) -> Valid | T79: =IF(TRIM(J79)="","Missing",IF(OR(EXACT(TRIM(J79),"Net 15"),EXACT(TRIM(J79),"Net 30"),EXACT(TRIM(J79),"Net 45"),EXACT(TRIM(J79),"Net 60")),"Valid","Invalid")) -> Valid | U79: =COUNTIF(M79:T79,"<>Valid") -> 4 | V79: =SUBSTITUTE(SUBSTITUTE(SUBSTITUTE(F79," ",""),"-",""),"+","") -> 792407553 | W79: V1225 | X79: =IF(COUNTIF($W$2:$W$229,W79)>1,"Duplicate","Unique") -> Unique
A80: V1138 | B80: Titan Engineering Works LLP | C80: DMBCC6629S | D80: 36DMBCC6629S1Z2 | E80: accounts@titanengineeringworks.in | F80: +91 85381 79217 | G80: 74773329456 | H80: ICIC0557701 | I80: India | J80: net 60 | K80: Active | L80: 2024-05-14 | M80: =IF(TRIM(C80)="","Missing",IF(AND(LEN(TRIM(C80))=10,SUMPRODUCT(--(CODE(MID(TRIM(C80),{1,2,3,4,5,10},1))>=65),--(CODE(MID(TRIM(C80),{1,2,3,4,5,10},1))<=90))=6,ISNUMBER(--MID(TRIM(C80),6,4))),"Valid","Invalid")) -> Valid | N80: =IF(TRIM(D80)="","Missing",IF(AND(LEN(TRIM(D80))=15,MID(TRIM(D80),14,1)="Z"),IF(AND(TRIM(C80)<>"",MID(TRIM(D80),3,10)=TRIM(C80)),"Valid","PAN Mismatch"),"Invalid")) -> Valid | O80: =IF(TRIM(E80)="","Missing",IF(AND(ISNUMBER(FIND("@",E80)),ISERROR(FIND(" ",TRIM(E80))),IFERROR(FIND(".",E80,FIND("@",E80)),0)>0),"Valid","Invalid")) -> Valid | P80: =IF(TRIM(F80)="","Missing",IFERROR(IF(AND(ISNUMBER(--V80),OR(LEN(V80)=10,AND(LEN(V80)=12,LEFT(V80,2)="91")),VALUE(LEFT(RIGHT(V80,10),1))>=6),"Valid","Invalid"),"Invalid")) -> Valid | Q80: =IF(TRIM(G80)="","Missing",IFERROR(IF(AND(ISNUMBER(--TRIM(G80)),LEN(TRIM(G80))>=9,LEN(TRIM(G80))<=18,ISERROR(FIND(".",G80))),"Valid","Invalid"),"Invalid")) -> Valid | R80: =IF(TRIM(H80)="","Missing",IF(AND(LEN(TRIM(H80))=11,SUMPRODUCT(--(CODE(MID(TRIM(H80),{1,2,3,4},1))>=65),--(CODE(MID(TRIM(H80),{1,2,3,4},1))<=90))=4,MID(TRIM(H80),5,1)="0"),"Valid","Invalid")) -> Valid | S80: =IF(TRIM(I80)="","Missing",IF(EXACT(TRIM(I80),"India"),"Valid","Invalid")) -> Valid | T80: =IF(TRIM(J80)="","Missing",IF(OR(EXACT(TRIM(J80),"Net 15"),EXACT(TRIM(J80),"Net 30"),EXACT(TRIM(J80),"Net 45"),EXACT(TRIM(J80),"Net 60")),"Valid","Invalid")) -> Invalid | U80: =COUNTIF(M80:T80,"<>Valid") -> 1 | V80: =SUBSTITUTE(SUBSTITUTE(SUBSTITUTE(F80," ",""),"-",""),"+","") -> 918538179217 | W80: V1138 | X80: =IF(COUNTIF($W$2:$W$229,W80)>1,"Duplicate","Unique") -> Unique
A81: V1202 | B81: EASTERN IT SERVICES LIMITED | C81: MMLCY2404W | D81: 27MMLCY2404W1ZW | E81: accounts@easternitservices.in | F81: 7042897317 | G81: 308330165712 | H81: HDFC0826773 | I81: India | J81: 45 Days | K81: Active | L81: 2021-04-30 | M81: =IF(TRIM(C81)="","Missing",IF(AND(LEN(TRIM(C81))=10,SUMPRODUCT(--(CODE(MID(TRIM(C81),{1,2,3,4,5,10},1))>=65),--(CODE(MID(TRIM(C81),{1,2,3,4,5,10},1))<=90))=6,ISNUMBER(--MID(TRIM(C81),6,4))),"Valid","Invalid")) -> Valid | N81: =IF(TRIM(D81)="","Missing",IF(AND(LEN(TRIM(D81))=15,MID(TRIM(D81),14,1)="Z"),IF(AND(TRIM(C81)<>"",MID(TRIM(D81),3,10)=TRIM(C81)),"Valid","PAN Mismatch"),"Invalid")) -> Valid | O81: =IF(TRIM(E81)="","Missing",IF(AND(ISNUMBER(FIND("@",E81)),ISERROR(FIND(" ",TRIM(E81))),IFERROR(FIND(".",E81,FIND("@",E81)),0)>0),"Valid","Invalid")) -> Valid | P81: =IF(TRIM(F81)="","Missing",IFERROR(IF(AND(ISNUMBER(--V81),OR(LEN(V81)=10,AND(LEN(V81)=12,LEFT(V81,2)="91")),VALUE(LEFT(RIGHT(V81,10),1))>=6),"Valid","Invalid"),"Invalid")) -> Valid | Q81: =IF(TRIM(G81)="","Missing",IFERROR(IF(AND(ISNUMBER(--TRIM(G81)),LEN(TRIM(G81))>=9,LEN(TRIM(G81))<=18,ISERROR(FIND(".",G81))),"Valid","Invalid"),"Invalid")) -> Valid | R81: =IF(TRIM(H81)="","Missing",IF(AND(LEN(TRIM(H81))=11,SUMPRODUCT(--(CODE(MID(TRIM(H81),{1,2,3,4},1))>=65),--(CODE(MID(TRIM(H81),{1,2,3,4},1))<=90))=4,MID(TRIM(H81),5,1)="0"),"Valid","Invalid")) -> Valid | S81: =IF(TRIM(I81)="","Missing",IF(EXACT(TRIM(I81),"India"),"Valid","Invalid")) -> Valid | T81: =IF(TRIM(J81)="","Missing",IF(OR(EXACT(TRIM(J81),"Net 15"),EXACT(TRIM(J81),"Net 30"),EXACT(TRIM(J81),"Net 45"),EXACT(TRIM(J81),"Net 60")),"Valid","Invalid")) -> Invalid | U81: =COUNTIF(M81:T81,"<>Valid") -> 1 | V81: =SUBSTITUTE(SUBSTITUTE(SUBSTITUTE(F81," ",""),"-",""),"+","") -> 7042897317 | W81: V1202 | X81: =IF(COUNTIF($W$2:$W$229,W81)>1,"Duplicate","Unique") -> Duplicate
A82: V1098 | B82: Crestline Facility Services Private Limited | D82: 36PRYCU0157H1ZP | E82: accounts@crestlinefacilityservices.in | G82: 70435811288013 | H82: ICIC0613861 | I82: India | J82: net 30 | K82: Inactive | L82: 2022-09-20 | M82: =IF(TRIM(C82)="","Missing",IF(AND(LEN(TRIM(C82))=10,SUMPRODUCT(--(CODE(MID(TRIM(C82),{1,2,3,4,5,10},1))>=65),--(CODE(MID(TRIM(C82),{1,2,3,4,5,10},1))<=90))=6,ISNUMBER(--MID(TRIM(C82),6,4))),"Valid","Invalid")) -> Missing | N82: =IF(TRIM(D82)="","Missing",IF(AND(LEN(TRIM(D82))=15,MID(TRIM(D82),14,1)="Z"),IF(AND(TRIM(C82)<>"",MID(TRIM(D82),3,10)=TRIM(C82)),"Valid","PAN Mismatch"),"Invalid")) -> PAN Mismatch | O82: =IF(TRIM(E82)="","Missing",IF(AND(ISNUMBER(FIND("@",E82)),ISERROR(FIND(" ",TRIM(E82))),IFERROR(FIND(".",E82,FIND("@",E82)),0)>0),"Valid","Invalid")) -> Valid | P82: =IF(TRIM(F82)="","Missing",IFERROR(IF(AND(ISNUMBER(--V82),OR(LEN(V82)=10,AND(LEN(V82)=12,LEFT(V82,2)="91")),VALUE(LEFT(RIGHT(V82,10),1))>=6),"Valid","Invalid"),"Invalid")) -> Missing | Q82: =IF(TRIM(G82)="","Missing",IFERROR(IF(AND(ISNUMBER(--TRIM(G82)),LEN(TRIM(G82))>=9,LEN(TRIM(G82))<=18,ISERROR(FIND(".",G82))),"Valid","Invalid"),"Invalid")) -> Valid | R82: =IF(TRIM(H82)="","Missing",IF(AND(LEN(TRIM(H82))=11,SUMPRODUCT(--(CODE(MID(TRIM(H82),{1,2,3,4},1))>=65),--(CODE(MID(TRIM(H82),{1,2,3,4},1))<=90))=4,MID(TRIM(H82),5,1)="0"),"Valid","Invalid")) -> Valid | S82: =IF(TRIM(I82)="","Missing",IF(EXACT(TRIM(I82),"India"),"Valid","Invalid")) -> Valid | T82: =IF(TRIM(J82)="","Missing",IF(OR(EXACT(TRIM(J82),"Net 15"),EXACT(TRIM(J82),"Net 30"),EXACT(TRIM(J82),"Net 45"),EXACT(TRIM(J82),"Net 60")),"Valid","Invalid")) -> Invalid | U82: =COUNTIF(M82:T82,"<>Valid") -> 4 | V82: =SUBSTITUTE(SUBSTITUTE(SUBSTITUTE(F82," ",""),"-",""),"+","") | W82: V1211 | X82: =IF(COUNTIF($W$2:$W$229,W82)>1,"Duplicate","Unique") -> Duplicate
A83: V1197 | B83: Lotus Electricals LLP | C83: JCUCU1076Z | D83: 27JCUCU1076Z1ZV | E83: ACCOUNTS@LOTUSELECTRICALS.IN | F83: +91 71735 05831 | G83: 17911006512070 | H83: SBIN0961108 | I83: India | J83: Net 15 | K83: Active | L83: 2023-04-12 | M83: =IF(TRIM(C83)="","Missing",IF(AND(LEN(TRIM(C83))=10,SUMPRODUCT(--(CODE(MID(TRIM(C83),{1,2,3,4,5,10},1))>=65),--(CODE(MID(TRIM(C83),{1,2,3,4,5,10},1))<=90))=6,ISNUMBER(--MID(TRIM(C83),6,4))),"Valid","Invalid")) -> Valid | N83: =IF(TRIM(D83)="","Missing",IF(AND(LEN(TRIM(D83))=15,MID(TRIM(D83),14,1)="Z"),IF(AND(TRIM(C83)<>"",MID(TRIM(D83),3,10)=TRIM(C83)),"Valid","PAN Mismatch"),"Invalid")) -> Valid | O83: =IF(TRIM(E83)="","Missing",IF(AND(ISNUMBER(FIND("@",E83)),ISERROR(FIND(" ",TRIM(E83))),IFERROR(FIND(".",E83,FIND("@",E83)),0)>0),"Valid","Invalid")) -> Valid | P83: =IF(TRIM(F83)="","Missing",IFERROR(IF(AND(ISNUMBER(--V83),OR(LEN(V83)=10,AND(LEN(V83)=12,LEFT(V83,2)="91")),VALUE(LEFT(RIGHT(V83,10),1))>=6),"Valid","Invalid"),"Invalid")) -> Valid | Q83: =IF(TRIM(G83)="","Missing",IFERROR(IF(AND(ISNUMBER(--TRIM(G83)),LEN(TRIM(G83))>=9,LEN(TRIM(G83))<=18,ISERROR(FIND(".",G83))),"Valid","Invalid"),"Invalid")) -> Valid | R83: =IF(TRIM(H83)="","Missing",IF(AND(LEN(TRIM(H83))=11,SUMPRODUCT(--(CODE(MID(TRIM(H83),{1,2,3,4},1))>=65),--(CODE(MID(TRIM(H83),{1,2,3,4},1))<=90))=4,MID(TRIM(H83),5,1)="0"),"Valid","Invalid")) -> Valid | S83: =IF(TRIM(I83)="","Missing",IF(EXACT(TRIM(I83),"India"),"Valid","Invalid")) -> Valid | T83: =IF(TRIM(J83)="","Missing",IF(OR(EXACT(TRIM(J83),"Net 15"),EXACT(TRIM(J83),"Net 30"),EXACT(TRIM(J83),"Net 45"),EXACT(TRIM(J83),"Net 60")),"Valid","Invalid")) -> Valid | U83: =COUNTIF(M83:T83,"<>Valid") -> 0 | V83: =SUBSTITUTE(SUBSTITUTE(SUBSTITUTE(F83," ",""),"-",""),"+","") -> 917173505831 | W83: V1197 | X83: =IF(COUNTIF($W$2:$W$229,W83)>1,"Duplicate","Unique") -> Duplicate
A84: V1184 | B84: Bluewave Housekeeping Limited | C84: VPECF3297D | D84: 19VPECF3297D1Z0 | F84: +91 83380 05452 | G84: 801561931837 | H84: SBIN0550842 | I84: India | J84: 15 Days | K84: Active | L84: 2023-11-29 | M84: =IF(TRIM(C84)="","Missing",IF(AND(LEN(TRIM(C84))=10,SUMPRODUCT(--(CODE(MID(TRIM(C84),{1,2,3,4,5,10},1))>=65),--(CODE(MID(TRIM(C84),{1,2,3,4,5,10},1))<=90))=6,ISNUMBER(--MID(TRIM(C84),6,4))),"Valid","Invalid")) -> Valid | N84: =IF(TRIM(D84)="","Missing",IF(AND(LEN(TRIM(D84))=15,MID(TRIM(D84),14,1)="Z"),IF(AND(TRIM(C84)<>"",MID(TRIM(D84),3,10)=TRIM(C84)),"Valid","PAN Mismatch"),"Invalid")) -> Valid | O84: =IF(TRIM(E84)="","Missing",IF(AND(ISNUMBER(FIND("@",E84)),ISERROR(FIND(" ",TRIM(E84))),IFERROR(FIND(".",E84,FIND("@",E84)),0)>0),"Valid","Invalid")) -> Missing | P84: =IF(TRIM(F84)="","Missing",IFERROR(IF(AND(ISNUMBER(--V84),OR(LEN(V84)=10,AND(LEN(V84)=12,LEFT(V84,2)="91")),VALUE(LEFT(RIGHT(V84,10),1))>=6),"Valid","Invalid"),"Invalid")) -> Valid | Q84: =IF(TRIM(G84)="","Missing",IFERROR(IF(AND(ISNUMBER(--TRIM(G84)),LEN(TRIM(G84))>=9,LEN(TRIM(G84))<=18,ISERROR(FIND(".",G84))),"Valid","Invalid"),"Invalid")) -> Valid | R84: =IF(TRIM(H84)="","Missing",IF(AND(LEN(TRIM(H84))=11,SUMPRODUCT(--(CODE(MID(TRIM(H84),{1,2,3,4},1))>=65),--(CODE(MID(TRIM(H84),{1,2,3,4},1))<=90))=4,MID(TRIM(H84),5,1)="0"),"Valid","Invalid")) -> Valid | S84: =IF(TRIM(I84)="","Missing",IF(EXACT(TRIM(I84),"India"),"Valid","Invalid")) -> Valid | T84: =IF(TRIM(J84)="","Missing",IF(OR(EXACT(TRIM(J84),"Net 15"),EXACT(TRIM(J84),"Net 30"),EXACT(TRIM(J84),"Net 45"),EXACT(TRIM(J84),"Net 60")),"Valid","Invalid")) -> Invalid | U84: =COUNTIF(M84:T84,"<>Valid") -> 2 | V84: =SUBSTITUTE(SUBSTITUTE(SUBSTITUTE(F84," ",""),"-",""),"+","") -> 918338005452 | W84: V1184 | X84: =IF(COUNTIF($W$2:$W$229,W84)>1,"Duplicate","Unique") -> Unique
A85: V1035 | B85: Kaveri Security Solutions Limited | C85: OTACC0432R | D85: 36OTACC0432R1Z7 | E85: ACCOUNTS@KAVERISECURITYSOLUTIONS.IN | F85: 6434103697 | G85: 17980893246 | H85: HDFC0953962 | I85: India | J85: 15 Days | K85: Active | L85: 2023-01-17 | M85: =IF(TRIM(C85)="","Missing",IF(AND(LEN(TRIM(C85))=10,SUMPRODUCT(--(CODE(MID(TRIM(C85),{1,2,3,4,5,10},1))>=65),--(CODE(MID(TRIM(C85),{1,2,3,4,5,10},1))<=90))=6,ISNUMBER(--MID(TRIM(C85),6,4))),"Valid","Invalid")) -> Valid | N85: =IF(TRIM(D85)="","Missing",IF(AND(LEN(TRIM(D85))=15,MID(TRIM(D85),14,1)="Z"),IF(AND(TRIM(C85)<>"",MID(TRIM(D85),3,10)=TRIM(C85)),"Valid","PAN Mismatch"),"Invalid")) -> Valid | O85: =IF(TRIM(E85)="","Missing",IF(AND(ISNUMBER(FIND("@",E85)),ISERROR(FIND(" ",TRIM(E85))),IFERROR(FIND(".",E85,FIND("@",E85)),0)>0),"Valid","Invalid")) -> Valid | P85: =IF(TRIM(F85)="","Missing",IFERROR(IF(AND(ISNUMBER(--V85),OR(LEN(V85)=10,AND(LEN(V85)=12,LEFT(V85,2)="91")),VALUE(LEFT(RIGHT(V85,10),1))>=6),"Valid","Invalid"),"Invalid")) -> Valid | Q85: =IF(TRIM(G85)="","Missing",IFERROR(IF(AND(ISNUMBER(--TRIM(G85)),LEN(TRIM(G85))>=9,LEN(TRIM(G85))<=18,ISERROR(FIND(".",G85))),"Valid","Invalid"),"Invalid")) -> Valid | R85: =IF(TRIM(H85)="","Missing",IF(AND(LEN(TRIM(H85))=11,SUMPRODUCT(--(CODE(MID(TRIM(H85),{1,2,3,4},1))>=65),--(CODE(MID(TRIM(H85),{1,2,3,4},1))<=90))=4,MID(TRIM(H85),5,1)="0"),"Valid","Invalid")) -> Valid | S85: =IF(TRIM(I85)="","Missing",IF(EXACT(TRIM(I85),"India"),"Valid","Invalid")) -> Valid | T85: =IF(TRIM(J85)="","Missing",IF(OR(EXACT(TRIM(J85),"Net 15"),EXACT(TRIM(J85),"Net 30"),EXACT(TRIM(J85),"Net 45"),EXACT(TRIM(J85),"Net 60")),"Valid","Invalid")) -> Invalid | U85: =COUNTIF(M85:T85,"<>Valid") -> 1 | V85: =SUBSTITUTE(SUBSTITUTE(SUBSTITUTE(F85," ",""),"-",""),"+","") -> 6434103697 | W85: V1035 | X85: =IF(COUNTIF($W$2:$W$229,W85)>1,"Duplicate","Unique") -> Unique
A86: V1206 | B86: Aaryan Security Solutions Limited | C86: UXECN9731D | D86: 29UXECN9731D1ZH | E86: ACCOUNTS@AARYANSECURITYSOLUTIONS.IN | F86: 737363466 | G86: 0438983640376 | H86: HDFC0379180 | I86: India | J86: 45D | K86: Active | L86: 2022-11-10 | M86: =IF(TRIM(C86)="","Missing",IF(AND(LEN(TRIM(C86))=10,SUMPRODUCT(--(CODE(MID(TRIM(C86),{1,2,3,4,5,10},1))>=65),--(CODE(MID(TRIM(C86),{1,2,3,4,5,10},1))<=90))=6,ISNUMBER(--MID(TRIM(C86),6,4))),"Valid","Invalid")) -> Valid | N86: =IF(TRIM(D86)="","Missing",IF(AND(LEN(TRIM(D86))=15,MID(TRIM(D86),14,1)="Z"),IF(AND(TRIM(C86)<>"",MID(TRIM(D86),3,10)=TRIM(C86)),"Valid","PAN Mismatch"),"Invalid")) -> Valid | O86: =IF(TRIM(E86)="","Missing",IF(AND(ISNUMBER(FIND("@",E86)),ISERROR(FIND(" ",TRIM(E86))),IFERROR(FIND(".",E86,FIND("@",E86)),0)>0),"Valid","Invalid")) -> Valid | P86: =IF(TRIM(F86)="","Missing",IFERROR(IF(AND(ISNUMBER(--V86),OR(LEN(V86)=10,AND(LEN(V86)=12,LEFT(V86,2)="91")),VALUE(LEFT(RIGHT(V86,10),1))>=6),"Valid","Invalid"),"Invalid")) -> Invalid | Q86: =IF(TRIM(G86)="","Missing",IFERROR(IF(AND(ISNUMBER(--TRIM(G86)),LEN(TRIM(G86))>=9,LEN(TRIM(G86))<=18,ISERROR(FIND(".",G86))),"Valid","Invalid"),"Invalid")) -> Valid | R86: =IF(TRIM(H86)="","Missing",IF(AND(LEN(TRIM(H86))=11,SUMPRODUCT(--(CODE(MID(TRIM(H86),{1,2,3,4},1))>=65),--(CODE(MID(TRIM(H86),{1,2,3,4},1))<=90))=4,MID(TRIM(H86),5,1)="0"),"Valid","Invalid")) -> Valid | S86: =IF(TRIM(I86)="","Missing",IF(EXACT(TRIM(I86),"India"),"Valid","Invalid")) -> Valid | T86: =IF(TRIM(J86)="","Missing",IF(OR(EXACT(TRIM(J86),"Net 15"),EXACT(TRIM(J86),"Net 30"),EXACT(TRIM(J86),"Net 45"),EXACT(TRIM(J86),"Net 60")),"Valid","Invalid")) -> Invalid | U86: =COUNTIF(M86:T86,"<>Valid") -> 2 | V86: =SUBSTITUTE(SUBSTITUTE(SUBSTITUTE(F86," ",""),"-",""),"+","") -> 737363466 | W86: V1068 | X86: =IF(COUNTIF($W$2:$W$229,W86)>1,"Duplicate","Unique") -> Duplicate
A87: V1213 | B87: BHARAT IT SERVICES PVT LTD | C87: QVJCB3690A | D87: 29QVJCB3690A1ZT | E87: accounts@bharatitservices.in | F87: +91 74151 48881 | G87: 83885160607159 | H87: UTIB0966416 | I87: IN | J87: 15D | K87: Active | L87: 2021-11-08 | M87: =IF(TRIM(C87)="","Missing",IF(AND(LEN(TRIM(C87))=10,SUMPRODUCT(--(CODE(MID(TRIM(C87),{1,2,3,4,5,10},1))>=65),--(CODE(MID(TRIM(C87),{1,2,3,4,5,10},1))<=90))=6,ISNUMBER(--MID(TRIM(C87),6,4))),"Valid","Invalid")) -> Valid | N87: =IF(TRIM(D87)="","Missing",IF(AND(LEN(TRIM(D87))=15,MID(TRIM(D87),14,1)="Z"),IF(AND(TRIM(C87)<>"",MID(TRIM(D87),3,10)=TRIM(C87)),"Valid","PAN Mismatch"),"Invalid")) -> Valid | O87: =IF(TRIM(E87)="","Missing",IF(AND(ISNUMBER(FIND("@",E87)),ISERROR(FIND(" ",TRIM(E87))),IFERROR(FIND(".",E87,FIND("@",E87)),0)>0),"Valid","Invalid")) -> Valid | P87: =IF(TRIM(F87)="","Missing",IFERROR(IF(AND(ISNUMBER(--V87),OR(LEN(V87)=10,AND(LEN(V87)=12,LEFT(V87,2)="91")),VALUE(LEFT(RIGHT(V87,10),1))>=6),"Valid","Invalid"),"Invalid")) -> Valid | Q87: =IF(TRIM(G87)="","Missing",IFERROR(IF(AND(ISNUMBER(--TRIM(G87)),LEN(TRIM(G87))>=9,LEN(TRIM(G87))<=18,ISERROR(FIND(".",G87))),"Valid","Invalid"),"Invalid")) -> Valid | R87: =IF(TRIM(H87)="","Missing",IF(AND(LEN(TRIM(H87))=11,SUMPRODUCT(--(CODE(MID(TRIM(H87),{1,2,3,4},1))>=65),--(CODE(MID(TRIM(H87),{1,2,3,4},1))<=90))=4,MID(TRIM(H87),5,1)="0"),"Valid","Invalid")) -> Valid | S87: =IF(TRIM(I87)="","Missing",IF(EXACT(TRIM(I87),"India"),"Valid","Invalid")) -> Invalid | T87: =IF(TRIM(J87)="","Missing",IF(OR(EXACT(TRIM(J87),"Net 15"),EXACT(TRIM(J87),"Net 30"),EXACT(TRIM(J87),"Net 45"),EXACT(TRIM(J87),"Net 60")),"Valid","Invalid")) -> Invalid | U87: =COUNTIF(M87:T87,"<>Valid") -> 2 | V87: =SUBSTITUTE(SUBSTITUTE(SUBSTITUTE(F87," ",""),"-",""),"+","") -> 917415148881 | W87: V1213 | X87: =IF(COUNTIF($W$2:$W$229,W87)>1,"Duplicate","Unique") -> Duplicate
A88: V1181 | B88: Nova Logistics Limited | C88: FZFCM0164K | D88: 24FZFCM0164K1Z3 | E88: accounts@novalogistics.in | F88: 8523219416 | G88: 06102776974 | H88: KKBK0956412 | I88: India | J88: NET30 | K88: Inactive | L88: 2020-04-03 | M88: =IF(TRIM(C88)="","Missing",IF(AND(LEN(TRIM(C88))=10,SUMPRODUCT(--(CODE(MID(TRIM(C88),{1,2,3,4,5,10},1))>=65),--(CODE(MID(TRIM(C88),{1,2,3,4,5,10},1))<=90))=6,ISNUMBER(--MID(TRIM(C88),6,4))),"Valid","Invalid")) -> Valid | N88: =IF(TRIM(D88)="","Missing",IF(AND(LEN(TRIM(D88))=15,MID(TRIM(D88),14,1)="Z"),IF(AND(TRIM(C88)<>"",MID(TRIM(D88),3,10)=TRIM(C88)),"Valid","PAN Mismatch"),"Invalid")) -> Valid | O88: =IF(TRIM(E88)="","Missing",IF(AND(ISNUMBER(FIND("@",E88)),ISERROR(FIND(" ",TRIM(E88))),IFERROR(FIND(".",E88,FIND("@",E88)),0)>0),"Valid","Invalid")) -> Valid | P88: =IF(TRIM(F88)="","Missing",IFERROR(IF(AND(ISNUMBER(--V88),OR(LEN(V88)=10,AND(LEN(V88)=12,LEFT(V88,2)="91")),VALUE(LEFT(RIGHT(V88,10),1))>=6),"Valid","Invalid"),"Invalid")) -> Valid | Q88: =IF(TRIM(G88)="","Missing",IFERROR(IF(AND(ISNUMBER(--TRIM(G88)),LEN(TRIM(G88))>=9,LEN(TRIM(G88))<=18,ISERROR(FIND(".",G88))),"Valid","Invalid"),"Invalid")) -> Valid | R88: =IF(TRIM(H88)="","Missing",IF(AND(LEN(TRIM(H88))=11,SUMPRODUCT(--(CODE(MID(TRIM(H88),{1,2,3,4},1))>=65),--(CODE(MID(TRIM(H88),{1,2,3,4},1))<=90))=4,MID(TRIM(H88),5,1)="0"),"Valid","Invalid")) -> Valid | S88: =IF(TRIM(I88)="","Missing",IF(EXACT(TRIM(I88),"India"),"Valid","Invalid")) -> Valid | T88: =IF(TRIM(J88)="","Missing",IF(OR(EXACT(TRIM(J88),"Net 15"),EXACT(TRIM(J88),"Net 30"),EXACT(TRIM(J88),"Net 45"),EXACT(TRIM(J88),"Net 60")),"Valid","Invalid")) -> Invalid | U88: =COUNTIF(M88:T88,"<>Valid") -> 1 | V88: =SUBSTITUTE(SUBSTITUTE(SUBSTITUTE(F88," ",""),"-",""),"+","") -> 8523219416 | W88: V1181 | X88: =IF(COUNTIF($W$2:$W$229,W88)>1,"Duplicate","Unique") -> Unique
A89: V1203 | B89: Western Electricals PVT LTD | C89: OLECI3106T | D89: 19OLECI3106T1ZB | E89: accounts@westernelectricals.in | F89: +91 98578 72558 | G89: 73830284395995 | H89: ICIC0428364 | I89: India | J89: 45 Days | K89: Inactive | L89: 2023-05-06 | M89: =IF(TRIM(C89)="","Missing",IF(AND(LEN(TRIM(C89))=10,SUMPRODUCT(--(CODE(MID(TRIM(C89),{1,2,3,4,5,10},1))>=65),--(CODE(MID(TRIM(C89),{1,2,3,4,5,10},1))<=90))=6,ISNUMBER(--MID(TRIM(C89),6,4))),"Valid","Invalid")) -> Valid | N89: =IF(TRIM(D89)="","Missing",IF(AND(LEN(TRIM(D89))=15,MID(TRIM(D89),14,1)="Z"),IF(AND(TRIM(C89)<>"",MID(TRIM(D89),3,10)=TRIM(C89)),"Valid","PAN Mismatch"),"Invalid")) -> Valid | O89: =IF(TRIM(E89)="","Missing",IF(AND(ISNUMBER(FIND("@",E89)),ISERROR(FIND(" ",TRIM(E89))),IFERROR(FIND(".",E89,FIND("@",E89)),0)>0),"Valid","Invalid")) -> Valid | P89: =IF(TRIM(F89)="","Missing",IFERROR(IF(AND(ISNUMBER(--V89),OR(LEN(V89)=10,AND(LEN(V89)=12,LEFT(V89,2)="91")),VALUE(LEFT(RIGHT(V89,10),1))>=6),"Valid","Invalid"),"Invalid")) -> Valid | Q89: =IF(TRIM(G89)="","Missing",IFERROR(IF(AND(ISNUMBER(--TRIM(G89)),LEN(TRIM(G89))>=9,LEN(TRIM(G89))<=18,ISERROR(FIND(".",G89))),"Valid","Invalid"),"Invalid")) -> Valid | R89: =IF(TRIM(H89)="","Missing",IF(AND(LEN(TRIM(H89))=11,SUMPRODUCT(--(CODE(MID(TRIM(H89),{1,2,3,4},1))>=65),--(CODE(MID(TRIM(H89),{1,2,3,4},1))<=90))=4,MID(TRIM(H89),5,1)="0"),"Valid","Invalid")) -> Valid | S89: =IF(TRIM(I89)="","Missing",IF(EXACT(TRIM(I89),"India"),"Valid","Invalid")) -> Valid | T89: =IF(TRIM(J89)="","Missing",IF(OR(EXACT(TRIM(J89),"Net 15"),EXACT(TRIM(J89),"Net 30"),EXACT(TRIM(J89),"Net 45"),EXACT(TRIM(J89),"Net 60")),"Valid","Invalid")) -> Invalid | U89: =COUNTIF(M89:T89,"<>Valid") -> 1 | V89: =SUBSTITUTE(SUBSTITUTE(SUBSTITUTE(F89," ",""),"-",""),"+","") -> 919857872558 | W89: V1203 | X89: =IF(COUNTIF($W$2:$W$229,W89)>1,"Duplicate","Unique") -> Duplicate
A90: V1183 | B90: Orchid Pest Control Private Limited | C90: QSXCT7308A | D90: 07CZDCU7308A1ZU | F90: 8671795760 | G90: 437573839597 | H90: ICIC0466572 | I90: India | J90: 30D | K90: Active | L90: 2019-12-20 | M90: =IF(TRIM(C90)="","Missing",IF(AND(LEN(TRIM(C90))=10,SUMPRODUCT(--(CODE(MID(TRIM(C90),{1,2,3,4,5,10},1))>=65),--(CODE(MID(TRIM(C90),{1,2,3,4,5,10},1))<=90))=6,ISNUMBER(--MID(TRIM(C90),6,4))),"Valid","Invalid")) -> Valid | N90: =IF(TRIM(D90)="","Missing",IF(AND(LEN(TRIM(D90))=15,MID(TRIM(D90),14,1)="Z"),IF(AND(TRIM(C90)<>"",MID(TRIM(D90),3,10)=TRIM(C90)),"Valid","PAN Mismatch"),"Invalid")) -> PAN Mismatch | O90: =IF(TRIM(E90)="","Missing",IF(AND(ISNUMBER(FIND("@",E90)),ISERROR(FIND(" ",TRIM(E90))),IFERROR(FIND(".",E90,FIND("@",E90)),0)>0),"Valid","Invalid")) -> Missing | P90: =IF(TRIM(F90)="","Missing",IFERROR(IF(AND(ISNUMBER(--V90),OR(LEN(V90)=10,AND(LEN(V90)=12,LEFT(V90,2)="91")),VALUE(LEFT(RIGHT(V90,10),1))>=6),"Valid","Invalid"),"Invalid")) -> Valid | Q90: =IF(TRIM(G90)="","Missing",IFERROR(IF(AND(ISNUMBER(--TRIM(G90)),LEN(TRIM(G90))>=9,LEN(TRIM(G90))<=18,ISERROR(FIND(".",G90))),"Valid","Invalid"),"Invalid")) -> Valid | R90: =IF(TRIM(H90)="","Missing",IF(AND(LEN(TRIM(H90))=11,SUMPRODUCT(--(CODE(MID(TRIM(H90),{1,2,3,4},1))>=65),--(CODE(MID(TRIM(H90),{1,2,3,4},1))<=90))=4,MID(TRIM(H90),5,1)="0"),"Valid","Invalid")) -> Valid | S90: =IF(TRIM(I90)="","Missing",IF(EXACT(TRIM(I90),"India"),"Valid","Invalid")) -> Valid | T90: =IF(TRIM(J90)="","Missing",IF(OR(EXACT(TRIM(J90),"Net 15"),EXACT(TRIM(J90),"Net 30"),EXACT(TRIM(J90),"Net 45"),EXACT(TRIM(J90),"Net 60")),"Valid","Invalid")) -> Invalid | U90: =COUNTIF(M90:T90,"<>Valid") -> 3 | V90: =SUBSTITUTE(SUBSTITUTE(SUBSTITUTE(F90," ",""),"-",""),"+","") -> 8671795760 | W90: V1183 | X90: =IF(COUNTIF($W$2:$W$229,W90)>1,"Duplicate","Unique") -> Unique
A91: V1105 | B91: Horizon Maintenance Limited | C91: FQMCT9041G | D91: 07FQMCT9041G1Z4 | E91: accounts@horizonmaintenance.in | F91: +91 73692 92984 | G91: 579913662103 | H91: KKBK1862912 | I91: India | J91: 60 Days | K91: Active | L91: 2019-06-09 | M91: =IF(TRIM(C91)="","Missing",IF(AND(LEN(TRIM(C91))=10,SUMPRODUCT(--(CODE(MID(TRIM(C91),{1,2,3,4,5,10},1))>=65),--(CODE(MID(TRIM(C91),{1,2,3,4,5,10},1))<=90))=6,ISNUMBER(--MID(TRIM(C91),6,4))),"Valid","Invalid")) -> Valid | N91: =IF(TRIM(D91)="","Missing",IF(AND(LEN(TRIM(D91))=15,MID(TRIM(D91),14,1)="Z"),IF(AND(TRIM(C91)<>"",MID(TRIM(D91),3,10)=TRIM(C91)),"Valid","PAN Mismatch"),"Invalid")) -> Valid | O91: =IF(TRIM(E91)="","Missing",IF(AND(ISNUMBER(FIND("@",E91)),ISERROR(FIND(" ",TRIM(E91))),IFERROR(FIND(".",E91,FIND("@",E91)),0)>0),"Valid","Invalid")) -> Valid | P91: =IF(TRIM(F91)="","Missing",IFERROR(IF(AND(ISNUMBER(--V91),OR(LEN(V91)=10,AND(LEN(V91)=12,LEFT(V91,2)="91")),VALUE(LEFT(RIGHT(V91,10),1))>=6),"Valid","Invalid"),"Invalid")) -> Valid | Q91: =IF(TRIM(G91)="","Missing",IFERROR(IF(AND(ISNUMBER(--TRIM(G91)),LEN(TRIM(G91))>=9,LEN(TRIM(G91))<=18,ISERROR(FIND(".",G91))),"Valid","Invalid"),"Invalid")) -> Valid | R91: =IF(TRIM(H91)="","Missing",IF(AND(LEN(TRIM(H91))=11,SUMPRODUCT(--(CODE(MID(TRIM(H91),{1,2,3,4},1))>=65),--(CODE(MID(TRIM(H91),{1,2,3,4},1))<=90))=4,MID(TRIM(H91),5,1)="0"),"Valid","Invalid")) -> Invalid | S91: =IF(TRIM(I91)="","Missing",IF(EXACT(TRIM(I91),"India"),"Valid","Invalid")) -> Valid | T91: =IF(TRIM(J91)="","Missing",IF(OR(EXACT(TRIM(J91),"Net 15"),EXACT(TRIM(J91),"Net 30"),EXACT(TRIM(J91),"Net 45"),EXACT(TRIM(J91),"Net 60")),"Valid","Invalid")) -> Invalid | U91: =COUNTIF(M91:T91,"<>Valid") -> 2 | V91: =SUBSTITUTE(SUBSTITUTE(SUBSTITUTE(F91," ",""),"-",""),"+","") -> 917369292984 | W91: V1105 | X91: =IF(COUNTIF($W$2:$W$229,W91)>1,"Duplicate","Unique") -> Unique
A92: V1147 | B92: Pinnacle Pest Control Private Limited | C92: CSXCI7072 | D92: 36CSXCI7072U1ZA | E92: accounts@pinnaclepestcontrol.in | F92: 9425690877 | G92: 61830671985546 | H92: HDFC0158517 | I92: India | J92: Net 45 | K92: Active | L92: 2020-12-24 | M92: =IF(TRIM(C92)="","Missing",IF(AND(LEN(TRIM(C92))=10,SUMPRODUCT(--(CODE(MID(TRIM(C92),{1,2,3,4,5,10},1))>=65),--(CODE(MID(TRIM(C92),{1,2,3,4,5,10},1))<=90))=6,ISNUMBER(--MID(TRIM(C92),6,4))),"Valid","Invalid")) -> #VALUE! | N92: =IF(TRIM(D92)="","Missing",IF(AND(LEN(TRIM(D92))=15,MID(TRIM(D92),14,1)="Z"),IF(AND(TRIM(C92)<>"",MID(TRIM(D92),3,10)=TRIM(C92)),"Valid","PAN Mismatch"),"Invalid")) -> PAN Mismatch | O92: =IF(TRIM(E92)="","Missing",IF(AND(ISNUMBER(FIND("@",E92)),ISERROR(FIND(" ",TRIM(E92))),IFERROR(FIND(".",E92,FIND("@",E92)),0)>0),"Valid","Invalid")) -> Valid | P92: =IF(TRIM(F92)="","Missing",IFERROR(IF(AND(ISNUMBER(--V92),OR(LEN(V92)=10,AND(LEN(V92)=12,LEFT(V92,2)="91")),VALUE(LEFT(RIGHT(V92,10),1))>=6),"Valid","Invalid"),"Invalid")) -> Valid | Q92: =IF(TRIM(G92)="","Missing",IFERROR(IF(AND(ISNUMBER(--TRIM(G92)),LEN(TRIM(G92))>=9,LEN(TRIM(G92))<=18,ISERROR(FIND(".",G92))),"Valid","Invalid"),"Invalid")) -> Valid | R92: =IF(TRIM(H92)="","Missing",IF(AND(LEN(TRIM(H92))=11,SUMPRODUCT(--(CODE(MID(TRIM(H92),{1,2,3,4},1))>=65),--(CODE(MID(TRIM(H92),{1,2,3,4},1))<=90))=4,MID(TRIM(H92),5,1)="0"),"Valid","Invalid")) -> Valid | S92: =IF(TRIM(I92)="","Missing",IF(EXACT(TRIM(I92),"India"),"Valid","Invalid")) -> Valid | T92: =IF(TRIM(J92)="","Missing",IF(OR(EXACT(TRIM(J92),"Net 15"),EXACT(TRIM(J92),"Net 30"),EXACT(TRIM(J92),"Net 45"),EXACT(TRIM(J92),"Net 60")),"Valid","Invalid")) -> Valid | U92: =COUNTIF(M92:T92,"<>Valid") -> 2 | V92: =SUBSTITUTE(SUBSTITUTE(SUBSTITUTE(F92," ",""),"-",""),"+","") -> 9425690877 | W92: V1147 | X92: =IF(COUNTIF($W$2:$W$229,W92)>1,"Duplicate","Unique") -> Unique
A93: V1018 | B93: Bluewave Electricals Pvt Ltd | C93: ONBCG8597U | D93: 07WJOBT8597U1ZD | F93: 8824771093 | G93: 480861317127 | H93: SBIN0846773 | I93: India | J93: Net 60 | K93: Active | L93: 2023-04-21 | M93: =IF(TRIM(C93)="","Missing",IF(AND(LEN(TRIM(C93))=10,SUMPRODUCT(--(CODE(MID(TRIM(C93),{1,2,3,4,5,10},1))>=65),--(CODE(MID(TRIM(C93),{1,2,3,4,5,10},1))<=90))=6,ISNUMBER(--MID(TRIM(C93),6,4))),"Valid","Invalid")) -> Valid | N93: =IF(TRIM(D93)="","Missing",IF(AND(LEN(TRIM(D93))=15,MID(TRIM(D93),14,1)="Z"),IF(AND(TRIM(C93)<>"",MID(TRIM(D93),3,10)=TRIM(C93)),"Valid","PAN Mismatch"),"Invalid")) -> PAN Mismatch | O93: =IF(TRIM(E93)="","Missing",IF(AND(ISNUMBER(FIND("@",E93)),ISERROR(FIND(" ",TRIM(E93))),IFERROR(FIND(".",E93,FIND("@",E93)),0)>0),"Valid","Invalid")) -> Missing | P93: =IF(TRIM(F93)="","Missing",IFERROR(IF(AND(ISNUMBER(--V93),OR(LEN(V93)=10,AND(LEN(V93)=12,LEFT(V93,2)="91")),VALUE(LEFT(RIGHT(V93,10),1))>=6),"Valid","Invalid"),"Invalid")) -> Valid | Q93: =IF(TRIM(G93)="","Missing",IFERROR(IF(AND(ISNUMBER(--TRIM(G93)),LEN(TRIM(G93))>=9,LEN(TRIM(G93))<=18,ISERROR(FIND(".",G93))),"Valid","Invalid"),"Invalid")) -> Valid | R93: =IF(TRIM(H93)="","Missing",IF(AND(LEN(TRIM(H93))=11,SUMPRODUCT(--(CODE(MID(TRIM(H93),{1,2,3,4},1))>=65),--(CODE(MID(TRIM(H93),{1,2,3,4},1))<=90))=4,MID(TRIM(H93),5,1)="0"),"Valid","Invalid")) -> Valid | S93: =IF(TRIM(I93)="","Missing",IF(EXACT(TRIM(I93),"India"),"Valid","Invalid")) -> Valid | T93: =IF(TRIM(J93)="","Missing",IF(OR(EXACT(TRIM(J93),"Net 15"),EXACT(TRIM(J93),"Net 30"),EXACT(TRIM(J93),"Net 45"),EXACT(TRIM(J93),"Net 60")),"Valid","Invalid")) -> Valid | U93: =COUNTIF(M93:T93,"<>Valid") -> 2 | V93: =SUBSTITUTE(SUBSTITUTE(SUBSTITUTE(F93," ",""),"-",""),"+","") -> 8824771093 | W93: V1018 | X93: =IF(COUNTIF($W$2:$W$229,W93)>1,"Duplicate","Unique") -> Unique
A94: V1033 | B94: Quantum Logistics Private Limited | C94: GKYCP3322C | D94: 33GKYCP3322C1ZG | E94: accounts@quantumlogistics.in | F94: +91 89296 22292 | G94: 06537947383473 | H94: SBIN0977468 | I94: India | J94: 60 Days | K94: Active | L94: 2021-03-28 | M94: =IF(TRIM(C94)="","Missing",IF(AND(LEN(TRIM(C94))=10,SUMPRODUCT(--(CODE(MID(TRIM(C94),{1,2,3,4,5,10},1))>=65),--(CODE(MID(TRIM(C94),{1,2,3,4,5,10},1))<=90))=6,ISNUMBER(--MID(TRIM(C94),6,4))),"Valid","Invalid")) -> Valid | N94: =IF(TRIM(D94)="","Missing",IF(AND(LEN(TRIM(D94))=15,MID(TRIM(D94),14,1)="Z"),IF(AND(TRIM(C94)<>"",MID(TRIM(D94),3,10)=TRIM(C94)),"Valid","PAN Mismatch"),"Invalid")) -> Valid | O94: =IF(TRIM(E94)="","Missing",IF(AND(ISNUMBER(FIND("@",E94)),ISERROR(FIND(" ",TRIM(E94))),IFERROR(FIND(".",E94,FIND("@",E94)),0)>0),"Valid","Invalid")) -> Valid | P94: =IF(TRIM(F94)="","Missing",IFERROR(IF(AND(ISNUMBER(--V94),OR(LEN(V94)=10,AND(LEN(V94)=12,LEFT(V94,2)="91")),VALUE(LEFT(RIGHT(V94,10),1))>=6),"Valid","Invalid"),"Invalid")) -> Valid | Q94: =IF(TRIM(G94)="","Missing",IFERROR(IF(AND(ISNUMBER(--TRIM(G94)),LEN(TRIM(G94))>=9,LEN(TRIM(G94))<=18,ISERROR(FIND(".",G94))),"Valid","Invalid"),"Invalid")) -> Valid | R94: =IF(TRIM(H94)="","Missing",IF(AND(LEN(TRIM(H94))=11,SUMPRODUCT(--(CODE(MID(TRIM(H94),{1,2,3,4},1))>=65),--(CODE(MID(TRIM(H94),{1,2,3,4},1))<=90))=4,MID(TRIM(H94),5,1)="0"),"Valid","Invalid")) -> Valid | S94: =IF(TRIM(I94)="","Missing",IF(EXACT(TRIM(I94),"India"),"Valid","Invalid")) -> Valid | T94: =IF(TRIM(J94)="","Missing",IF(OR(EXACT(TRIM(J94),"Net 15"),EXACT(TRIM(J94),"Net 30"),EXACT(TRIM(J94),"Net 45"),EXACT(TRIM(J94),"Net 60")),"Valid","Invalid")) -> Invalid | U94: =COUNTIF(M94:T94,"<>Valid") -> 1 | V94: =SUBSTITUTE(SUBSTITUTE(SUBSTITUTE(F94," ",""),"-",""),"+","") -> 918929622292 | W94: V1033 | X94: =IF(COUNTIF($W$2:$W$229,W94)>1,"Duplicate","Unique") -> Unique
A95: V1102 | B95: Orchid IT Services Private Limited | C95: FUTCC4283I | D95: 36FUTCC4283I1ZE | E95: accounts@orchiditservices.in | F95: 6809969308 | G95: 8872563942788 | H95: HDFC0658039 | I95: India | J95: 30 Days | K95: Active | L95: 2020-07-28 | M95: =IF(TRIM(C95)="","Missing",IF(AND(LEN(TRIM(C95))=10,SUMPRODUCT(--(CODE(MID(TRIM(C95),{1,2,3,4,5,10},1))>=65),--(CODE(MID(TRIM(C95),{1,2,3,4,5,10},1))<=90))=6,ISNUMBER(--MID(TRIM(C95),6,4))),"Valid","Invalid")) -> Valid | N95: =IF(TRIM(D95)="","Missing",IF(AND(LEN(TRIM(D95))=15,MID(TRIM(D95),14,1)="Z"),IF(AND(TRIM(C95)<>"",MID(TRIM(D95),3,10)=TRIM(C95)),"Valid","PAN Mismatch"),"Invalid")) -> Valid | O95: =IF(TRIM(E95)="","Missing",IF(AND(ISNUMBER(FIND("@",E95)),ISERROR(FIND(" ",TRIM(E95))),IFERROR(FIND(".",E95,FIND("@",E95)),0)>0),"Valid","Invalid")) -> Valid | P95: =IF(TRIM(F95)="","Missing",IFERROR(IF(AND(ISNUMBER(--V95),OR(LEN(V95)=10,AND(LEN(V95)=12,LEFT(V95,2)="91")),VALUE(LEFT(RIGHT(V95,10),1))>=6),"Valid","Invalid"),"Invalid")) -> Valid | Q95: =IF(TRIM(G95)="","Missing",IFERROR(IF(AND(ISNUMBER(--TRIM(G95)),LEN(TRIM(G95))>=9,LEN(TRIM(G95))<=18,ISERROR(FIND(".",G95))),"Valid","Invalid"),"Invalid")) -> Valid | R95: =IF(TRIM(H95)="","Missing",IF(AND(LEN(TRIM(H95))=11,SUMPRODUCT(--(CODE(MID(TRIM(H95),{1,2,3,4},1))>=65),--(CODE(MID(TRIM(H95),{1,2,3,4},1))<=90))=4,MID(TRIM(H95),5,1)="0"),"Valid","Invalid")) -> Valid | S95: =IF(TRIM(I95)="","Missing",IF(EXACT(TRIM(I95),"India"),"Valid","Invalid")) -> Valid | T95: =IF(TRIM(J95)="","Missing",IF(OR(EXACT(TRIM(J95),"Net 15"),EXACT(TRIM(J95),"Net 30"),EXACT(TRIM(J95),"Net 45"),EXACT(TRIM(J95),"Net 60")),"Valid","Invalid")) -> Invalid | U95: =COUNTIF(M95:T95,"<>Valid") -> 1 | V95: =SUBSTITUTE(SUBSTITUTE(SUBSTITUTE(F95," ",""),"-",""),"+","") -> 6809969308 | W95: V1102 | X95: =IF(COUNTIF($W$2:$W$229,W95)>1,"Duplicate","Unique") -> Unique
A96: V1099 | B96: Ironbridge Logistics LLP | C96: BCCCB2481S | D96: 19BCCCB2481S1ZO | E96: accounts@ironbridgelogistics.in | F96: 96766-50618 | H96: HDFC0476607 | I96: India | J96: 30D | K96: Active | L96: 2020-07-12 | M96: =IF(TRIM(C96)="","Missing",IF(AND(LEN(TRIM(C96))=10,SUMPRODUCT(--(CODE(MID(TRIM(C96),{1,2,3,4,5,10},1))>=65),--(CODE(MID(TRIM(C96),{1,2,3,4,5,10},1))<=90))=6,ISNUMBER(--MID(TRIM(C96),6,4))),"Valid","Invalid")) -> Valid | N96: =IF(TRIM(D96)="","Missing",IF(AND(LEN(TRIM(D96))=15,MID(TRIM(D96),14,1)="Z"),IF(AND(TRIM(C96)<>"",MID(TRIM(D96),3,10)=TRIM(C96)),"Valid","PAN Mismatch"),"Invalid")) -> Valid | O96: =IF(TRIM(E96)="","Missing",IF(AND(ISNUMBER(FIND("@",E96)),ISERROR(FIND(" ",TRIM(E96))),IFERROR(FIND(".",E96,FIND("@",E96)),0)>0),"Valid","Invalid")) -> Valid | P96: =IF(TRIM(F96)="","Missing",IFERROR(IF(AND(ISNUMBER(--V96),OR(LEN(V96)=10,AND(LEN(V96)=12,LEFT(V96,2)="91")),VALUE(LEFT(RIGHT(V96,10),1))>=6),"Valid","Invalid"),"Invalid")) -> Valid | Q96: =IF(TRIM(G96)="","Missing",IFERROR(IF(AND(ISNUMBER(--TRIM(G96)),LEN(TRIM(G96))>=9,LEN(TRIM(G96))<=18,ISERROR(FIND(".",G96))),"Valid","Invalid"),"Invalid")) -> Missing | R96: =IF(TRIM(H96)="","Missing",IF(AND(LEN(TRIM(H96))=11,SUMPRODUCT(--(CODE(MID(TRIM(H96),{1,2,3,4},1))>=65),--(CODE(MID(TRIM(H96),{1,2,3,4},1))<=90))=4,MID(TRIM(H96),5,1)="0"),"Valid","Invalid")) -> Valid | S96: =IF(TRIM(I96)="","Missing",IF(EXACT(TRIM(I96),"India"),"Valid","Invalid")) -> Valid | T96: =IF(TRIM(J96)="","Missing",IF(OR(EXACT(TRIM(J96),"Net 15"),EXACT(TRIM(J96),"Net 30"),EXACT(TRIM(J96),"Net 45"),EXACT(TRIM(J96),"Net 60")),"Valid","Invalid")) -> Invalid | U96: =COUNTIF(M96:T96,"<>Valid") -> 2 | V96: =SUBSTITUTE(SUBSTITUTE(SUBSTITUTE(F96," ",""),"-",""),"+","") -> 9676650618 | W96: V1099 | X96: =IF(COUNTIF($W$2:$W$229,W96)>1,"Duplicate","Unique") -> Unique
A97: V1144 | B97: Deccan Security Solutions Limited | C97: BKCCE9276Y | D97: 07BKCCE9276Y1ZP | E97: accounts@deccansecuritysolutions.in | F97: +91 73950 41027 | G97: 74783667428604 | H97: UTIB0658018 | I97: India | J97: 45 Days | K97: Active | L97: 2023-11-04 | M97: =IF(TRIM(C97)="","Missing",IF(AND(LEN(TRIM(C97))=10,SUMPRODUCT(--(CODE(MID(TRIM(C97),{1,2,3,4,5,10},1))>=65),--(CODE(MID(TRIM(C97),{1,2,3,4,5,10},1))<=90))=6,ISNUMBER(--MID(TRIM(C97),6,4))),"Valid","Invalid")) -> Valid | N97: =IF(TRIM(D97)="","Missing",IF(AND(LEN(TRIM(D97))=15,MID(TRIM(D97),14,1)="Z"),IF(AND(TRIM(C97)<>"",MID(TRIM(D97),3,10)=TRIM(C97)),"Valid","PAN Mismatch"),"Invalid")) -> Valid | O97: =IF(TRIM(E97)="","Missing",IF(AND(ISNUMBER(FIND("@",E97)),ISERROR(FIND(" ",TRIM(E97))),IFERROR(FIND(".",E97,FIND("@",E97)),0)>0),"Valid","Invalid")) -> Valid | P97: =IF(TRIM(F97)="","Missing",IFERROR(IF(AND(ISNUMBER(--V97),OR(LEN(V97)=10,AND(LEN(V97)=12,LEFT(V97,2)="91")),VALUE(LEFT(RIGHT(V97,10),1))>=6),"Valid","Invalid"),"Invalid")) -> Valid | Q97: =IF(TRIM(G97)="","Missing",IFERROR(IF(AND(ISNUMBER(--TRIM(G97)),LEN(TRIM(G97))>=9,LEN(TRIM(G97))<=18,ISERROR(FIND(".",G97))),"Valid","Invalid"),"Invalid")) -> Valid | R97: =IF(TRIM(H97)="","Missing",IF(AND(LEN(TRIM(H97))=11,SUMPRODUCT(--(CODE(MID(TRIM(H97),{1,2,3,4},1))>=65),--(CODE(MID(TRIM(H97),{1,2,3,4},1))<=90))=4,MID(TRIM(H97),5,1)="0"),"Valid","Invalid")) -> Valid | S97: =IF(TRIM(I97)="","Missing",IF(EXACT(TRIM(I97),"India"),"Valid","Invalid")) -> Valid | T97: =IF(TRIM(J97)="","Missing",IF(OR(EXACT(TRIM(J97),"Net 15"),EXACT(TRIM(J97),"Net 30"),EXACT(TRIM(J97),"Net 45"),EXACT(TRIM(J97),"Net 60")),"Valid","Invalid")) -> Invalid | U97: =COUNTIF(M97:T97,"<>Valid") -> 1 | V97: =SUBSTITUTE(SUBSTITUTE(SUBSTITUTE(F97," ",""),"-",""),"+","") -> 917395041027 | W97: V1144 | X97: =IF(COUNTIF($W$2:$W$229,W97)>1,"Duplicate","Unique") -> Unique
A98: V1222 | B98: Metro Engg Works LLP | D98: 29QOECT8259K1ZZ | E98: accounts@metroengineeringworks.in | F98: +91 88887 94705 | G98: 1694097499309 | H98: UTIB0289623 | I98: India | J98: 15D | K98: Active | L98: 2021-08-07 | M98: =IF(TRIM(C98)="","Missing",IF(AND(LEN(TRIM(C98))=10,SUMPRODUCT(--(CODE(MID(TRIM(C98),{1,2,3,4,5,10},1))>=65),--(CODE(MID(TRIM(C98),{1,2,3,4,5,10},1))<=90))=6,ISNUMBER(--MID(TRIM(C98),6,4))),"Valid","Invalid")) -> Missing | N98: =IF(TRIM(D98)="","Missing",IF(AND(LEN(TRIM(D98))=15,MID(TRIM(D98),14,1)="Z"),IF(AND(TRIM(C98)<>"",MID(TRIM(D98),3,10)=TRIM(C98)),"Valid","PAN Mismatch"),"Invalid")) -> PAN Mismatch | O98: =IF(TRIM(E98)="","Missing",IF(AND(ISNUMBER(FIND("@",E98)),ISERROR(FIND(" ",TRIM(E98))),IFERROR(FIND(".",E98,FIND("@",E98)),0)>0),"Valid","Invalid")) -> Valid | P98: =IF(TRIM(F98)="","Missing",IFERROR(IF(AND(ISNUMBER(--V98),OR(LEN(V98)=10,AND(LEN(V98)=12,LEFT(V98,2)="91")),VALUE(LEFT(RIGHT(V98,10),1))>=6),"Valid","Invalid"),"Invalid")) -> Valid | Q98: =IF(TRIM(G98)="","Missing",IFERROR(IF(AND(ISNUMBER(--TRIM(G98)),LEN(TRIM(G98))>=9,LEN(TRIM(G98))<=18,ISERROR(FIND(".",G98))),"Valid","Invalid"),"Invalid")) -> Valid | R98: =IF(TRIM(H98)="","Missing",IF(AND(LEN(TRIM(H98))=11,SUMPRODUCT(--(CODE(MID(TRIM(H98),{1,2,3,4},1))>=65),--(CODE(MID(TRIM(H98),{1,2,3,4},1))<=90))=4,MID(TRIM(H98),5,1)="0"),"Valid","Invalid")) -> Valid | S98: =IF(TRIM(I98)="","Missing",IF(EXACT(TRIM(I98),"India"),"Valid","Invalid")) -> Valid | T98: =IF(TRIM(J98)="","Missing",IF(OR(EXACT(TRIM(J98),"Net 15"),EXACT(TRIM(J98),"Net 30"),EXACT(TRIM(J98),"Net 45"),EXACT(TRIM(J98),"Net 60")),"Valid","Invalid")) -> Invalid | U98: =COUNTIF(M98:T98,"<>Valid") -> 3 | V98: =SUBSTITUTE(SUBSTITUTE(SUBSTITUTE(F98," ",""),"-",""),"+","") -> 918888794705 | W98: V1222 | X98: =IF(COUNTIF($W$2:$W$229,W98)>1,"Duplicate","Unique") -> Unique
A99: V1056 | B99: Evergreen Water Solutions Limited | C99: PNUCZ5918 | D99: 29PNUCZ5918B1ZN | E99: accounts@evergreenwatersolutions.in | F99: 8014890250 | G99: 926142939685 | H99: UTIB0218501 | I99: IN | J99: NET60 | K99: Active | L99: 2019-11-08 | M99: =IF(TRIM(C99)="","Missing",IF(AND(LEN(TRIM(C99))=10,SUMPRODUCT(--(CODE(MID(TRIM(C99),{1,2,3,4,5,10},1))>=65),--(CODE(MID(TRIM(C99),{1,2,3,4,5,10},1))<=90))=6,ISNUMBER(--MID(TRIM(C99),6,4))),"Valid","Invalid")) -> #VALUE! | N99: =IF(TRIM(D99)="","Missing",IF(AND(LEN(TRIM(D99))=15,MID(TRIM(D99),14,1)="Z"),IF(AND(TRIM(C99)<>"",MID(TRIM(D99),3,10)=TRIM(C99)),"Valid","PAN Mismatch"),"Invalid")) -> PAN Mismatch | O99: =IF(TRIM(E99)="","Missing",IF(AND(ISNUMBER(FIND("@",E99)),ISERROR(FIND(" ",TRIM(E99))),IFERROR(FIND(".",E99,FIND("@",E99)),0)>0),"Valid","Invalid")) -> Valid | P99: =IF(TRIM(F99)="","Missing",IFERROR(IF(AND(ISNUMBER(--V99),OR(LEN(V99)=10,AND(LEN(V99)=12,LEFT(V99,2)="91")),VALUE(LEFT(RIGHT(V99,10),1))>=6),"Valid","Invalid"),"Invalid")) -> Valid | Q99: =IF(TRIM(G99)="","Missing",IFERROR(IF(AND(ISNUMBER(--TRIM(G99)),LEN(TRIM(G99))>=9,LEN(TRIM(G99))<=18,ISERROR(FIND(".",G99))),"Valid","Invalid"),"Invalid")) -> Valid | R99: =IF(TRIM(H99)="","Missing",IF(AND(LEN(TRIM(H99))=11,SUMPRODUCT(--(CODE(MID(TRIM(H99),{1,2,3,4},1))>=65),--(CODE(MID(TRIM(H99),{1,2,3,4},1))<=90))=4,MID(TRIM(H99),5,1)="0"),"Valid","Invalid")) -> Valid | S99: =IF(TRIM(I99)="","Missing",IF(EXACT(TRIM(I99),"India"),"Valid","Invalid")) -> Invalid | T99: =IF(TRIM(J99)="","Missing",IF(OR(EXACT(TRIM(J99),"Net 15"),EXACT(TRIM(J99),"Net 30"),EXACT(TRIM(J99),"Net 45"),EXACT(TRIM(J99),"Net 60")),"Valid","Invalid")) -> Invalid | U99: =COUNTIF(M99:T99,"<>Valid") -> 4 | V99: =SUBSTITUTE(SUBSTITUTE(SUBSTITUTE(F99," ",""),"-",""),"+","") -> 8014890250 | W99: V1056 | X99: =IF(COUNTIF($W$2:$W$229,W99)>1,"Duplicate","Unique") -> Unique
A100: V1211 | B100: CRESTLINE FACILITY SERVICES PVT. LTD. | C100: PRYCU0157H | D100: 36PRYCU0157H1ZP | E100: accounts@crestlinefacilityservices.in | F100: 86164-84085 | G100: 70435811288013 | H100: ICIC0613861 | I100: India | J100: net 30 | K100: Inactive | L100: 2023-10-29 | M100: =IF(TRIM(C100)="","Missing",IF(AND(LEN(TRIM(C100))=10,SUMPRODUCT(--(CODE(MID(TRIM(C100),{1,2,3,4,5,10},1))>=65),--(CODE(MID(TRIM(C100),{1,2,3,4,5,10},1))<=90))=6,ISNUMBER(--MID(TRIM(C100),6,4))),"Valid","Invalid")) -> Valid | N100: =IF(TRIM(D100)="","Missing",IF(AND(LEN(TRIM(D100))=15,MID(TRIM(D100),14,1)="Z"),IF(AND(TRIM(C100)<>"",MID(TRIM(D100),3,10)=TRIM(C100)),"Valid","PAN Mismatch"),"Invalid")) -> Valid | O100: =IF(TRIM(E100)="","Missing",IF(AND(ISNUMBER(FIND("@",E100)),ISERROR(FIND(" ",TRIM(E100))),IFERROR(FIND(".",E100,FIND("@",E100)),0)>0),"Valid","Invalid")) -> Valid | P100: =IF(TRIM(F100)="","Missing",IFERROR(IF(AND(ISNUMBER(--V100),OR(LEN(V100)=10,AND(LEN(V100)=12,LEFT(V100,2)="91")),VALUE(LEFT(RIGHT(V100,10),1))>=6),"Valid","Invalid"),"Invalid")) -> Valid | Q100: =IF(TRIM(G100)="","Missing",IFERROR(IF(AND(ISNUMBER(--TRIM(G100)),LEN(TRIM(G100))>=9,LEN(TRIM(G100))<=18,ISERROR(FIND(".",G100))),"Valid","Invalid"),"Invalid")) -> Valid | R100: =IF(TRIM(H100)="","Missing",IF(AND(LEN(TRIM(H100))=11,SUMPRODUCT(--(CODE(MID(TRIM(H100),{1,2,3,4},1))>=65),--(CODE(MID(TRIM(H100),{1,2,3,4},1))<=90))=4,MID(TRIM(H100),5,1)="0"),"Valid","Invalid")) -> Valid | S100: =IF(TRIM(I100)="","Missing",IF(EXACT(TRIM(I100),"India"),"Valid","Invalid")) -> Valid | T100: =IF(TRIM(J100)="","Missing",IF(OR(EXACT(TRIM(J100),"Net 15"),EXACT(TRIM(J100),"Net 30"),EXACT(TRIM(J100),"Net 45"),EXACT(TRIM(J100),"Net 60")),"Valid","Invalid")) -> Invalid | U100: =COUNTIF(M100:T100,"<>Valid") -> 1 | V100: =SUBSTITUTE(SUBSTITUTE(SUBSTITUTE(F100," ",""),"-",""),"+","") -> 8616484085 | W100: V1211 | X100: =IF(COUNTIF($W$2:$W$229,W100)>1,"Duplicate","Unique") -> Duplicate
...

Sheet Vendor_Master_Golden
A1: Vendor_ID | B1: Vendor_Name | C1: PAN | D1: GSTIN | E1: Email | F1: Phone | G1: Bank_Account | H1: IFSC | I1: Country | J1: Payment_Terms | K1: Status | L1: Created_Date | M1: PAN_Check | N1: GSTIN_Check | O1: Email_Check | P1: Phone_Check | Q1: Bank_Check | R1: IFSC_Check | S1: Country_Check | T1: Terms_Check | U1: Issue_Count | V1: Phone_Digits_(helper)
A2: V1001 | B2: Zenith Logistics Pvt Ltd | C2: YXWCG4657Q | E2: accounts@zenithlogistics.in | F2: +91 7150983930 | G2: 03105183473 | H2: KKBK0299737 | I2: India | J2: Net 60 | K2: Active | L2: 2020-02-02 | M2: =IF(TRIM(C2)="","Missing",IF(AND(LEN(TRIM(C2))=10,SUMPRODUCT(--(CODE(MID(TRIM(C2),{1,2,3,4,5,10},1))>=65),--(CODE(MID(TRIM(C2),{1,2,3,4,5,10},1))<=90))=6,ISNUMBER(--MID(TRIM(C2),6,4))),"Valid","Invalid")) -> Valid | N2: =IF(TRIM(D2)="","Missing",IF(AND(LEN(TRIM(D2))=15,MID(TRIM(D2),14,1)="Z"),IF(AND(TRIM(C2)<>"",MID(TRIM(D2),3,10)=TRIM(C2)),"Valid","PAN Mismatch"),"Invalid")) -> Missing | O2: =IF(TRIM(E2)="","Missing",IF(AND(ISNUMBER(FIND("@",E2)),ISERROR(FIND(" ",TRIM(E2))),IFERROR(FIND(".",E2,FIND("@",E2)),0)>0),"Valid","Invalid")) -> Valid | P2: =IF(TRIM(F2)="","Missing",IFERROR(IF(AND(ISNUMBER(--V2),OR(LEN(V2)=10,AND(LEN(V2)=12,LEFT(V2,2)="91")),VALUE(LEFT(RIGHT(V2,10),1))>=6),"Valid","Invalid"),"Invalid")) -> Valid | Q2: =IF(TRIM(G2)="","Missing",IFERROR(IF(AND(ISNUMBER(--TRIM(G2)),LEN(TRIM(G2))>=9,LEN(TRIM(G2))<=18,ISERROR(FIND(".",G2))),"Valid","Invalid"),"Invalid")) -> Valid | R2: =IF(TRIM(H2)="","Missing",IF(AND(LEN(TRIM(H2))=11,SUMPRODUCT(--(CODE(MID(TRIM(H2),{1,2,3,4},1))>=65),--(CODE(MID(TRIM(H2),{1,2,3,4},1))<=90))=4,MID(TRIM(H2),5,1)="0"),"Valid","Invalid")) -> Valid | S2: =IF(TRIM(I2)="","Missing",IF(EXACT(TRIM(I2),"India"),"Valid","Invalid")) -> Valid | T2: =IF(TRIM(J2)="","Missing",IF(OR(EXACT(TRIM(J2),"Net 15"),EXACT(TRIM(J2),"Net 30"),EXACT(TRIM(J2),"Net 45"),EXACT(TRIM(J2),"Net 60")),"Valid","Invalid")) -> Valid | U2: =COUNTIF(M2:T2,"<>Valid") -> 1 | V2: =SUBSTITUTE(SUBSTITUTE(SUBSTITUTE(F2," ",""),"-",""),"+","") -> 917150983930
A3: V1002 | B3: Evergreen Electricals Private Limited | C3: VNLCN6701B | D3: 07VNLCN6701B1ZV | E3: accounts@evergreenelectricals.in | F3: +91 7338726247 | G3: 178108013267 | H3: UTIB0360260 | I3: India | J3: Net 60 | K3: Active | L3: 2024-02-07 | M3: =IF(TRIM(C3)="","Missing",IF(AND(LEN(TRIM(C3))=10,SUMPRODUCT(--(CODE(MID(TRIM(C3),{1,2,3,4,5,10},1))>=65),--(CODE(MID(TRIM(C3),{1,2,3,4,5,10},1))<=90))=6,ISNUMBER(--MID(TRIM(C3),6,4))),"Valid","Invalid")) -> Valid | N3: =IF(TRIM(D3)="","Missing",IF(AND(LEN(TRIM(D3))=15,MID(TRIM(D3),14,1)="Z"),IF(AND(TRIM(C3)<>"",MID(TRIM(D3),3,10)=TRIM(C3)),"Valid","PAN Mismatch"),"Invalid")) -> Valid | O3: =IF(TRIM(E3)="","Missing",IF(AND(ISNUMBER(FIND("@",E3)),ISERROR(FIND(" ",TRIM(E3))),IFERROR(FIND(".",E3,FIND("@",E3)),0)>0),"Valid","Invalid")) -> Valid | P3: =IF(TRIM(F3)="","Missing",IFERROR(IF(AND(ISNUMBER(--V3),OR(LEN(V3)=10,AND(LEN(V3)=12,LEFT(V3,2)="91")),VALUE(LEFT(RIGHT(V3,10),1))>=6),"Valid","Invalid"),"Invalid")) -> Valid | Q3: =IF(TRIM(G3)="","Missing",IFERROR(IF(AND(ISNUMBER(--TRIM(G3)),LEN(TRIM(G3))>=9,LEN(TRIM(G3))<=18,ISERROR(FIND(".",G3))),"Valid","Invalid"),"Invalid")) -> Valid | R3: =IF(TRIM(H3)="","Missing",IF(AND(LEN(TRIM(H3))=11,SUMPRODUCT(--(CODE(MID(TRIM(H3),{1,2,3,4},1))>=65),--(CODE(MID(TRIM(H3),{1,2,3,4},1))<=90))=4,MID(TRIM(H3),5,1)="0"),"Valid","Invalid")) -> Valid | S3: =IF(TRIM(I3)="","Missing",IF(EXACT(TRIM(I3),"India"),"Valid","Invalid")) -> Valid | T3: =IF(TRIM(J3)="","Missing",IF(OR(EXACT(TRIM(J3),"Net 15"),EXACT(TRIM(J3),"Net 30"),EXACT(TRIM(J3),"Net 45"),EXACT(TRIM(J3),"Net 60")),"Valid","Invalid")) -> Valid | U3: =COUNTIF(M3:T3,"<>Valid") -> 0 | V3: =SUBSTITUTE(SUBSTITUTE(SUBSTITUTE(F3," ",""),"-",""),"+","") -> 917338726247
A4: V1003 | B4: Apex Pest Control Private Limited | C4: JNWCX8723J | D4: 29JNWCX8723J1ZD | E4: accounts@apexpestcontrol.in | F4: +91 8009788208 | G4: 21913619399 | H4: HDFC0916998 | I4: India | J4: Net 45 | K4: Active | L4: 2021-04-16 | M4: =IF(TRIM(C4)="","Missing",IF(AND(LEN(TRIM(C4))=10,SUMPRODUCT(--(CODE(MID(TRIM(C4),{1,2,3,4,5,10},1))>=65),--(CODE(MID(TRIM(C4),{1,2,3,4,5,10},1))<=90))=6,ISNUMBER(--MID(TRIM(C4),6,4))),"Valid","Invalid")) -> Valid | N4: =IF(TRIM(D4)="","Missing",IF(AND(LEN(TRIM(D4))=15,MID(TRIM(D4),14,1)="Z"),IF(AND(TRIM(C4)<>"",MID(TRIM(D4),3,10)=TRIM(C4)),"Valid","PAN Mismatch"),"Invalid")) -> Valid | O4: =IF(TRIM(E4)="","Missing",IF(AND(ISNUMBER(FIND("@",E4)),ISERROR(FIND(" ",TRIM(E4))),IFERROR(FIND(".",E4,FIND("@",E4)),0)>0),"Valid","Invalid")) -> Valid | P4: =IF(TRIM(F4)="","Missing",IFERROR(IF(AND(ISNUMBER(--V4),OR(LEN(V4)=10,AND(LEN(V4)=12,LEFT(V4,2)="91")),VALUE(LEFT(RIGHT(V4,10),1))>=6),"Valid","Invalid"),"Invalid")) -> Valid | Q4: =IF(TRIM(G4)="","Missing",IFERROR(IF(AND(ISNUMBER(--TRIM(G4)),LEN(TRIM(G4))>=9,LEN(TRIM(G4))<=18,ISERROR(FIND(".",G4))),"Valid","Invalid"),"Invalid")) -> Valid | R4: =IF(TRIM(H4)="","Missing",IF(AND(LEN(TRIM(H4))=11,SUMPRODUCT(--(CODE(MID(TRIM(H4),{1,2,3,4},1))>=65),--(CODE(MID(TRIM(H4),{1,2,3,4},1))<=90))=4,MID(TRIM(H4),5,1)="0"),"Valid","Invalid")) -> Valid | S4: =IF(TRIM(I4)="","Missing",IF(EXACT(TRIM(I4),"India"),"Valid","Invalid")) -> Valid | T4: =IF(TRIM(J4)="","Missing",IF(OR(EXACT(TRIM(J4),"Net 15"),EXACT(TRIM(J4),"Net 30"),EXACT(TRIM(J4),"Net 45"),EXACT(TRIM(J4),"Net 60")),"Valid","Invalid")) -> Valid | U4: =COUNTIF(M4:T4,"<>Valid") -> 0 | V4: =SUBSTITUTE(SUBSTITUTE(SUBSTITUTE(F4," ",""),"-",""),"+","") -> 918009788208
A5: V1004 | B5: Deccan Electricals Private Limited | D5: 33VWKCH4624O1ZE | E5: accounts@deccanelectricals.in | F5: +91 9991183842 | G5: 1354278498084 | H5: HDFC0241182 | I5: India | J5: Net 45 | K5: Active | L5: 2021-05-12 | M5: =IF(TRIM(C5)="","Missing",IF(AND(LEN(TRIM(C5))=10,SUMPRODUCT(--(CODE(MID(TRIM(C5),{1,2,3,4,5,10},1))>=65),--(CODE(MID(TRIM(C5),{1,2,3,4,5,10},1))<=90))=6,ISNUMBER(--MID(TRIM(C5),6,4))),"Valid","Invalid")) -> Missing | N5: =IF(TRIM(D5)="","Missing",IF(AND(LEN(TRIM(D5))=15,MID(TRIM(D5),14,1)="Z"),IF(AND(TRIM(C5)<>"",MID(TRIM(D5),3,10)=TRIM(C5)),"Valid","PAN Mismatch"),"Invalid")) -> PAN Mismatch | O5: =IF(TRIM(E5)="","Missing",IF(AND(ISNUMBER(FIND("@",E5)),ISERROR(FIND(" ",TRIM(E5))),IFERROR(FIND(".",E5,FIND("@",E5)),0)>0),"Valid","Invalid")) -> Valid | P5: =IF(TRIM(F5)="","Missing",IFERROR(IF(AND(ISNUMBER(--V5),OR(LEN(V5)=10,AND(LEN(V5)=12,LEFT(V5,2)="91")),VALUE(LEFT(RIGHT(V5,10),1))>=6),"Valid","Invalid"),"Invalid")) -> Valid | Q5: =IF(TRIM(G5)="","Missing",IFERROR(IF(AND(ISNUMBER(--TRIM(G5)),LEN(TRIM(G5))>=9,LEN(TRIM(G5))<=18,ISERROR(FIND(".",G5))),"Valid","Invalid"),"Invalid")) -> Valid | R5: =IF(TRIM(H5)="","Missing",IF(AND(LEN(TRIM(H5))=11,SUMPRODUCT(--(CODE(MID(TRIM(H5),{1,2,3,4},1))>=65),--(CODE(MID(TRIM(H5),{1,2,3,4},1))<=90))=4,MID(TRIM(H5),5,1)="0"),"Valid","Invalid")) -> Valid | S5: =IF(TRIM(I5)="","Missing",IF(EXACT(TRIM(I5),"India"),"Valid","Invalid")) -> Valid | T5: =IF(TRIM(J5)="","Missing",IF(OR(EXACT(TRIM(J5),"Net 15"),EXACT(TRIM(J5),"Net 30"),EXACT(TRIM(J5),"Net 45"),EXACT(TRIM(J5),"Net 60")),"Valid","Invalid")) -> Valid | U5: =COUNTIF(M5:T5,"<>Valid") -> 2 | V5: =SUBSTITUTE(SUBSTITUTE(SUBSTITUTE(F5," ",""),"-",""),"+","") -> 919991183842
